Workbook

Sheet Assumptions
B1: RealAI — Real Estate Investment Pro Forma
B2: Blue = Input | Black = Formula | Green = Cross-Tab Link
B4: PROPERTY OVERVIEW | G4: KEY METRICS
B5: Property Name | G5: T12 Cap Rate | H5: =IF(C15=0,0,H52/C15) -> 0
B6: Address | G6: Year 1 Cap Rate | H6: =IF(C15=0,0,'Pro Forma'!D$26/C15) -> 0
B7: City, State, Zip | G7: Yield on Cost | H7: =IF(C19=0,0,'Pro Forma'!D$26/C19) -> 0
B8: Property Type | G8: Unlevered IRR | H8: ='Returns Summary'!C$15 -> 0
B9: Unit Count | G9: Levered IRR | H9: ='Returns Summary'!C$21 -> 0
B10: Rentable Square Feet | G10: Avg Cash-on-Cash | H10: ='Returns Summary'!C$24 -> 0
B11: Year Built | G11: Equity Multiple | H11: ='Returns Summary'!C$22 -> 0
B12: Year Renovated
B14: ACQUISITION | G14: GROWTH & HOLD PERIOD
B15: Purchase Price | G15: Hold Period (Years)
B16: Price / Unit | C16: =IFERROR(C15/C9,0) -> 0 | G16: Rent Growth (%/yr)
B17: Price / SF | C17: =IFERROR(C15/C10,0) -> 0 | G17: Expense Growth (%/yr)
B18: Closing Costs (%) | G18: Other Income Growth
B19: Total Basis | C19: =C15*(1+C18)+C26+C33 -> 0 | G19: Stabilized Occupancy
B21: DISPOSITION | G21: YEAR-BY-YEAR OVERRIDES (OPTIONAL)
B22: Exit Cap Rate | G22: Use Staged Inputs | H22: No
B23: Disposition Costs (%) | G23: "No" = uses single Rent Growth, Occupancy, etc. from Growth section
G24: "Yes" = uses year-by-year values below (overrides single rates)
B25: CAPITAL EXPENDITURES | H25: Year 1 | I25: Year 2 | J25: Year 3 | K25: Year 4 | L25: Year 5 | M25: Year 6 | N25: Year 7 | O25: Year 8 | P25: Year 9 | Q25: Year 10
B26: Total CapEx Budget | G26: Rent Growth (%)
B27: CapEx / Unit | C27: =IFERROR(C26/C9,0) -> 0 | G27: Occupancy (%)
B28: Timing (1=Yr1 Lump, 0=Spread) | G28: Other Income Growth (%)
G29: Expense Growth (%)
B31: RESERVES | G31: T12 OPERATING STATEMENT (YEAR 0) | L31: OPERATING STATEMENT (YEAR 1)
B32: Reserves / Unit / Year | G32: Revenue | L32: Revenue
B33: Annual Reserves | C33: =C9*C32 -> 0 | G33: Gross Potential Rent (GPR) | L33: Gross Potential Rent (GPR) | M33: ='Pro Forma'!D6
G34: Less: Vacancy & Credit Loss | L34: Less: Vacancy & Credit Loss | M34: ='Pro Forma'!D8
B35: FINANCING — SENIOR DEBT | G35: Net Rental Income | H35: =H33+H34 -> 0 | L35: Net Rental Income | M35: =IFERROR(M33+M34,0) -> 0
B36: Loan Structure | C36: Interest Only | G36: Implied Occupancy | H36: =IF(H33=0,0,1+H34/H33) -> 0 | L36: Implied Occupancy | M36: =IFERROR(IF(M33=0,0,1+M34/M33),0) -> 0
B37: Loan Code | C37: =IF(C36="Interest Only",1,IF(C36="Fully Amortizing",2,3)) -> 1 | G37: Other Income | L37: Other Income | M37: ='Pro Forma'!D10
B38: LTV (%) | G38: Effective Gross Income (EGI) | H38: =H35+H37 -> 0 | L38: Effective Gross Income (EGI) | M38: =IFERROR(M35+M37,0) -> 0
B39: Loan Amount | C39: =C15*C38 -> 0
B40: Interest Rate | G40: Operating Expenses | H40: $/Year | I40: Per Unit | J40: % of EGI | L40: Operating Expenses | M40: $/Year | N40: Per Unit | O40: % of EGI
B41: IO Period (Years) | G41: Real Estate Taxes | I41: =IF(H41=0,0,H41/$C$9) -> 0 | J41: =IF(H41=0,0,H41/$H$38) -> 0 | L41: Real Estate Taxes | M41: ='Pro Forma'!D14 | N41: =IFERROR(IF(M41=0,0,M41/$C$9),0) -> 0 | O41: =IFERROR(IF(M41=0,0,M41/$H$38),0) -> 0
B42: Amortization (Years) | G42: Insurance | I42: =IF(H42=0,0,H42/$C$9) -> 0 | J42: =IF(H42=0,0,H42/$H$38) -> 0 | L42: Insurance | M42: ='Pro Forma'!D15 | N42: =IFERROR(IF(M42=0,0,M42/$C$9),0) -> 0 | O42: =IFERROR(IF(M42=0,0,M42/$H$38),0) -> 0
B43: Loan Term (Years) | G43: Utilities | I43: =IF(H43=0,0,H43/$C$9) -> 0 | J43: =IF(H43=0,0,H43/$H$38) -> 0 | L43: Utilities | M43: ='Pro Forma'!D16 | N43: =IFERROR(IF(M43=0,0,M43/$C$9),0) -> 0 | O43: =IFERROR(IF(M43=0,0,M43/$H$38),0) -> 0
G44: Repairs & Maintenance | I44: =IF(H44=0,0,H44/$C$9) -> 0 | J44: =IF(H44=0,0,H44/$H$38) -> 0 | L44: Repairs & Maintenance | M44: ='Pro Forma'!D17 | N44: =IFERROR(IF(M44=0,0,M44/$C$9),0) -> 0 | O44: =IFERROR(IF(M44=0,0,M44/$H$38),0) -> 0
B45: Debt Service | G45: Management Fees | I45: =IF(H45=0,0,H45/$C$9) -> 0 | J45: =IF(H45=0,0,H45/$H$38) -> 0 | L45: Management Fees | M45: ='Pro Forma'!D18 | N45: =IFERROR(IF(M45=0,0,M45/$C$9),0) -> 0 | O45: =IFERROR(IF(M45=0,0,M45/$H$38),0) -> 0
B46: IO Annual Payment | C46: =C39*C40 -> 0 | G46: Payroll & Benefits | I46: =IF(H46=0,0,H46/$C$9) -> 0 | J46: =IF(H46=0,0,H46/$H$38) -> 0 | L46: Payroll & Benefits | M46: ='Pro Forma'!D19 | N46: =IFERROR(IF(M46=0,0,M46/$C$9),0) -> 0 | O46: =IFERROR(IF(M46=0,0,M46/$H$38),0) -> 0
B47: Amortizing Annual Payment | C47: =IF(C42=0,0,-PMT(C40/12,C42*12,C39)*12) -> 0 | G47: General & Administrative | I47: =IF(H47=0,0,H47/$C$9) -> 0 | J47: =IF(H47=0,0,H47/$H$38) -> 0 | L47: General & Administrative | M47: ='Pro Forma'!D20 | N47: =IFERROR(IF(M47=0,0,M47/$C$9),0) -> 0 | O47: =IFERROR(IF(M47=0,0,M47/$H$38),0) -> 0
G48: Advertising & Marketing | I48: =IF(H48=0,0,H48/$C$9) -> 0 | J48: =IF(H48=0,0,H48/$H$38) -> 0 | L48: Advertising & Marketing | M48: ='Pro Forma'!D21 | N48: =IFERROR(IF(M48=0,0,M48/$C$9),0) -> 0 | O48: =IFERROR(IF(M48=0,0,M48/$H$38),0) -> 0
B49: DEBT METRICS | G49: Other Expenses | I49: =IF(H49=0,0,H49/$C$9) -> 0 | J49: =IF(H49=0,0,H49/$H$38) -> 0 | L49: Other Expenses | M49: ='Pro Forma'!D22 | N49: =IFERROR(IF(M49=0,0,M49/$C$9),0) -> 0 | O49: =IFERROR(IF(M49=0,0,M49/$H$38),0) -> 0
B50: ="Going-In DSCR ("&IF(Assumptions!$C$37=1,"IO",IF(Assumptions!$C$37=2,"Amort",IF(1<=Assumptions!$C$41,"IO","Amort")))&")" -> Going-In DSCR (IO) | C50: =IFERROR(IF('Pro Forma'!D$34=0,0,'Pro Forma'!D$26/'Pro Forma'!D$34),0) -> 0 | G50: Total Operating Expenses | H50: =SUM(H41:H49) -> 0 | I50: =IF(H50=0,0,H50/$C$9) -> 0 | J50: =IF(H50=0,0,H50/$H$38) -> 0 | L50: Total Operating Expenses | M50: =SUM(M41:M49) -> 0 | N50: =IF(M50=0,0,M50/$C$9) -> 0 | O50: =IF(M50=0,0,M50/$H$38) -> 0
B51: Debt Yield | C51: =IF(C39=0,0,H52/C39) -> 0
B52: Breakeven Occupancy | C52: =IF(H33=0,0,(H50+C68)/H33) -> 0 | G52: Net Operating Income (NOI) | H52: =H38-H50 -> 0 | I52: =IF(H52=0,0,H52/$C$9) -> 0 | J52: =IF(H52=0,0,H52/$H$38) -> 0 | L52: Net Operating Income (NOI) | M52: =M38-M50 -> 0 | N52: =IF(M52=0,0,M52/$C$9) -> 0 | O52: =IF(M52=0,0,M52/$H$38) -> 0
G53: Less: Replacement Reserves | H53: =C9*C32 -> 0 | I53: =IF(H53=0,0,H53/$C$9) -> 0 | J53: =IF($H$38=0,0,H53/$H$38) -> 0 | L53: Less: Replacement Reserves | M53: ='Pro Forma'!D36 | N53: =IFERROR(IF(M53=0,0,M53/$C$9),0) -> 0 | O53: =IF($H$38=0,0,M53/$H$38) -> 0
B54: FINANCING — MEZZANINE (OPTIONAL) | G54: Net Cash Flow (NCF) | H54: =H52-H53 -> 0 | I54: =IF(H54=0,0,H54/$C$9) -> 0 | J54: =IF($H$38=0,0,H54/$H$38) -> 0 | L54: Net Cash Flow (NCF) | M54: =IFERROR(M52-M53,0) -> 0 | N54: =IF(M54=0,0,M54/$C$9) -> 0 | O54: =IF($H$38=0,0,M54/$H$38) -> 0
B55: Mezz Enabled (1=Yes, 0=No) | C55: 0
B56: Mezz LTV (Incremental) | G56: Per-Unit / Per-SF Metrics | L56: Per-Unit / Per-SF Metrics
B57: Mezz Rate | G57: NOI / Unit | H57: =IF(C9=0,0,H52/C9) -> 0 | L57: NOI / Unit | M57: =IF(C9=0,0,M52/C9) -> 0
B58: Mezz Annual Payment | C58: =C55*C15*C56*C57 -> 0 | G58: NOI / SF | H58: =IF(C10=0,0,H52/C10) -> 0 | L58: NOI / SF | M58: =IF(C10=0,0,M52/C10) -> 0
G59: EGI / Unit | H59: =IF(C9=0,0,H38/C9) -> 0 | L59: EGI / Unit | M59: =IF(C9=0,0,M38/C9) -> 0
B60: CAPITAL STRUCTURE | C60: Total | D60: Per Unit | E60: % of Total | G60: OpEx Ratio | H60: =IF(H38=0,0,H50/H38) -> 0 | L60: OpEx Ratio | M60: =IFERROR(IF(M38=0,0,M50/M38),0) -> 0
B61: Senior Debt | C61: =C39 -> 0 | D61: =IF(C61=0,0,C61/$C$9) -> 0 | E61: =IF(C19=0,0,C61/C19) -> 0 | G61: In-Place Rent / Unit / Mo | H61: =IF(C9=0,0,H33/C9/12) -> 0 | L61: In-Place Rent / Unit / Mo | M61: =IF(C9=0,0,M35/C9/12) -> 0
B62: Mezzanine Debt | C62: =C55*C15*C56 -> 0 | D62: =IF(C62=0,0,C62/$C$9) -> 0 | E62: =IF(C19=0,0,C62/C19) -> 0
B63: Total Debt | C63: =C61+C62 -> 0 | D63: =IF(C63=0,0,C63/$C$9) -> 0 | E63: =IF(C19=0,0,C63/C19) -> 0
B64: Total Equity Required | C64: =C19-C63 -> 0 | D64: =IF(C64=0,0,C64/$C$9) -> 0 | E64: =IF(C19=0,0,C64/C19) -> 0
B65: Total Capitalization | C65: =C19 -> 0 | D65: =IF(C65=0,0,C65/$C$9) -> 0 | E65: =IF(C19=0,0,1) -> 0
B66: Combined LTV | C66: =IF(C15=0,0,C63/C15) -> 0
B67: Blended Cost of Debt | C67: =IF(C63=0,0,(C61*C40+C62*C57)/C63) -> 0
B68: Annual DS (IO Phase) | C68: =C46+C58 -> 0
B69: Annual DS (Amort Phase) | C69: =C47+C58 -> 0
B70: Equity at Close (Day-One) | C70: =C15*(1+C18)-C63 -> 0
B72: GP / LP WATERFALL STRUCTURE
B73: Co-Invest / Promote Structure | C73: No
B74: If "No", waterfall is bypassed (100% to equity holder)
B75: GP Co-Invest %
B76: LP Equity % | C76: =1-C75 -> 1
B77: GP Equity ($) | C77: =IF(C73="Yes",C64*C75,0) -> 0
B78: LP Equity ($) | C78: =IF(C73="Yes",C64*C76,C64) -> 0
B79: Tier 1: Preferred Return
B80: Tier 2: Hurdle IRR
B81: Tier 2: GP Promote %
B82: Tier 3: Hurdle IRR
B83: Tier 3: GP Promote %
B84: Tier 4: GP Promote % (Residual)

Sheet Pro Forma
B1: Operating Pro Forma
B2: Years beyond hold period are blank by design
B3: Year # | D3: =C3+1 -> 1 | E3: =D3+1 -> 2 | F3: =E3+1 -> 3 | G3: =F3+1 -> 4 | H3: =G3+1 -> 5 | I3: =H3+1 -> 6 | J3: =I3+1 -> 7 | K3: =J3+1 -> 8 | ... M3: =L3+1 -> 10
C4: Year 0 (T12) | D4: Year 1 | E4: Year 2 | F4: Year 3 | G4: Year 4 | H4: Year 5 | I4: Year 6 | J4: Year 7 | K4: Year 8 | L4: Year 9 | M4: Year 10
B5: REVENUE
B6: Gross Potential Rent | C6: =Assumptions!$H$33 -> 0 | D6: =IF(D$3>Assumptions!$H$15,"",C6*(1+IF(Assumptions!$H$22="Yes",Assumptions!$H$26,Assumptions!$H$16))) | E6: =IF(E$3>Assumptions!$H$15,"",D6*(1+IF(Assumptions!$H$22="Yes",Assumptions!$I$26,Assumptions!$H$16))) | F6: =IF(F$3>Assumptions!$H$15,"",E6*(1+IF(Assumptions!$H$22="Yes",Assumptions!$J$26,Assumptions!$H$16))) | G6: =IF(G$3>Assumptions!$H$15,"",F6*(1+IF(Assumptions!$H$22="Yes",Assumptions!$K$26,Assumptions!$H$16))) | H6: =IF(H$3>Assumptions!$H$15,"",G6*(1+IF(Assumptions!$H$22="Yes",Assumptions!$L$26,Assumptions!$H$16))) | I6: =IF(I$3>Assumptions!$H$15,"",H6*(1+IF(Assumptions!$H$22="Yes",Assumptions!$M$26,Assumptions!$H$16))) | J6: =IF(J$3>Assumptions!$H$15,"",I6*(1+IF(Assumptions!$H$22="Yes",Assumptions!$N$26,Assumptions!$H$16))) | K6: =IF(K$3>Assumptions!$H$15,"",J6*(1+IF(Assumptions!$H$22="Yes",Assumptions!$O$26,Assumptions!$H$16))) | L6: =IF(L$3>Assumptions!$H$15,"",K6*(1+IF(Assumptions!$H$22="Yes",Assumptions!$P$26,Assumptions!$H$16))) | M6: =IF(M$3>Assumptions!$H$15,"",L6*(1+IF(Assumptions!$H$22="Yes",Assumptions!$Q$26,Assumptions!$H$16)))
B7: GPR Growth (YoY) | C7: — | D7: =IF(D$3>Assumptions!$H$15,"",IF(C6=0,"",(D6-C6)/C6)) | E7: =IF(E$3>Assumptions!$H$15,"",IF(D6=0,"",(E6-D6)/D6)) | F7: =IF(F$3>Assumptions!$H$15,"",IF(E6=0,"",(F6-E6)/E6)) | G7: =IF(G$3>Assumptions!$H$15,"",IF(F6=0,"",(G6-F6)/F6)) | H7: =IF(H$3>Assumptions!$H$15,"",IF(G6=0,"",(H6-G6)/G6)) | I7: =IF(I$3>Assumptions!$H$15,"",IF(H6=0,"",(I6-H6)/H6)) | J7: =IF(J$3>Assumptions!$H$15,"",IF(I6=0,"",(J6-I6)/I6)) | K7: =IF(K$3>Assumptions!$H$15,"",IF(J6=0,"",(K6-J6)/J6)) | ... M7: =IF(M$3>Assumptions!$H$15,"",IF(L6=0,"",(M6-L6)/L6))
B8: Less: Vacancy & Credit Loss | C8: =Assumptions!$H$34 -> 0 | D8: =IF(D$3>Assumptions!$H$15,"",-D6*(1-IF(Assumptions!$H$22="Yes",Assumptions!$H$27,Assumptions!$H$19))) | E8: =IF(E$3>Assumptions!$H$15,"",-E6*(1-IF(Assumptions!$H$22="Yes",Assumptions!$I$27,Assumptions!$H$19))) | F8: =IF(F$3>Assumptions!$H$15,"",-F6*(1-IF(Assumptions!$H$22="Yes",Assumptions!$J$27,Assumptions!$H$19))) | G8: =IF(G$3>Assumptions!$H$15,"",-G6*(1-IF(Assumptions!$H$22="Yes",Assumptions!$K$27,Assumptions!$H$19))) | H8: =IF(H$3>Assumptions!$H$15,"",-H6*(1-IF(Assumptions!$H$22="Yes",Assumptions!$L$27,Assumptions!$H$19))) | I8: =IF(I$3>Assumptions!$H$15,"",-I6*(1-IF(Assumptions!$H$22="Yes",Assumptions!$M$27,Assumptions!$H$19))) | J8: =IF(J$3>Assumptions!$H$15,"",-J6*(1-IF(Assumptions!$H$22="Yes",Assumptions!$N$27,Assumptions!$H$19))) | K8: =IF(K$3>Assumptions!$H$15,"",-K6*(1-IF(Assumptions!$H$22="Yes",Assumptions!$O$27,Assumptions!$H$19))) | L8: =IF(L$3>Assumptions!$H$15,"",-L6*(1-IF(Assumptions!$H$22="Yes",Assumptions!$P$27,Assumptions!$H$19))) | M8: =IF(M$3>Assumptions!$H$15,"",-M6*(1-IF(Assumptions!$H$22="Yes",Assumptions!$Q$27,Assumptions!$H$19)))
B9: Net Rental Income | C9: =C6+C8 -> 0 | D9: =IF(D$3>Assumptions!$H$15,"",D6+D8) | E9: =IF(E$3>Assumptions!$H$15,"",E6+E8) | F9: =IF(F$3>Assumptions!$H$15,"",F6+F8) | G9: =IF(G$3>Assumptions!$H$15,"",G6+G8) | H9: =IF(H$3>Assumptions!$H$15,"",H6+H8) | I9: =IF(I$3>Assumptions!$H$15,"",I6+I8) | J9: =IF(J$3>Assumptions!$H$15,"",J6+J8) | K9: =IF(K$3>Assumptions!$H$15,"",K6+K8) | ... M9: =IF(M$3>Assumptions!$H$15,"",M6+M8)
B10: Other Income | C10: =Assumptions!$H$37 -> 0 | D10: =IF(D$3>Assumptions!$H$15,"",C10*(1+IF(Assumptions!$H$22="Yes",Assumptions!$H$28,Assumptions!$H$18))) | E10: =IF(E$3>Assumptions!$H$15,"",D10*(1+IF(Assumptions!$H$22="Yes",Assumptions!$I$28,Assumptions!$H$18))) | F10: =IF(F$3>Assumptions!$H$15,"",E10*(1+IF(Assumptions!$H$22="Yes",Assumptions!$J$28,Assumptions!$H$18))) | G10: =IF(G$3>Assumptions!$H$15,"",F10*(1+IF(Assumptions!$H$22="Yes",Assumptions!$K$28,Assumptions!$H$18))) | H10: =IF(H$3>Assumptions!$H$15,"",G10*(1+IF(Assumptions!$H$22="Yes",Assumptions!$L$28,Assumptions!$H$18))) | I10: =IF(I$3>Assumptions!$H$15,"",H10*(1+IF(Assumptions!$H$22="Yes",Assumptions!$M$28,Assumptions!$H$18))) | J10: =IF(J$3>Assumptions!$H$15,"",I10*(1+IF(Assumptions!$H$22="Yes",Assumptions!$N$28,Assumptions!$H$18))) | K10: =IF(K$3>Assumptions!$H$15,"",J10*(1+IF(Assumptions!$H$22="Yes",Assumptions!$O$28,Assumptions!$H$18))) | L10: =IF(L$3>Assumptions!$H$15,"",K10*(1+IF(Assumptions!$H$22="Yes",Assumptions!$P$28,Assumptions!$H$18))) | M10: =IF(M$3>Assumptions!$H$15,"",L10*(1+IF(Assumptions!$H$22="Yes",Assumptions!$Q$28,Assumptions!$H$18)))
B11: Effective Gross Income | C11: =C9+C10 -> 0 | D11: =IF(D$3>Assumptions!$H$15,"",D9+D10) | E11: =IF(E$3>Assumptions!$H$15,"",E9+E10) | F11: =IF(F$3>Assumptions!$H$15,"",F9+F10) | G11: =IF(G$3>Assumptions!$H$15,"",G9+G10) | H11: =IF(H$3>Assumptions!$H$15,"",H9+H10) | I11: =IF(I$3>Assumptions!$H$15,"",I9+I10) | J11: =IF(J$3>Assumptions!$H$15,"",J9+J10) | K11: =IF(K$3>Assumptions!$H$15,"",K9+K10) | ... M11: =IF(M$3>Assumptions!$H$15,"",M9+M10)
B13: OPERATING EXPENSES
B14: Real Estate Taxes | C14: =Assumptions!$H$41 -> 0 | D14: =IF(D$3>Assumptions!$H$15,"",C14*(1+IF(Assumptions!$H$22="Yes",Assumptions!$H$29,Assumptions!$H$17))) | E14: =IF(E$3>Assumptions!$H$15,"",D14*(1+IF(Assumptions!$H$22="Yes",Assumptions!$I$29,Assumptions!$H$17))) | F14: =IF(F$3>Assumptions!$H$15,"",E14*(1+IF(Assumptions!$H$22="Yes",Assumptions!$J$29,Assumptions!$H$17))) | G14: =IF(G$3>Assumptions!$H$15,"",F14*(1+IF(Assumptions!$H$22="Yes",Assumptions!$K$29,Assumptions!$H$17))) | H14: =IF(H$3>Assumptions!$H$15,"",G14*(1+IF(Assumptions!$H$22="Yes",Assumptions!$L$29,Assumptions!$H$17))) | I14: =IF(I$3>Assumptions!$H$15,"",H14*(1+IF(Assumptions!$H$22="Yes",Assumptions!$M$29,Assumptions!$H$17))) | J14: =IF(J$3>Assumptions!$H$15,"",I14*(1+IF(Assumptions!$H$22="Yes",Assumptions!$N$29,Assumptions!$H$17))) | K14: =IF(K$3>Assumptions!$H$15,"",J14*(1+IF(Assumptions!$H$22="Yes",Assumptions!$O$29,Assumptions!$H$17))) | L14: =IF(L$3>Assumptions!$H$15,"",K14*(1+IF(Assumptions!$H$22="Yes",Assumptions!$P$29,Assumptions!$H$17))) | M14: =IF(M$3>Assumptions!$H$15,"",L14*(1+IF(Assumptions!$H$22="Yes",Assumptions!$Q$29,Assumptions!$H$17)))
B15: Insurance | C15: =Assumptions!$H$42 -> 0 | D15: =IF(D$3>Assumptions!$H$15,"",C15*(1+IF(Assumptions!$H$22="Yes",Assumptions!$H$29,Assumptions!$H$17))) | E15: =IF(E$3>Assumptions!$H$15,"",D15*(1+IF(Assumptions!$H$22="Yes",Assumptions!$I$29,Assumptions!$H$17))) | F15: =IF(F$3>Assumptions!$H$15,"",E15*(1+IF(Assumptions!$H$22="Yes",Assumptions!$J$29,Assumptions!$H$17))) | G15: =IF(G$3>Assumptions!$H$15,"",F15*(1+IF(Assumptions!$H$22="Yes",Assumptions!$K$29,Assumptions!$H$17))) | H15: =IF(H$3>Assumptions!$H$15,"",G15*(1+IF(Assumptions!$H$22="Yes",Assumptions!$L$29,Assumptions!$H$17))) | I15: =IF(I$3>Assumptions!$H$15,"",H15*(1+IF(Assumptions!$H$22="Yes",Assumptions!$M$29,Assumptions!$H$17))) | J15: =IF(J$3>Assumptions!$H$15,"",I15*(1+IF(Assumptions!$H$22="Yes",Assumptions!$N$29,Assumptions!$H$17))) | K15: =IF(K$3>Assumptions!$H$15,"",J15*(1+IF(Assumptions!$H$22="Yes",Assumptions!$O$29,Assumptions!$H$17))) | L15: =IF(L$3>Assumptions!$H$15,"",K15*(1+IF(Assumptions!$H$22="Yes",Assumptions!$P$29,Assumptions!$H$17))) | M15: =IF(M$3>Assumptions!$H$15,"",L15*(1+IF(Assumptions!$H$22="Yes",Assumptions!$Q$29,Assumptions!$H$17)))
B16: Utilities | C16: =Assumptions!$H$43 -> 0 | D16: =IF(D$3>Assumptions!$H$15,"",C16*(1+IF(Assumptions!$H$22="Yes",Assumptions!$H$29,Assumptions!$H$17))) | E16: =IF(E$3>Assumptions!$H$15,"",D16*(1+IF(Assumptions!$H$22="Yes",Assumptions!$I$29,Assumptions!$H$17))) | F16: =IF(F$3>Assumptions!$H$15,"",E16*(1+IF(Assumptions!$H$22="Yes",Assumptions!$J$29,Assumptions!$H$17))) | G16: =IF(G$3>Assumptions!$H$15,"",F16*(1+IF(Assumptions!$H$22="Yes",Assumptions!$K$29,Assumptions!$H$17))) | H16: =IF(H$3>Assumptions!$H$15,"",G16*(1+IF(Assumptions!$H$22="Yes",Assumptions!$L$29,Assumptions!$H$17))) | I16: =IF(I$3>Assumptions!$H$15,"",H16*(1+IF(Assumptions!$H$22="Yes",Assumptions!$M$29,Assumptions!$H$17))) | J16: =IF(J$3>Assumptions!$H$15,"",I16*(1+IF(Assumptions!$H$22="Yes",Assumptions!$N$29,Assumptions!$H$17))) | K16: =IF(K$3>Assumptions!$H$15,"",J16*(1+IF(Assumptions!$H$22="Yes",Assumptions!$O$29,Assumptions!$H$17))) | L16: =IF(L$3>Assumptions!$H$15,"",K16*(1+IF(Assumptions!$H$22="Yes",Assumptions!$P$29,Assumptions!$H$17))) | M16: =IF(M$3>Assumptions!$H$15,"",L16*(1+IF(Assumptions!$H$22="Yes",Assumptions!$Q$29,Assumptions!$H$17)))
B17: Repairs & Maintenance | C17: =Assumptions!$H$44 -> 0 | D17: =IF(D$3>Assumptions!$H$15,"",C17*(1+IF(Assumptions!$H$22="Yes",Assumptions!$H$29,Assumptions!$H$17))) | E17: =IF(E$3>Assumptions!$H$15,"",D17*(1+IF(Assumptions!$H$22="Yes",Assumptions!$I$29,Assumptions!$H$17))) | F17: =IF(F$3>Assumptions!$H$15,"",E17*(1+IF(Assumptions!$H$22="Yes",Assumptions!$J$29,Assumptions!$H$17))) | G17: =IF(G$3>Assumptions!$H$15,"",F17*(1+IF(Assumptions!$H$22="Yes",Assumptions!$K$29,Assumptions!$H$17))) | H17: =IF(H$3>Assumptions!$H$15,"",G17*(1+IF(Assumptions!$H$22="Yes",Assumptions!$L$29,Assumptions!$H$17))) | I17: =IF(I$3>Assumptions!$H$15,"",H17*(1+IF(Assumptions!$H$22="Yes",Assumptions!$M$29,Assumptions!$H$17))) | J17: =IF(J$3>Assumptions!$H$15,"",I17*(1+IF(Assumptions!$H$22="Yes",Assumptions!$N$29,Assumptions!$H$17))) | K17: =IF(K$3>Assumptions!$H$15,"",J17*(1+IF(Assumptions!$H$22="Yes",Assumptions!$O$29,Assumptions!$H$17))) | L17: =IF(L$3>Assumptions!$H$15,"",K17*(1+IF(Assumptions!$H$22="Yes",Assumptions!$P$29,Assumptions!$H$17))) | M17: =IF(M$3>Assumptions!$H$15,"",L17*(1+IF(Assumptions!$H$22="Yes",Assumptions!$Q$29,Assumptions!$H$17)))
B18: Management Fees | C18: =Assumptions!$H$45 -> 0 | D18: =IF(D$3>Assumptions!$H$15,"",C18*(1+IF(Assumptions!$H$22="Yes",Assumptions!$H$29,Assumptions!$H$17))) | E18: =IF(E$3>Assumptions!$H$15,"",D18*(1+IF(Assumptions!$H$22="Yes",Assumptions!$I$29,Assumptions!$H$17))) | F18: =IF(F$3>Assumptions!$H$15,"",E18*(1+IF(Assumptions!$H$22="Yes",Assumptions!$J$29,Assumptions!$H$17))) | G18: =IF(G$3>Assumptions!$H$15,"",F18*(1+IF(Assumptions!$H$22="Yes",Assumptions!$K$29,Assumptions!$H$17))) | H18: =IF(H$3>Assumptions!$H$15,"",G18*(1+IF(Assumptions!$H$22="Yes",Assumptions!$L$29,Assumptions!$H$17))) | I18: =IF(I$3>Assumptions!$H$15,"",H18*(1+IF(Assumptions!$H$22="Yes",Assumptions!$M$29,Assumptions!$H$17))) | J18: =IF(J$3>Assumptions!$H$15,"",I18*(1+IF(Assumptions!$H$22="Yes",Assumptions!$N$29,Assumptions!$H$17))) | K18: =IF(K$3>Assumptions!$H$15,"",J18*(1+IF(Assumptions!$H$22="Yes",Assumptions!$O$29,Assumptions!$H$17))) | L18: =IF(L$3>Assumptions!$H$15,"",K18*(1+IF(Assumptions!$H$22="Yes",Assumptions!$P$29,Assumptions!$H$17))) | M18: =IF(M$3>Assumptions!$H$15,"",L18*(1+IF(Assumptions!$H$22="Yes",Assumptions!$Q$29,Assumptions!$H$17)))
B19: Payroll & Benefits | C19: =Assumptions!$H$46 -> 0 | D19: =IF(D$3>Assumptions!$H$15,"",C19*(1+IF(Assumptions!$H$22="Yes",Assumptions!$H$29,Assumptions!$H$17))) | E19: =IF(E$3>Assumptions!$H$15,"",D19*(1+IF(Assumptions!$H$22="Yes",Assumptions!$I$29,Assumptions!$H$17))) | F19: =IF(F$3>Assumptions!$H$15,"",E19*(1+IF(Assumptions!$H$22="Yes",Assumptions!$J$29,Assumptions!$H$17))) | G19: =IF(G$3>Assumptions!$H$15,"",F19*(1+IF(Assumptions!$H$22="Yes",Assumptions!$K$29,Assumptions!$H$17))) | H19: =IF(H$3>Assumptions!$H$15,"",G19*(1+IF(Assumptions!$H$22="Yes",Assumptions!$L$29,Assumptions!$H$17))) | I19: =IF(I$3>Assumptions!$H$15,"",H19*(1+IF(Assumptions!$H$22="Yes",Assumptions!$M$29,Assumptions!$H$17))) | J19: =IF(J$3>Assumptions!$H$15,"",I19*(1+IF(Assumptions!$H$22="Yes",Assumptions!$N$29,Assumptions!$H$17))) | K19: =IF(K$3>Assumptions!$H$15,"",J19*(1+IF(Assumptions!$H$22="Yes",Assumptions!$O$29,Assumptions!$H$17))) | L19: =IF(L$3>Assumptions!$H$15,"",K19*(1+IF(Assumptions!$H$22="Yes",Assumptions!$P$29,Assumptions!$H$17))) | M19: =IF(M$3>Assumptions!$H$15,"",L19*(1+IF(Assumptions!$H$22="Yes",Assumptions!$Q$29,Assumptions!$H$17)))
B20: General & Administrative | C20: =Assumptions!$H$47 -> 0 | D20: =IF(D$3>Assumptions!$H$15,"",C20*(1+IF(Assumptions!$H$22="Yes",Assumptions!$H$29,Assumptions!$H$17))) | E20: =IF(E$3>Assumptions!$H$15,"",D20*(1+IF(Assumptions!$H$22="Yes",Assumptions!$I$29,Assumptions!$H$17))) | F20: =IF(F$3>Assumptions!$H$15,"",E20*(1+IF(Assumptions!$H$22="Yes",Assumptions!$J$29,Assumptions!$H$17))) | G20: =IF(G$3>Assumptions!$H$15,"",F20*(1+IF(Assumptions!$H$22="Yes",Assumptions!$K$29,Assumptions!$H$17))) | H20: =IF(H$3>Assumptions!$H$15,"",G20*(1+IF(Assumptions!$H$22="Yes",Assumptions!$L$29,Assumptions!$H$17))) | I20: =IF(I$3>Assumptions!$H$15,"",H20*(1+IF(Assumptions!$H$22="Yes",Assumptions!$M$29,Assumptions!$H$17))) | J20: =IF(J$3>Assumptions!$H$15,"",I20*(1+IF(Assumptions!$H$22="Yes",Assumptions!$N$29,Assumptions!$H$17))) | K20: =IF(K$3>Assumptions!$H$15,"",J20*(1+IF(Assumptions!$H$22="Yes",Assumptions!$O$29,Assumptions!$H$17))) | L20: =IF(L$3>Assumptions!$H$15,"",K20*(1+IF(Assumptions!$H$22="Yes",Assumptions!$P$29,Assumptions!$H$17))) | M20: =IF(M$3>Assumptions!$H$15,"",L20*(1+IF(Assumptions!$H$22="Yes",Assumptions!$Q$29,Assumptions!$H$17)))
B21: Advertising & Marketing | C21: =Assumptions!$H$48 -> 0 | D21: =IF(D$3>Assumptions!$H$15,"",C21*(1+IF(Assumptions!$H$22="Yes",Assumptions!$H$29,Assumptions!$H$17))) | E21: =IF(E$3>Assumptions!$H$15,"",D21*(1+IF(Assumptions!$H$22="Yes",Assumptions!$I$29,Assumptions!$H$17))) | F21: =IF(F$3>Assumptions!$H$15,"",E21*(1+IF(Assumptions!$H$22="Yes",Assumptions!$J$29,Assumptions!$H$17))) | G21: =IF(G$3>Assumptions!$H$15,"",F21*(1+IF(Assumptions!$H$22="Yes",Assumptions!$K$29,Assumptions!$H$17))) | H21: =IF(H$3>Assumptions!$H$15,"",G21*(1+IF(Assumptions!$H$22="Yes",Assumptions!$L$29,Assumptions!$H$17))) | I21: =IF(I$3>Assumptions!$H$15,"",H21*(1+IF(Assumptions!$H$22="Yes",Assumptions!$M$29,Assumptions!$H$17))) | J21: =IF(J$3>Assumptions!$H$15,"",I21*(1+IF(Assumptions!$H$22="Yes",Assumptions!$N$29,Assumptions!$H$17))) | K21: =IF(K$3>Assumptions!$H$15,"",J21*(1+IF(Assumptions!$H$22="Yes",Assumptions!$O$29,Assumptions!$H$17))) | L21: =IF(L$3>Assumptions!$H$15,"",K21*(1+IF(Assumptions!$H$22="Yes",Assumptions!$P$29,Assumptions!$H$17))) | M21: =IF(M$3>Assumptions!$H$15,"",L21*(1+IF(Assumptions!$H$22="Yes",Assumptions!$Q$29,Assumptions!$H$17)))
B22: Other Expenses | C22: =Assumptions!$H$49 -> 0 | D22: =IF(D$3>Assumptions!$H$15,"",C22*(1+IF(Assumptions!$H$22="Yes",Assumptions!$H$29,Assumptions!$H$17))) | E22: =IF(E$3>Assumptions!$H$15,"",D22*(1+IF(Assumptions!$H$22="Yes",Assumptions!$I$29,Assumptions!$H$17))) | F22: =IF(F$3>Assumptions!$H$15,"",E22*(1+IF(Assumptions!$H$22="Yes",Assumptions!$J$29,Assumptions!$H$17))) | G22: =IF(G$3>Assumptions!$H$15,"",F22*(1+IF(Assumptions!$H$22="Yes",Assumptions!$K$29,Assumptions!$H$17))) | H22: =IF(H$3>Assumptions!$H$15,"",G22*(1+IF(Assumptions!$H$22="Yes",Assumptions!$L$29,Assumptions!$H$17))) | I22: =IF(I$3>Assumptions!$H$15,"",H22*(1+IF(Assumptions!$H$22="Yes",Assumptions!$M$29,Assumptions!$H$17))) | J22: =IF(J$3>Assumptions!$H$15,"",I22*(1+IF(Assumptions!$H$22="Yes",Assumptions!$N$29,Assumptions!$H$17))) | K22: =IF(K$3>Assumptions!$H$15,"",J22*(1+IF(Assumptions!$H$22="Yes",Assumptions!$O$29,Assumptions!$H$17))) | L22: =IF(L$3>Assumptions!$H$15,"",K22*(1+IF(Assumptions!$H$22="Yes",Assumptions!$P$29,Assumptions!$H$17))) | M22: =IF(M$3>Assumptions!$H$15,"",L22*(1+IF(Assumptions!$H$22="Yes",Assumptions!$Q$29,Assumptions!$H$17)))
B23: Total Operating Expenses | C23: =SUM(C14:C22) -> 0 | D23: =IF(D$3>Assumptions!$H$15,"",SUM(D14:D22)) | E23: =IF(E$3>Assumptions!$H$15,"",SUM(E14:E22)) | F23: =IF(F$3>Assumptions!$H$15,"",SUM(F14:F22)) | G23: =IF(G$3>Assumptions!$H$15,"",SUM(G14:G22)) | H23: =IF(H$3>Assumptions!$H$15,"",SUM(H14:H22)) | I23: =IF(I$3>Assumptions!$H$15,"",SUM(I14:I22)) | J23: =IF(J$3>Assumptions!$H$15,"",SUM(J14:J22)) | K23: =IF(K$3>Assumptions!$H$15,"",SUM(K14:K22)) | ... M23: =IF(M$3>Assumptions!$H$15,"",SUM(M14:M22))
B24: OpEx Growth (YoY) | C24: — | D24: =IF(D$3>Assumptions!$H$15,"",IF(C23=0,"",(D23-C23)/C23)) | E24: =IF(E$3>Assumptions!$H$15,"",IF(D23=0,"",(E23-D23)/D23)) | F24: =IF(F$3>Assumptions!$H$15,"",IF(E23=0,"",(F23-E23)/E23)) | G24: =IF(G$3>Assumptions!$H$15,"",IF(F23=0,"",(G23-F23)/F23)) | H24: =IF(H$3>Assumptions!$H$15,"",IF(G23=0,"",(H23-G23)/G23)) | I24: =IF(I$3>Assumptions!$H$15,"",IF(H23=0,"",(I23-H23)/H23)) | J24: =IF(J$3>Assumptions!$H$15,"",IF(I23=0,"",(J23-I23)/I23)) | K24: =IF(K$3>Assumptions!$H$15,"",IF(J23=0,"",(K23-J23)/J23)) | ... M24: =IF(M$3>Assumptions!$H$15,"",IF(L23=0,"",(M23-L23)/L23))
B25: OpEx Ratio | C25: =IF(C11=0,0,C23/C11) -> 0 | D25: =IF(D$3>Assumptions!$H$15,"",IF(D11=0,"",D23/D11)) | E25: =IF(E$3>Assumptions!$H$15,"",IF(E11=0,"",E23/E11)) | F25: =IF(F$3>Assumptions!$H$15,"",IF(F11=0,"",F23/F11)) | G25: =IF(G$3>Assumptions!$H$15,"",IF(G11=0,"",G23/G11)) | H25: =IF(H$3>Assumptions!$H$15,"",IF(H11=0,"",H23/H11)) | I25: =IF(I$3>Assumptions!$H$15,"",IF(I11=0,"",I23/I11)) | J25: =IF(J$3>Assumptions!$H$15,"",IF(J11=0,"",J23/J11)) | K25: =IF(K$3>Assumptions!$H$15,"",IF(K11=0,"",K23/K11)) | ... M25: =IF(M$3>Assumptions!$H$15,"",IF(M11=0,"",M23/M11))
B26: Net Operating Income (NOI) | C26: =C11-C23 -> 0 | D26: =IF(D$3>Assumptions!$H$15,"",D11-D23) | E26: =IF(E$3>Assumptions!$H$15,"",E11-E23) | F26: =IF(F$3>Assumptions!$H$15,"",F11-F23) | G26: =IF(G$3>Assumptions!$H$15,"",G11-G23) | H26: =IF(H$3>Assumptions!$H$15,"",H11-H23) | I26: =IF(I$3>Assumptions!$H$15,"",I11-I23) | J26: =IF(J$3>Assumptions!$H$15,"",J11-J23) | K26: =IF(K$3>Assumptions!$H$15,"",K11-K23) | ... M26: =IF(M$3>Assumptions!$H$15,"",M11-M23)
B27: NOI Growth (YoY) | C27: — | D27: =IF(D$3>Assumptions!$H$15,"",IF(C26=0,"",(D26-C26)/C26)) | E27: =IF(E$3>Assumptions!$H$15,"",IF(D26=0,"",(E26-D26)/D26)) | F27: =IF(F$3>Assumptions!$H$15,"",IF(E26=0,"",(F26-E26)/E26)) | G27: =IF(G$3>Assumptions!$H$15,"",IF(F26=0,"",(G26-F26)/F26)) | H27: =IF(H$3>Assumptions!$H$15,"",IF(G26=0,"",(H26-G26)/G26)) | I27: =IF(I$3>Assumptions!$H$15,"",IF(H26=0,"",(I26-H26)/H26)) | J27: =IF(J$3>Assumptions!$H$15,"",IF(I26=0,"",(J26-I26)/I26)) | K27: =IF(K$3>Assumptions!$H$15,"",IF(J26=0,"",(K26-J26)/J26)) | ... M27: =IF(M$3>Assumptions!$H$15,"",IF(L26=0,"",(M26-L26)/L26))
B28: NOI / Unit | C28: =IF(Assumptions!$C$9=0,0,C26/Assumptions!$C$9) -> 0 | D28: =IF(D$3>Assumptions!$H$15,"",D26/Assumptions!$C$9) | E28: =IF(E$3>Assumptions!$H$15,"",E26/Assumptions!$C$9) | F28: =IF(F$3>Assumptions!$H$15,"",F26/Assumptions!$C$9) | G28: =IF(G$3>Assumptions!$H$15,"",G26/Assumptions!$C$9) | H28: =IF(H$3>Assumptions!$H$15,"",H26/Assumptions!$C$9) | I28: =IF(I$3>Assumptions!$H$15,"",I26/Assumptions!$C$9) | J28: =IF(J$3>Assumptions!$H$15,"",J26/Assumptions!$C$9) | K28: =IF(K$3>Assumptions!$H$15,"",K26/Assumptions!$C$9) | ... M28: =IF(M$3>Assumptions!$H$15,"",M26/Assumptions!$C$9)
B30: Unlevered Cash Flow (NOI − CapEx − Reserves) | D30: =IF(D$3>Assumptions!$H$15,"",D26-D35-D36) | E30: =IF(E$3>Assumptions!$H$15,"",E26-E35-E36) | F30: =IF(F$3>Assumptions!$H$15,"",F26-F35-F36) | G30: =IF(G$3>Assumptions!$H$15,"",G26-G35-G36) | H30: =IF(H$3>Assumptions!$H$15,"",H26-H35-H36) | I30: =IF(I$3>Assumptions!$H$15,"",I26-I35-I36) | J30: =IF(J$3>Assumptions!$H$15,"",J26-J35-J36) | K30: =IF(K$3>Assumptions!$H$15,"",K26-K35-K36) | ... M30: =IF(M$3>Assumptions!$H$15,"",M26-M35-M36)
B31: BELOW THE LINE
B32: Senior Debt Service | D32: =IF(D$3>Assumptions!$H$15,"",IF(Assumptions!$C$37=1,Assumptions!$C$46,IF(Assumptions!$C$37=2,Assumptions!$C$47,IF(D$3<=Assumptions!$C$41,Assumptions!$C$46,Assumptions!$C$47)))) | E32: =IF(E$3>Assumptions!$H$15,"",IF(Assumptions!$C$37=1,Assumptions!$C$46,IF(Assumptions!$C$37=2,Assumptions!$C$47,IF(E$3<=Assumptions!$C$41,Assumptions!$C$46,Assumptions!$C$47)))) | F32: =IF(F$3>Assumptions!$H$15,"",IF(Assumptions!$C$37=1,Assumptions!$C$46,IF(Assumptions!$C$37=2,Assumptions!$C$47,IF(F$3<=Assumptions!$C$41,Assumptions!$C$46,Assumptions!$C$47)))) | G32: =IF(G$3>Assumptions!$H$15,"",IF(Assumptions!$C$37=1,Assumptions!$C$46,IF(Assumptions!$C$37=2,Assumptions!$C$47,IF(G$3<=Assumptions!$C$41,Assumptions!$C$46,Assumptions!$C$47)))) | H32: =IF(H$3>Assumptions!$H$15,"",IF(Assumptions!$C$37=1,Assumptions!$C$46,IF(Assumptions!$C$37=2,Assumptions!$C$47,IF(H$3<=Assumptions!$C$41,Assumptions!$C$46,Assumptions!$C$47)))) | I32: =IF(I$3>Assumptions!$H$15,"",IF(Assumptions!$C$37=1,Assumptions!$C$46,IF(Assumptions!$C$37=2,Assumptions!$C$47,IF(I$3<=Assumptions!$C$41,Assumptions!$C$46,Assumptions!$C$47)))) | J32: =IF(J$3>Assumptions!$H$15,"",IF(Assumptions!$C$37=1,Assumptions!$C$46,IF(Assumptions!$C$37=2,Assumptions!$C$47,IF(J$3<=Assumptions!$C$41,Assumptions!$C$46,Assumptions!$C$47)))) | K32: =IF(K$3>Assumptions!$H$15,"",IF(Assumptions!$C$37=1,Assumptions!$C$46,IF(Assumptions!$C$37=2,Assumptions!$C$47,IF(K$3<=Assumptions!$C$41,Assumptions!$C$46,Assumptions!$C$47)))) | ... M32: =IF(M$3>Assumptions!$H$15,"",IF(Assumptions!$C$37=1,Assumptions!$C$46,IF(Assumptions!$C$37=2,Assumptions!$C$47,IF(M$3<=Assumptions!$C$41,Assumptions!$C$46,Assumptions!$C$47))))
B33: Mezzanine Debt Service | D33: =IF(D$3>Assumptions!$H$15,"",Assumptions!$C$58) | E33: =IF(E$3>Assumptions!$H$15,"",Assumptions!$C$58) | F33: =IF(F$3>Assumptions!$H$15,"",Assumptions!$C$58) | G33: =IF(G$3>Assumptions!$H$15,"",Assumptions!$C$58) | H33: =IF(H$3>Assumptions!$H$15,"",Assumptions!$C$58) | I33: =IF(I$3>Assumptions!$H$15,"",Assumptions!$C$58) | J33: =IF(J$3>Assumptions!$H$15,"",Assumptions!$C$58) | K33: =IF(K$3>Assumptions!$H$15,"",Assumptions!$C$58) | ... M33: =IF(M$3>Assumptions!$H$15,"",Assumptions!$C$58)
B34: Total Debt Service | D34: =IF(D$3>Assumptions!$H$15,"",D32+D33) | E34: =IF(E$3>Assumptions!$H$15,"",E32+E33) | F34: =IF(F$3>Assumptions!$H$15,"",F32+F33) | G34: =IF(G$3>Assumptions!$H$15,"",G32+G33) | H34: =IF(H$3>Assumptions!$H$15,"",H32+H33) | I34: =IF(I$3>Assumptions!$H$15,"",I32+I33) | J34: =IF(J$3>Assumptions!$H$15,"",J32+J33) | K34: =IF(K$3>Assumptions!$H$15,"",K32+K33) | ... M34: =IF(M$3>Assumptions!$H$15,"",M32+M33)
B35: Capital Expenditures | D35: =IF(D$3>Assumptions!$H$15,"",IF(Assumptions!$C$28=1,IF(D$3=1,Assumptions!$C$26,0),Assumptions!$C$26/Assumptions!$H$15)) | E35: =IF(E$3>Assumptions!$H$15,"",IF(Assumptions!$C$28=1,IF(E$3=1,Assumptions!$C$26,0),Assumptions!$C$26/Assumptions!$H$15)) | F35: =IF(F$3>Assumptions!$H$15,"",IF(Assumptions!$C$28=1,IF(F$3=1,Assumptions!$C$26,0),Assumptions!$C$26/Assumptions!$H$15)) | G35: =IF(G$3>Assumptions!$H$15,"",IF(Assumptions!$C$28=1,IF(G$3=1,Assumptions!$C$26,0),Assumptions!$C$26/Assumptions!$H$15)) | H35: =IF(H$3>Assumptions!$H$15,"",IF(Assumptions!$C$28=1,IF(H$3=1,Assumptions!$C$26,0),Assumptions!$C$26/Assumptions!$H$15)) | I35: =IF(I$3>Assumptions!$H$15,"",IF(Assumptions!$C$28=1,IF(I$3=1,Assumptions!$C$26,0),Assumptions!$C$26/Assumptions!$H$15)) | J35: =IF(J$3>Assumptions!$H$15,"",IF(Assumptions!$C$28=1,IF(J$3=1,Assumptions!$C$26,0),Assumptions!$C$26/Assumptions!$H$15)) | K35: =IF(K$3>Assumptions!$H$15,"",IF(Assumptions!$C$28=1,IF(K$3=1,Assumptions!$C$26,0),Assumptions!$C$26/Assumptions!$H$15)) | ... M35: =IF(M$3>Assumptions!$H$15,"",IF(Assumptions!$C$28=1,IF(M$3=1,Assumptions!$C$26,0),Assumptions!$C$26/Assumptions!$H$15))
B36: Replacement Reserves | D36: =IF(D$3>Assumptions!$H$15,"",Assumptions!$C$33) | E36: =IF(E$3>Assumptions!$H$15,"",Assumptions!$C$33) | F36: =IF(F$3>Assumptions!$H$15,"",Assumptions!$C$33) | G36: =IF(G$3>Assumptions!$H$15,"",Assumptions!$C$33) | H36: =IF(H$3>Assumptions!$H$15,"",Assumptions!$C$33) | I36: =IF(I$3>Assumptions!$H$15,"",Assumptions!$C$33) | J36: =IF(J$3>Assumptions!$H$15,"",Assumptions!$C$33) | K36: =IF(K$3>Assumptions!$H$15,"",Assumptions!$C$33) | ... M36: =IF(M$3>Assumptions!$H$15,"",Assumptions!$C$33)
B38: Levered Net Cash Flow | D38: =IF(D$3>Assumptions!$H$15,"",D26-D34-D35-D36) | E38: =IF(E$3>Assumptions!$H$15,"",E26-E34-E35-E36) | F38: =IF(F$3>Assumptions!$H$15,"",F26-F34-F35-F36) | G38: =IF(G$3>Assumptions!$H$15,"",G26-G34-G35-G36) | H38: =IF(H$3>Assumptions!$H$15,"",H26-H34-H35-H36) | I38: =IF(I$3>Assumptions!$H$15,"",I26-I34-I35-I36) | J38: =IF(J$3>Assumptions!$H$15,"",J26-J34-J35-J36) | K38: =IF(K$3>Assumptions!$H$15,"",K26-K34-K35-K36) | ... M38: =IF(M$3>Assumptions!$H$15,"",M26-M34-M35-M36)
B39: Cash-on-Cash Return (Levered) | C39: — | D39: =IF(D$3>Assumptions!$H$15,"",IF(Assumptions!$C$64=0,"",D38/Assumptions!$C$64)) | E39: =IF(E$3>Assumptions!$H$15,"",IF(Assumptions!$C$64=0,"",E38/Assumptions!$C$64)) | F39: =IF(F$3>Assumptions!$H$15,"",IF(Assumptions!$C$64=0,"",F38/Assumptions!$C$64)) | G39: =IF(G$3>Assumptions!$H$15,"",IF(Assumptions!$C$64=0,"",G38/Assumptions!$C$64)) | H39: =IF(H$3>Assumptions!$H$15,"",IF(Assumptions!$C$64=0,"",H38/Assumptions!$C$64)) | I39: =IF(I$3>Assumptions!$H$15,"",IF(Assumptions!$C$64=0,"",I38/Assumptions!$C$64)) | J39: =IF(J$3>Assumptions!$H$15,"",IF(Assumptions!$C$64=0,"",J38/Assumptions!$C$64)) | K39: =IF(K$3>Assumptions!$H$15,"",IF(Assumptions!$C$64=0,"",K38/Assumptions!$C$64)) | ... M39: =IF(M$3>Assumptions!$H$15,"",IF(Assumptions!$C$64=0,"",M38/Assumptions!$C$64))
B41: Debt Metrics
B42: DSCR | C42: — | D42: =IF(D$3>Assumptions!$H$15,"",IF(D34=0,"",D26/D34)) | E42: =IF(E$3>Assumptions!$H$15,"",IF(E34=0,"",E26/E34)) | F42: =IF(F$3>Assumptions!$H$15,"",IF(F34=0,"",F26/F34)) | G42: =IF(G$3>Assumptions!$H$15,"",IF(G34=0,"",G26/G34)) | H42: =IF(H$3>Assumptions!$H$15,"",IF(H34=0,"",H26/H34)) | I42: =IF(I$3>Assumptions!$H$15,"",IF(I34=0,"",I26/I34)) | J42: =IF(J$3>Assumptions!$H$15,"",IF(J34=0,"",J26/J34)) | K42: =IF(K$3>Assumptions!$H$15,"",IF(K34=0,"",K26/K34)) | ... M42: =IF(M$3>Assumptions!$H$15,"",IF(M34=0,"",M26/M34))
B43: Debt Yield | C43: — | D43: =IF(D$3>Assumptions!$H$15,"",IF(Assumptions!$C$39=0,"",D26/Assumptions!$C$39)) | E43: =IF(E$3>Assumptions!$H$15,"",IF(Assumptions!$C$39=0,"",E26/Assumptions!$C$39)) | F43: =IF(F$3>Assumptions!$H$15,"",IF(Assumptions!$C$39=0,"",F26/Assumptions!$C$39)) | G43: =IF(G$3>Assumptions!$H$15,"",IF(Assumptions!$C$39=0,"",G26/Assumptions!$C$39)) | H43: =IF(H$3>Assumptions!$H$15,"",IF(Assumptions!$C$39=0,"",H26/Assumptions!$C$39)) | I43: =IF(I$3>Assumptions!$H$15,"",IF(Assumptions!$C$39=0,"",I26/Assumptions!$C$39)) | J43: =IF(J$3>Assumptions!$H$15,"",IF(Assumptions!$C$39=0,"",J26/Assumptions!$C$39)) | K43: =IF(K$3>Assumptions!$H$15,"",IF(Assumptions!$C$39=0,"",K26/Assumptions!$C$39)) | ... M43: =IF(M$3>Assumptions!$H$15,"",IF(Assumptions!$C$39=0,"",M26/Assumptions!$C$39))

Sheet Sources & Uses
B1: Sources & Uses of Capital
B3: SOURCES | C3: Amount | D3: % | F3: USES | G3: Amount | H3: %
B4: Senior Debt | C4: =Assumptions!$C$39 -> 0 | D4: =IF(C9=0,0,C4/C9) -> 0 | F4: Purchase Price | G4: =Assumptions!$C$15 -> 0 | H4: =IF(G9=0,0,G4/G9) -> 0
B5: Mezzanine Debt | C5: =Assumptions!$C$62 -> 0 | D5: =IF(C9=0,0,C5/C9) -> 0 | F5: Closing Costs | G5: =Assumptions!$C$15*Assumptions!$C$18 -> 0 | H5: =IF(G9=0,0,G5/G9) -> 0
B6: GP Equity (at Close) | C6: =Assumptions!$C$77 -> 0 | D6: =IF(C9=0,0,C6/C9) -> 0 | F6: CapEx Budget | G6: =Assumptions!$C$26 -> 0 | H6: =IF(G9=0,0,G6/G9) -> 0
B7: LP Equity (at Close) | C7: =Assumptions!$C$70 -> 0 | D7: =IF(C9=0,0,C7/C9) -> 0 | F7: Working Capital / Reserves | G7: =Assumptions!$C$33 -> 0 | H7: =IF(G9=0,0,G7/G9) -> 0
B8: LP Equity (Funded over hold) | C8: =Assumptions!$C$64-Assumptions!$C$70 -> 0 | D8: =IF(C9=0,0,C8/C9) -> 0
B9: Total Sources | C9: =SUM(C4:C8) -> 0 | D9: =IF(C9=0,0,1) -> 0 | F9: Total Uses | G9: =SUM(G4:G7) -> 0 | H9: =IF(G9=0,0,1) -> 0
B11: CHECK: Sources − Uses | C11: =C9-G9 -> 0 | G11: =IF(ABS(C9-G9)<1,"BALANCED","IMBALANCED") -> BALANCED

Sheet Rent Comps
B1: Rent Comps
B2: Blue = Input | Black = Formula | Green = Cross-Tab Link
B4: COMPARABLE PROPERTIES
C5: Subject | D5: Comp 1 | E5: Comp 2 | F5: Comp 3 | G5: Comp 4 | H5: Comp 5 | I5: Comp 6 | J5: Comp 7 | K5: Comp 8
B6: Property Name | C6: =Assumptions!$C$5 -> 0
B7: Address | C7: =Assumptions!$C$6 -> 0
B8: City, State, Zip | C8: =Assumptions!$C$7 -> 0
B9: Distance (mi) | C9: —
B10: Unit Count | C10: =Assumptions!$C$9 -> 0
B11: Rentable SF | C11: =Assumptions!$C$10 -> 0
B12: Year Built | C12: =Assumptions!$C$11 -> 0
B13: Year Renovated | C13: =Assumptions!$C$12 -> 0
B14: In-Place Rent / Unit | C14: =IFERROR(Assumptions!$H$33/12/Assumptions!$C$9,"")
B16: UNIT MIX
B17: Studio — Units
B18: 1 BR — Units
B19: 2 BR — Units
B20: 3 BR — Units
B21: 4 BR — Units
B22: Total Units | C22: =SUM(C17:C21) -> 0 | D22: =SUM(D17:D21) -> 0 | E22: =SUM(E17:E21) -> 0 | F22: =SUM(F17:F21) -> 0 | G22: =SUM(G17:G21) -> 0 | H22: =SUM(H17:H21) -> 0 | I22: =SUM(I17:I21) -> 0 | J22: =SUM(J17:J21) -> 0 | K22: =SUM(K17:K21) -> 0
B24: IN-PLACE RENT BY UNIT TYPE
B25: Studio — In-Place Rent
B26: 1 BR — In-Place Rent
B27: 2 BR — In-Place Rent
B28: 3 BR — In-Place Rent
B29: 4 BR — In-Place Rent
B30: In-Place Rent / Unit (Wtd Avg) | C30: =IFERROR(SUMPRODUCT(C25:C29,C$17:C$21)/SUM(C$17:C$21),"") | D30: =IFERROR(SUMPRODUCT(D25:D29,D$17:D$21)/SUM(D$17:D$21),"") | E30: =IFERROR(SUMPRODUCT(E25:E29,E$17:E$21)/SUM(E$17:E$21),"") | F30: =IFERROR(SUMPRODUCT(F25:F29,F$17:F$21)/SUM(F$17:F$21),"") | G30: =IFERROR(SUMPRODUCT(G25:G29,G$17:G$21)/SUM(G$17:G$21),"") | H30: =IFERROR(SUMPRODUCT(H25:H29,H$17:H$21)/SUM(H$17:H$21),"") | I30: =IFERROR(SUMPRODUCT(I25:I29,I$17:I$21)/SUM(I$17:I$21),"") | J30: =IFERROR(SUMPRODUCT(J25:J29,J$17:J$21)/SUM(J$17:J$21),"") | K30: =IFERROR(SUMPRODUCT(K25:K29,K$17:K$21)/SUM(K$17:K$21),"")
B33: OPERATIONAL METRICS
B34: Occupancy (%) | C34: =Assumptions!$H$19 -> 0
B35: Vacancy (%) | C35: =IF(C34="","",1-C34) | D35: =IF(D34="","",1-D34) | E35: =IF(E34="","",1-E34) | F35: =IF(F34="","",1-F34) | G35: =IF(G34="","",1-G34) | H35: =IF(H34="","",1-H34) | I35: =IF(I34="","",1-I34) | J35: =IF(J34="","",1-J34) | K35: =IF(K34="","",1-K34)
B37: MARKET SUMMARY
B38: Comp Avg In-Place Rent | C38: =IFERROR(AVERAGEIF($D$14:$K$14,"<>"),"")
B39: Comp Median In-Place Rent | C39: =IFERROR(MEDIAN($D$14:$K$14),"")
B40: Min In-Place Rent / Unit | C40: =IF(COUNTA($D$14:$K$14)=0,"",MIN($D$14:$K$14))
B41: Max In-Place Rent / Unit | C41: =IF(COUNTA($D$14:$K$14)=0,"",MAX($D$14:$K$14))
B42: Comp Avg In-Place Rent (Wtd) | C42: =IFERROR(AVERAGEIF($D$30:$K$30,"<>"),"")
B43: Comp Median In-Place Rent (Wtd) | C43: =IFERROR(MEDIAN($D$30:$K$30),"")
B44: Min In-Place Rent / Unit (Wtd) | C44: =IF(COUNTA($D$30:$K$30)=0,"",MIN($D$30:$K$30)) -> 0
B45: Max In-Place Rent / Unit (Wtd) | C45: =IF(COUNTA($D$30:$K$30)=0,"",MAX($D$30:$K$30)) -> 0
B46: Comp Avg Occupancy | C46: =IFERROR(AVERAGEIF($D$34:$K$34,"<>"),"")
B47: Subject In-Place Rent / Unit | C47: =$C$14
B48: Subject Premium / (Discount) | C48: =IFERROR((C14-C38)/C38,"")
B49: Subject Premium / (Discount) (Wtd) | C49: =IFERROR((C14-C42)/C42,"")

Sheet Sales Comps
B1: Sales Comps
B2: Blue = Input | Black = Formula | Green = Cross-Tab Link
B4: COMPARABLE SALES
C5: Subject | D5: Comp 1 | E5: Comp 2 | F5: Comp 3 | G5: Comp 4 | H5: Comp 5 | I5: Comp 6 | J5: Comp 7 | K5: Comp 8
B6: Property Name | C6: =Assumptions!$C$5 -> 0
B7: Address | C7: =Assumptions!$C$6 -> 0
B8: City, State, Zip | C8: =Assumptions!$C$7 -> 0
B9: Distance (mi) | C9: —
B10: Unit Count | C10: =Assumptions!$C$9 -> 0
B11: Year Built | C11: =Assumptions!$C$11 -> 0
B12: Year Renovated | C12: =Assumptions!$C$12 -> 0
B14: TRANSACTION DETAIL
B15: Sale Date | C15: —
B16: Sale Price | C16: =Assumptions!$C$15 -> 0
B17: Price / Unit | C17: =IFERROR(C16/C10,"") | D17: =IFERROR(D16/D10,"") | E17: =IFERROR(E16/E10,"") | F17: =IFERROR(F16/F10,"") | G17: =IFERROR(G16/G10,"") | H17: =IFERROR(H16/H10,"") | I17: =IFERROR(I16/I10,"") | J17: =IFERROR(J16/J10,"") | K17: =IFERROR(K16/K10,"")
B18: In-Place Rent / Unit | C18: =IFERROR(Assumptions!$H$33/12/Assumptions!$C$9,"")
B19: Buyer | C19: —
B20: Seller | C20: —
B21: Source / Notes | C21: —
B23: ADJUSTMENTS
B24: Time (%) | C24: —
B25: Size (%) | C25: —
B26: Year Built / Condition (%) | C26: —
B27: Location (%) | C27: —
B28: Market Conditions (%) | C28: —
B29: Total Adjustment (%) | C29: — | D29: =SUM(D24:D28) -> 0 | E29: =SUM(E24:E28) -> 0 | F29: =SUM(F24:F28) -> 0 | G29: =SUM(G24:G28) -> 0 | H29: =SUM(H24:H28) -> 0 | I29: =SUM(I24:I28) -> 0 | J29: =SUM(J24:J28) -> 0 | K29: =SUM(K24:K28) -> 0
B30: Weight (%) | C30: —
B31: Adjusted Price / Unit | C31: — | D31: =IFERROR(D17*(1+D29),"") | E31: =IFERROR(E17*(1+E29),"") | F31: =IFERROR(F17*(1+F29),"") | G31: =IFERROR(G17*(1+G29),"") | H31: =IFERROR(H17*(1+H29),"") | I31: =IFERROR(I17*(1+I29),"") | J31: =IFERROR(J17*(1+J29),"") | K31: =IFERROR(K17*(1+K29),"")
B33: CONCLUDED VALUE
B34: Wtd Avg Adj Price / Unit | C34: =IFERROR(SUMPRODUCT($D$31:$K$31,$D$30:$K$30)/SUM($D$30:$K$30),"")
B35: Implied Value (Per Unit) | C35: =IFERROR($C$34*C10,"")
B36: Comp Avg Price / Unit (Unadj) | C36: =IFERROR(AVERAGEIF($D$17:$K$17,"<>"),"")
B37: Subject Premium / (Discount) | C37: =IFERROR((C34-C36)/C36,"")

Sheet Debt Schedule
B1: Debt Schedule
B2: Year # | D2: =C2+1 -> 1 | E2: =D2+1 -> 2 | F2: =E2+1 -> 3 | G2: =F2+1 -> 4 | H2: =G2+1 -> 5 | I2: =H2+1 -> 6 | J2: =I2+1 -> 7 | K2: =J2+1 -> 8 | L2: =K2+1 -> 9
B3: SENIOR DEBT | C3: Year 1 | D3: Year 2 | E3: Year 3 | F3: Year 4 | G3: Year 5 | H3: Year 6 | I3: Year 7 | J3: Year 8 | K3: Year 9 | L3: Year 10
B4: Beginning Balance | C4: =Assumptions!$C$39 -> 0 | D4: =IF(D$2>Assumptions!$H$15,"",C8) | E4: =IF(E$2>Assumptions!$H$15,"",D8) | F4: =IF(F$2>Assumptions!$H$15,"",E8) | G4: =IF(G$2>Assumptions!$H$15,"",F8) | H4: =IF(H$2>Assumptions!$H$15,"",G8) | I4: =IF(I$2>Assumptions!$H$15,"",H8) | J4: =IF(J$2>Assumptions!$H$15,"",I8) | K4: =IF(K$2>Assumptions!$H$15,"",J8) | L4: =IF(L$2>Assumptions!$H$15,"",K8)
B5: Interest | C5: =IF(C$2>Assumptions!$H$15,"",C4*Assumptions!$C$40) -> 0 | D5: =IF(D$2>Assumptions!$H$15,"",D4*Assumptions!$C$40) | E5: =IF(E$2>Assumptions!$H$15,"",E4*Assumptions!$C$40) | F5: =IF(F$2>Assumptions!$H$15,"",F4*Assumptions!$C$40) | G5: =IF(G$2>Assumptions!$H$15,"",G4*Assumptions!$C$40) | H5: =IF(H$2>Assumptions!$H$15,"",H4*Assumptions!$C$40) | I5: =IF(I$2>Assumptions!$H$15,"",I4*Assumptions!$C$40) | J5: =IF(J$2>Assumptions!$H$15,"",J4*Assumptions!$C$40) | ... L5: =IF(L$2>Assumptions!$H$15,"",L4*Assumptions!$C$40)
B6: Scheduled Principal | C6: =IF(C$2>Assumptions!$H$15,"",IF(Assumptions!$C$37=1,0,IF(Assumptions!$C$37=2,'Pro Forma'!D$32-C5,IF(C$2<=Assumptions!$C$41,0,'Pro Forma'!D$32-C5)))) -> 0 | D6: =IF(D$2>Assumptions!$H$15,"",IF(Assumptions!$C$37=1,0,IF(Assumptions!$C$37=2,'Pro Forma'!E$32-D5,IF(D$2<=Assumptions!$C$41,0,'Pro Forma'!E$32-D5)))) | E6: =IF(E$2>Assumptions!$H$15,"",IF(Assumptions!$C$37=1,0,IF(Assumptions!$C$37=2,'Pro Forma'!F$32-E5,IF(E$2<=Assumptions!$C$41,0,'Pro Forma'!F$32-E5)))) | F6: =IF(F$2>Assumptions!$H$15,"",IF(Assumptions!$C$37=1,0,IF(Assumptions!$C$37=2,'Pro Forma'!G$32-F5,IF(F$2<=Assumptions!$C$41,0,'Pro Forma'!G$32-F5)))) | G6: =IF(G$2>Assumptions!$H$15,"",IF(Assumptions!$C$37=1,0,IF(Assumptions!$C$37=2,'Pro Forma'!H$32-G5,IF(G$2<=Assumptions!$C$41,0,'Pro Forma'!H$32-G5)))) | H6: =IF(H$2>Assumptions!$H$15,"",IF(Assumptions!$C$37=1,0,IF(Assumptions!$C$37=2,'Pro Forma'!I$32-H5,IF(H$2<=Assumptions!$C$41,0,'Pro Forma'!I$32-H5)))) | I6: =IF(I$2>Assumptions!$H$15,"",IF(Assumptions!$C$37=1,0,IF(Assumptions!$C$37=2,'Pro Forma'!J$32-I5,IF(I$2<=Assumptions!$C$41,0,'Pro Forma'!J$32-I5)))) | J6: =IF(J$2>Assumptions!$H$15,"",IF(Assumptions!$C$37=1,0,IF(Assumptions!$C$37=2,'Pro Forma'!K$32-J5,IF(J$2<=Assumptions!$C$41,0,'Pro Forma'!K$32-J5)))) | ... L6: =IF(L$2>Assumptions!$H$15,"",IF(Assumptions!$C$37=1,0,IF(Assumptions!$C$37=2,'Pro Forma'!M$32-L5,IF(L$2<=Assumptions!$C$41,0,'Pro Forma'!M$32-L5))))
B7: Total Payment | C7: =IF(C$2>Assumptions!$H$15,"",C5+C6) -> 0 | D7: =IF(D$2>Assumptions!$H$15,"",D5+D6) | E7: =IF(E$2>Assumptions!$H$15,"",E5+E6) | F7: =IF(F$2>Assumptions!$H$15,"",F5+F6) | G7: =IF(G$2>Assumptions!$H$15,"",G5+G6) | H7: =IF(H$2>Assumptions!$H$15,"",H5+H6) | I7: =IF(I$2>Assumptions!$H$15,"",I5+I6) | J7: =IF(J$2>Assumptions!$H$15,"",J5+J6) | ... L7: =IF(L$2>Assumptions!$H$15,"",L5+L6)
B8: Ending Balance | C8: =IF(C$2>Assumptions!$H$15,"",C4-C6) -> 0 | D8: =IF(D$2>Assumptions!$H$15,"",D4-D6) | E8: =IF(E$2>Assumptions!$H$15,"",E4-E6) | F8: =IF(F$2>Assumptions!$H$15,"",F4-F6) | G8: =IF(G$2>Assumptions!$H$15,"",G4-G6) | H8: =IF(H$2>Assumptions!$H$15,"",H4-H6) | I8: =IF(I$2>Assumptions!$H$15,"",I4-I6) | J8: =IF(J$2>Assumptions!$H$15,"",J4-J6) | ... L8: =IF(L$2>Assumptions!$H$15,"",L4-L6)
B10: COVERAGE METRICS
B11: DSCR | C11: =IF(C$2>Assumptions!$H$15,"",IFERROR(IF('Pro Forma'!D$34=0,"",'Pro Forma'!D$26/'Pro Forma'!D$34),"")) | D11: =IF(D$2>Assumptions!$H$15,"",IFERROR(IF('Pro Forma'!E$34=0,"",'Pro Forma'!E$26/'Pro Forma'!E$34),"")) | E11: =IF(E$2>Assumptions!$H$15,"",IFERROR(IF('Pro Forma'!F$34=0,"",'Pro Forma'!F$26/'Pro Forma'!F$34),"")) | F11: =IF(F$2>Assumptions!$H$15,"",IFERROR(IF('Pro Forma'!G$34=0,"",'Pro Forma'!G$26/'Pro Forma'!G$34),"")) | G11: =IF(G$2>Assumptions!$H$15,"",IFERROR(IF('Pro Forma'!H$34=0,"",'Pro Forma'!H$26/'Pro Forma'!H$34),"")) | H11: =IF(H$2>Assumptions!$H$15,"",IFERROR(IF('Pro Forma'!I$34=0,"",'Pro Forma'!I$26/'Pro Forma'!I$34),"")) | I11: =IF(I$2>Assumptions!$H$15,"",IFERROR(IF('Pro Forma'!J$34=0,"",'Pro Forma'!J$26/'Pro Forma'!J$34),"")) | J11: =IF(J$2>Assumptions!$H$15,"",IFERROR(IF('Pro Forma'!K$34=0,"",'Pro Forma'!K$26/'Pro Forma'!K$34),"")) | ... L11: =IF(L$2>Assumptions!$H$15,"",IFERROR(IF('Pro Forma'!M$34=0,"",'Pro Forma'!M$26/'Pro Forma'!M$34),""))
B12: Debt Yield | C12: =IF(C$2>Assumptions!$H$15,"",IF(C4=0,"",'Pro Forma'!D$26/C4)) | D12: =IF(D$2>Assumptions!$H$15,"",IF(D4=0,"",'Pro Forma'!E$26/D4)) | E12: =IF(E$2>Assumptions!$H$15,"",IF(E4=0,"",'Pro Forma'!F$26/E4)) | F12: =IF(F$2>Assumptions!$H$15,"",IF(F4=0,"",'Pro Forma'!G$26/F4)) | G12: =IF(G$2>Assumptions!$H$15,"",IF(G4=0,"",'Pro Forma'!H$26/G4)) | H12: =IF(H$2>Assumptions!$H$15,"",IF(H4=0,"",'Pro Forma'!I$26/H4)) | I12: =IF(I$2>Assumptions!$H$15,"",IF(I4=0,"",'Pro Forma'!J$26/I4)) | J12: =IF(J$2>Assumptions!$H$15,"",IF(J4=0,"",'Pro Forma'!K$26/J4)) | ... L12: =IF(L$2>Assumptions!$H$15,"",IF(L4=0,"",'Pro Forma'!M$26/L4))
B13: Implied LTV (at Exit Cap) | C13: =IF(C$2>Assumptions!$H$15,"",IF(Assumptions!$C$22=0,"",C8/('Pro Forma'!D$26/Assumptions!$C$22))) | D13: =IF(D$2>Assumptions!$H$15,"",IF(Assumptions!$C$22=0,"",D8/('Pro Forma'!E$26/Assumptions!$C$22))) | E13: =IF(E$2>Assumptions!$H$15,"",IF(Assumptions!$C$22=0,"",E8/('Pro Forma'!F$26/Assumptions!$C$22))) | F13: =IF(F$2>Assumptions!$H$15,"",IF(Assumptions!$C$22=0,"",F8/('Pro Forma'!G$26/Assumptions!$C$22))) | G13: =IF(G$2>Assumptions!$H$15,"",IF(Assumptions!$C$22=0,"",G8/('Pro Forma'!H$26/Assumptions!$C$22))) | H13: =IF(H$2>Assumptions!$H$15,"",IF(Assumptions!$C$22=0,"",H8/('Pro Forma'!I$26/Assumptions!$C$22))) | I13: =IF(I$2>Assumptions!$H$15,"",IF(Assumptions!$C$22=0,"",I8/('Pro Forma'!J$26/Assumptions!$C$22))) | J13: =IF(J$2>Assumptions!$H$15,"",IF(Assumptions!$C$22=0,"",J8/('Pro Forma'!K$26/Assumptions!$C$22))) | ... L13: =IF(L$2>Assumptions!$H$15,"",IF(Assumptions!$C$22=0,"",L8/('Pro Forma'!M$26/Assumptions!$C$22)))
B16: MEZZANINE DEBT | C16: Year 1 | D16: Year 2 | E16: Year 3 | F16: Year 4 | G16: Year 5 | H16: Year 6 | I16: Year 7 | J16: Year 8 | K16: Year 9 | L16: Year 10
B17: Beginning Balance | C17: =Assumptions!$C$62 -> 0 | D17: =IF(D$2>Assumptions!$H$15,"",C19) | E17: =IF(E$2>Assumptions!$H$15,"",D19) | F17: =IF(F$2>Assumptions!$H$15,"",E19) | G17: =IF(G$2>Assumptions!$H$15,"",F19) | H17: =IF(H$2>Assumptions!$H$15,"",G19) | I17: =IF(I$2>Assumptions!$H$15,"",H19) | J17: =IF(J$2>Assumptions!$H$15,"",I19) | K17: =IF(K$2>Assumptions!$H$15,"",J19) | L17: =IF(L$2>Assumptions!$H$15,"",K19)
B18: Interest / Cash Pay | C18: =IF(C$2>Assumptions!$H$15,"",C17*Assumptions!$C$57) -> 0 | D18: =IF(D$2>Assumptions!$H$15,"",D17*Assumptions!$C$57) | E18: =IF(E$2>Assumptions!$H$15,"",E17*Assumptions!$C$57) | F18: =IF(F$2>Assumptions!$H$15,"",F17*Assumptions!$C$57) | G18: =IF(G$2>Assumptions!$H$15,"",G17*Assumptions!$C$57) | H18: =IF(H$2>Assumptions!$H$15,"",H17*Assumptions!$C$57) | I18: =IF(I$2>Assumptions!$H$15,"",I17*Assumptions!$C$57) | J18: =IF(J$2>Assumptions!$H$15,"",J17*Assumptions!$C$57) | ... L18: =IF(L$2>Assumptions!$H$15,"",L17*Assumptions!$C$57)
B19: Ending Balance | C19: =IF(C$2>Assumptions!$H$15,"",C17) -> 0 | D19: =IF(D$2>Assumptions!$H$15,"",D17) | E19: =IF(E$2>Assumptions!$H$15,"",E17) | F19: =IF(F$2>Assumptions!$H$15,"",F17) | G19: =IF(G$2>Assumptions!$H$15,"",G17) | H19: =IF(H$2>Assumptions!$H$15,"",H17) | I19: =IF(I$2>Assumptions!$H$15,"",I17) | J19: =IF(J$2>Assumptions!$H$15,"",J17) | ... L19: =IF(L$2>Assumptions!$H$15,"",L17)

Sheet Returns Summary
B1: Returns Summary & Exit Analysis
B2: Year # | D2: =C2+1 -> 1 | E2: =D2+1 -> 2 | F2: =E2+1 -> 3 | G2: =F2+1 -> 4 | H2: =G2+1 -> 5 | I2: =H2+1 -> 6 | J2: =I2+1 -> 7 | K2: =J2+1 -> 8 | ... M2: =L2+1 -> 10
B3: EXIT ANALYSIS
B4: Hold Period (Years) | C4: =Assumptions!$H$15 -> 0
B5: Exit Year NOI | C5: =IFERROR(CHOOSE(Assumptions!$H$15,'Pro Forma'!D$26,'Pro Forma'!E$26,'Pro Forma'!F$26,'Pro Forma'!G$26,'Pro Forma'!H$26,'Pro Forma'!I$26,'Pro Forma'!J$26,'Pro Forma'!K$26,'Pro Forma'!L$26,'Pro Forma'!M$26),0) -> 0
B6: Exit Cap Rate | C6: =Assumptions!$C$22 -> 0
B7: Gross Disposition Value | C7: =IF(C6=0,0,C5/C6) -> 0
B8: Less: Disposition Costs | C8: =-C7*Assumptions!$C$23 -> 0
B9: Less: Senior Loan Payoff | C9: =IFERROR(-CHOOSE(Assumptions!$H$15,'Debt Schedule'!C$8,'Debt Schedule'!D$8,'Debt Schedule'!E$8,'Debt Schedule'!F$8,'Debt Schedule'!G$8,'Debt Schedule'!H$8,'Debt Schedule'!I$8,'Debt Schedule'!J$8,'Debt Schedule'!K$8,'Debt Schedule'!L$8),0) -> 0
B10: Less: Mezz Loan Payoff | C10: =IFERROR(-CHOOSE(Assumptions!$H$15,'Debt Schedule'!C$19,'Debt Schedule'!D$19,'Debt Schedule'!E$19,'Debt Schedule'!F$19,'Debt Schedule'!G$19,'Debt Schedule'!H$19,'Debt Schedule'!I$19,'Debt Schedule'!J$19,'Debt Schedule'!K$19,'Debt Schedule'!L$19),0) -> 0
B11: Net Sale Proceeds | C11: =C7+C8+C9+C10 -> 0
B12: Profit on Sale | C12: =C11-Assumptions!$C$64 -> 0
B14: UNLEVERED RETURNS
B15: IRR | C15: =IFERROR(IRR(C32:M32),0) -> 0
B16: Equity Multiple | C16: =IF(-C32=0,0,SUM(D32:M32)/(-C32)) -> 0
B17: Total Profit | C17: =SUM(C32:M32) -> 0
B18: Avg Cash-on-Cash | C18: =IF(OR(-C29=0,Assumptions!$H$15=0),0,SUM(D30:M30)/(Assumptions!$H$15*(-C29))) -> 0
B20: LEVERED RETURNS
B21: IRR | C21: =IFERROR(IRR(C38:M38),0) -> 0
B22: Equity Multiple | C22: =IF(-C38=0,0,SUM(D38:M38)/(-C38)) -> 0
B23: Total Profit | C23: =SUM(C38:M38) -> 0
B24: Avg Cash-on-Cash | C24: =IF(OR(Assumptions!$C$64=0,Assumptions!$H$15=0),0,SUM(D36:M36)/(Assumptions!$H$15*Assumptions!$C$70)) -> 0
B25: Return on Cost | C25: =IF(Assumptions!$C$19=0,0,'Pro Forma'!D$26/Assumptions!$C$19) -> 0
B26: Average DSCR | C26: =IFERROR(CHOOSE(Assumptions!$H$15,'Debt Schedule'!C$11,AVERAGE('Debt Schedule'!C$11:D11),AVERAGE('Debt Schedule'!C$11:E11),AVERAGE('Debt Schedule'!C$11:F11),AVERAGE('Debt Schedule'!C$11:G11),AVERAGE('Debt Schedule'!C$11:H11),AVERAGE('Debt Schedule'!C$11:I11),AVERAGE('Debt Schedule'!C$11:J11),AVERAGE('Debt Schedule'!C$11:K11),AVERAGE('Debt Schedule'!C$11:L11)),0) -> 0
B28: UNLEVERED CASH FLOW | C28: Year 0 | D28: Year 1 | E28: Year 2 | F28: Year 3 | G28: Year 4 | H28: Year 5 | I28: Year 6 | J28: Year 7 | K28: Year 8 | L28: Year 9 | M28: Year 10
B29: Total Investment | C29: =-(Assumptions!$C$15+Assumptions!$C$15*Assumptions!$C$18) -> 0 | D29: 0 | E29: 0 | F29: 0 | G29: 0 | H29: 0 | I29: 0 | J29: 0 | K29: 0 | L29: 0 | M29: 0
B30: Unlevered Operating CF | D30: =IF(D$2>Assumptions!$H$15,0,'Pro Forma'!D$30) -> 0 | E30: =IF(E$2>Assumptions!$H$15,0,'Pro Forma'!E$30) -> 0 | F30: =IF(F$2>Assumptions!$H$15,0,'Pro Forma'!F$30) -> 0 | G30: =IF(G$2>Assumptions!$H$15,0,'Pro Forma'!G$30) -> 0 | H30: =IF(H$2>Assumptions!$H$15,0,'Pro Forma'!H$30) -> 0 | I30: =IF(I$2>Assumptions!$H$15,0,'Pro Forma'!I$30) -> 0 | J30: =IF(J$2>Assumptions!$H$15,0,'Pro Forma'!J$30) -> 0 | K30: =IF(K$2>Assumptions!$H$15,0,'Pro Forma'!K$30) -> 0 | ... M30: =IF(M$2>Assumptions!$H$15,0,'Pro Forma'!M$30) -> 0
B31: Sale Proceeds (Net of Costs) | D31: =IF(D$2=Assumptions!$H$15,C7+C8,0) -> 0 | E31: =IF(E$2=Assumptions!$H$15,C7+C8,0) -> 0 | F31: =IF(F$2=Assumptions!$H$15,C7+C8,0) -> 0 | G31: =IF(G$2=Assumptions!$H$15,C7+C8,0) -> 0 | H31: =IF(H$2=Assumptions!$H$15,C7+C8,0) -> 0 | I31: =IF(I$2=Assumptions!$H$15,C7+C8,0) -> 0 | J31: =IF(J$2=Assumptions!$H$15,C7+C8,0) -> 0 | K31: =IF(K$2=Assumptions!$H$15,C7+C8,0) -> 0 | L31: =IF(L$2=Assumptions!$H$15,C7+C8,0) -> 0 | M31: =IF(M$2=Assumptions!$H$15,C7+C8,0) -> 0
B32: Total Unlevered Cash Flow | C32: =C29+C30+C31 -> 0 | D32: =D29+D30+D31 -> 0 | E32: =E29+E30+E31 -> 0 | F32: =F29+F30+F31 -> 0 | G32: =G29+G30+G31 -> 0 | H32: =H29+H30+H31 -> 0 | I32: =I29+I30+I31 -> 0 | J32: =J29+J30+J31 -> 0 | ... M32: =M29+M30+M31 -> 0
B34: LEVERED CASH FLOW | C34: Year 0 | D34: Year 1 | E34: Year 2 | F34: Year 3 | G34: Year 4 | H34: Year 5 | I34: Year 6 | J34: Year 7 | K34: Year 8 | L34: Year 9 | M34: Year 10
B35: Equity Investment | C35: =-Assumptions!$C$70 -> 0 | D35: 0 | E35: 0 | F35: 0 | G35: 0 | H35: 0 | I35: 0 | J35: 0 | K35: 0 | L35: 0 | M35: 0
B36: Operating Cash Flow | D36: =IF(D$2>Assumptions!$H$15,0,'Pro Forma'!D$38) -> 0 | E36: =IF(E$2>Assumptions!$H$15,0,'Pro Forma'!E$38) -> 0 | F36: =IF(F$2>Assumptions!$H$15,0,'Pro Forma'!F$38) -> 0 | G36: =IF(G$2>Assumptions!$H$15,0,'Pro Forma'!G$38) -> 0 | H36: =IF(H$2>Assumptions!$H$15,0,'Pro Forma'!H$38) -> 0 | I36: =IF(I$2>Assumptions!$H$15,0,'Pro Forma'!I$38) -> 0 | J36: =IF(J$2>Assumptions!$H$15,0,'Pro Forma'!J$38) -> 0 | K36: =IF(K$2>Assumptions!$H$15,0,'Pro Forma'!K$38) -> 0 | ... M36: =IF(M$2>Assumptions!$H$15,0,'Pro Forma'!M$38) -> 0
B37: Net Sale Proceeds | D37: =IF(D$2=Assumptions!$H$15,C11,0) -> 0 | E37: =IF(E$2=Assumptions!$H$15,C11,0) -> 0 | F37: =IF(F$2=Assumptions!$H$15,C11,0) -> 0 | G37: =IF(G$2=Assumptions!$H$15,C11,0) -> 0 | H37: =IF(H$2=Assumptions!$H$15,C11,0) -> 0 | I37: =IF(I$2=Assumptions!$H$15,C11,0) -> 0 | J37: =IF(J$2=Assumptions!$H$15,C11,0) -> 0 | K37: =IF(K$2=Assumptions!$H$15,C11,0) -> 0 | L37: =IF(L$2=Assumptions!$H$15,C11,0) -> 0 | M37: =IF(M$2=Assumptions!$H$15,C11,0) -> 0
B38: Total Levered Cash Flow | C38: =C35+C36+C37 -> 0 | D38: =D35+D36+D37 -> 0 | E38: =E35+E36+E37 -> 0 | F38: =F35+F36+F37 -> 0 | G38: =G35+G36+G37 -> 0 | H38: =H35+H36+H37 -> 0 | I38: =I35+I36+I37 -> 0 | J38: =J35+J36+J37 -> 0 | ... M38: =M35+M36+M37 -> 0

Sheet Waterfall
B1: JV Equity Waterfall
B2: Multi-tier IRR-based promote with BOP/EOP equity tracking
B3: Year # | D3: =C3+1 -> 1 | E3: =D3+1 -> 2 | F3: =E3+1 -> 3 | G3: =F3+1 -> 4 | H3: =G3+1 -> 5 | I3: =H3+1 -> 6 | J3: =I3+1 -> 7 | K3: =J3+1 -> 8 | ... M3: =L3+1 -> 10
B4: CONTRIBUTIONS & DISTRIBUTIONS
C5: Year 0 | D5: Year 1 | E5: Year 2 | F5: Year 3 | G5: Year 4 | H5: Year 5 | I5: Year 6 | J5: Year 7 | K5: Year 8 | L5: Year 9 | M5: Year 10
B6: Equity Contributions | C6: =-Assumptions!$C$70 -> 0 | D6: =IF(D$3>Assumptions!$H$15,0,0) -> 0 | E6: =IF(E$3>Assumptions!$H$15,0,0) -> 0 | F6: =IF(F$3>Assumptions!$H$15,0,0) -> 0 | G6: =IF(G$3>Assumptions!$H$15,0,0) -> 0 | H6: =IF(H$3>Assumptions!$H$15,0,0) -> 0 | I6: =IF(I$3>Assumptions!$H$15,0,0) -> 0 | J6: =IF(J$3>Assumptions!$H$15,0,0) -> 0 | K6: =IF(K$3>Assumptions!$H$15,0,0) -> 0 | ... M6: =IF(M$3>Assumptions!$H$15,0,0) -> 0
B7: Distributable Cash Flow | C7: =0 -> 0 | D7: =IF(D$3>Assumptions!$H$15,0,'Returns Summary'!D$36+'Returns Summary'!D$37) -> 0 | E7: =IF(E$3>Assumptions!$H$15,0,'Returns Summary'!E$36+'Returns Summary'!E$37) -> 0 | F7: =IF(F$3>Assumptions!$H$15,0,'Returns Summary'!F$36+'Returns Summary'!F$37) -> 0 | G7: =IF(G$3>Assumptions!$H$15,0,'Returns Summary'!G$36+'Returns Summary'!G$37) -> 0 | H7: =IF(H$3>Assumptions!$H$15,0,'Returns Summary'!H$36+'Returns Summary'!H$37) -> 0 | I7: =IF(I$3>Assumptions!$H$15,0,'Returns Summary'!I$36+'Returns Summary'!I$37) -> 0 | J7: =IF(J$3>Assumptions!$H$15,0,'Returns Summary'!J$36+'Returns Summary'!J$37) -> 0 | K7: =IF(K$3>Assumptions!$H$15,0,'Returns Summary'!K$36+'Returns Summary'!K$37) -> 0 | ... M7: =IF(M$3>Assumptions!$H$15,0,'Returns Summary'!M$36+'Returns Summary'!M$37) -> 0
B10: ="TIER 1 — PREFERRED RETURN ("&TEXT(Assumptions!$C$79,"0%")&")" -> TIER 1 — PREFERRED RETURN (0%)
B11: BOP Equity Balance | C11: =0 -> 0 | D11: =IF(D$3>Assumptions!$H$15,0,C15) -> 0 | E11: =IF(E$3>Assumptions!$H$15,0,D15) -> 0 | F11: =IF(F$3>Assumptions!$H$15,0,E15) -> 0 | G11: =IF(G$3>Assumptions!$H$15,0,F15) -> 0 | H11: =IF(H$3>Assumptions!$H$15,0,G15) -> 0 | I11: =IF(I$3>Assumptions!$H$15,0,H15) -> 0 | J11: =IF(J$3>Assumptions!$H$15,0,I15) -> 0 | K11: =IF(K$3>Assumptions!$H$15,0,J15) -> 0 | ... M11: =IF(M$3>Assumptions!$H$15,0,L15) -> 0
B12: + Contributions | C12: =Assumptions!$C$70 -> 0 | D12: =IF(D$3>Assumptions!$H$15,0,0) -> 0 | E12: =IF(E$3>Assumptions!$H$15,0,0) -> 0 | F12: =IF(F$3>Assumptions!$H$15,0,0) -> 0 | G12: =IF(G$3>Assumptions!$H$15,0,0) -> 0 | H12: =IF(H$3>Assumptions!$H$15,0,0) -> 0 | I12: =IF(I$3>Assumptions!$H$15,0,0) -> 0 | J12: =IF(J$3>Assumptions!$H$15,0,0) -> 0 | K12: =IF(K$3>Assumptions!$H$15,0,0) -> 0 | ... M12: =IF(M$3>Assumptions!$H$15,0,0) -> 0
B13: + Pref Return Accrual | C13: =0 -> 0 | D13: =IF(D$3>Assumptions!$H$15,0,D11*Assumptions!$C$79) -> 0 | E13: =IF(E$3>Assumptions!$H$15,0,E11*Assumptions!$C$79) -> 0 | F13: =IF(F$3>Assumptions!$H$15,0,F11*Assumptions!$C$79) -> 0 | G13: =IF(G$3>Assumptions!$H$15,0,G11*Assumptions!$C$79) -> 0 | H13: =IF(H$3>Assumptions!$H$15,0,H11*Assumptions!$C$79) -> 0 | I13: =IF(I$3>Assumptions!$H$15,0,I11*Assumptions!$C$79) -> 0 | J13: =IF(J$3>Assumptions!$H$15,0,J11*Assumptions!$C$79) -> 0 | K13: =IF(K$3>Assumptions!$H$15,0,K11*Assumptions!$C$79) -> 0 | ... M13: =IF(M$3>Assumptions!$H$15,0,M11*Assumptions!$C$79) -> 0
B14: − Distributions | C14: =0 -> 0 | D14: =IF(D$3>Assumptions!$H$15,0,MIN(D7,MAX(0,D11+D13))) -> 0 | E14: =IF(E$3>Assumptions!$H$15,0,MIN(E7,MAX(0,E11+E13))) -> 0 | F14: =IF(F$3>Assumptions!$H$15,0,MIN(F7,MAX(0,F11+F13))) -> 0 | G14: =IF(G$3>Assumptions!$H$15,0,MIN(G7,MAX(0,G11+G13))) -> 0 | H14: =IF(H$3>Assumptions!$H$15,0,MIN(H7,MAX(0,H11+H13))) -> 0 | I14: =IF(I$3>Assumptions!$H$15,0,MIN(I7,MAX(0,I11+I13))) -> 0 | J14: =IF(J$3>Assumptions!$H$15,0,MIN(J7,MAX(0,J11+J13))) -> 0 | K14: =IF(K$3>Assumptions!$H$15,0,MIN(K7,MAX(0,K11+K13))) -> 0 | ... M14: =IF(M$3>Assumptions!$H$15,0,MIN(M7,MAX(0,M11+M13))) -> 0
B15: EOP Equity Balance | C15: =C11+C12+C13-C14 -> 0 | D15: =IF(D$3>Assumptions!$H$15,0,MAX(0,D11+D13-D14)) -> 0 | E15: =IF(E$3>Assumptions!$H$15,0,MAX(0,E11+E13-E14)) -> 0 | F15: =IF(F$3>Assumptions!$H$15,0,MAX(0,F11+F13-F14)) -> 0 | G15: =IF(G$3>Assumptions!$H$15,0,MAX(0,G11+G13-G14)) -> 0 | H15: =IF(H$3>Assumptions!$H$15,0,MAX(0,H11+H13-H14)) -> 0 | I15: =IF(I$3>Assumptions!$H$15,0,MAX(0,I11+I13-I14)) -> 0 | J15: =IF(J$3>Assumptions!$H$15,0,MAX(0,J11+J13-J14)) -> 0 | K15: =IF(K$3>Assumptions!$H$15,0,MAX(0,K11+K13-K14)) -> 0 | ... M15: =IF(M$3>Assumptions!$H$15,0,MAX(0,M11+M13-M14)) -> 0
B17: Investor Distributions (100%) | C17: =0 -> 0 | D17: =IF(D$3>Assumptions!$H$15,0,D14) -> 0 | E17: =IF(E$3>Assumptions!$H$15,0,E14) -> 0 | F17: =IF(F$3>Assumptions!$H$15,0,F14) -> 0 | G17: =IF(G$3>Assumptions!$H$15,0,G14) -> 0 | H17: =IF(H$3>Assumptions!$H$15,0,H14) -> 0 | I17: =IF(I$3>Assumptions!$H$15,0,I14) -> 0 | J17: =IF(J$3>Assumptions!$H$15,0,J14) -> 0 | K17: =IF(K$3>Assumptions!$H$15,0,K14) -> 0 | ... M17: =IF(M$3>Assumptions!$H$15,0,M14) -> 0
B18: Investor CF (for IRR) | C18: =-Assumptions!$C$70 -> 0 | D18: =IF(D$3>Assumptions!$H$15,0,D17) -> 0 | E18: =IF(E$3>Assumptions!$H$15,0,E17) -> 0 | F18: =IF(F$3>Assumptions!$H$15,0,F17) -> 0 | G18: =IF(G$3>Assumptions!$H$15,0,G17) -> 0 | H18: =IF(H$3>Assumptions!$H$15,0,H17) -> 0 | I18: =IF(I$3>Assumptions!$H$15,0,I17) -> 0 | J18: =IF(J$3>Assumptions!$H$15,0,J17) -> 0 | K18: =IF(K$3>Assumptions!$H$15,0,K17) -> 0 | ... M18: =IF(M$3>Assumptions!$H$15,0,M17) -> 0
B19: IRR Check | C19: ="" | D19: =IF(D$3=Assumptions!$H$15,IFERROR(IRR($C$18:D18),"—"),"") | E19: =IF(E$3=Assumptions!$H$15,IFERROR(IRR($C$18:E18),"—"),"") | F19: =IF(F$3=Assumptions!$H$15,IFERROR(IRR($C$18:F18),"—"),"") | G19: =IF(G$3=Assumptions!$H$15,IFERROR(IRR($C$18:G18),"—"),"") | H19: =IF(H$3=Assumptions!$H$15,IFERROR(IRR($C$18:H18),"—"),"") | I19: =IF(I$3=Assumptions!$H$15,IFERROR(IRR($C$18:I18),"—"),"") | J19: =IF(J$3=Assumptions!$H$15,IFERROR(IRR($C$18:J18),"—"),"") | K19: =IF(K$3=Assumptions!$H$15,IFERROR(IRR($C$18:K18),"—"),"") | ... M19: =IF(M$3=Assumptions!$H$15,IFERROR(IRR($C$18:M18),"—"),"")
B20: Cash to Next Tier | C20: =0 -> 0 | D20: =IF(D$3>Assumptions!$H$15,0,D7-D14) -> 0 | E20: =IF(E$3>Assumptions!$H$15,0,E7-E14) -> 0 | F20: =IF(F$3>Assumptions!$H$15,0,F7-F14) -> 0 | G20: =IF(G$3>Assumptions!$H$15,0,G7-G14) -> 0 | H20: =IF(H$3>Assumptions!$H$15,0,H7-H14) -> 0 | I20: =IF(I$3>Assumptions!$H$15,0,I7-I14) -> 0 | J20: =IF(J$3>Assumptions!$H$15,0,J7-J14) -> 0 | K20: =IF(K$3>Assumptions!$H$15,0,K7-K14) -> 0 | ... M20: =IF(M$3>Assumptions!$H$15,0,M7-M14) -> 0
B22: ="TIER 2 — FIRST PROMOTE ("&TEXT(Assumptions!$C$80,"0%")&" IRR / "&TEXT(Assumptions!$C$81,"0%")&" Promote)" -> TIER 2 — FIRST PROMOTE (0% IRR / 0% Promote)
B23: BOP Equity Balance | C23: =0 -> 0 | D23: =IF(D$3>Assumptions!$H$15,0,C28) -> 0 | E23: =IF(E$3>Assumptions!$H$15,0,D28) -> 0 | F23: =IF(F$3>Assumptions!$H$15,0,E28) -> 0 | G23: =IF(G$3>Assumptions!$H$15,0,F28) -> 0 | H23: =IF(H$3>Assumptions!$H$15,0,G28) -> 0 | I23: =IF(I$3>Assumptions!$H$15,0,H28) -> 0 | J23: =IF(J$3>Assumptions!$H$15,0,I28) -> 0 | K23: =IF(K$3>Assumptions!$H$15,0,J28) -> 0 | ... M23: =IF(M$3>Assumptions!$H$15,0,L28) -> 0
B24: + Contributions | C24: =Assumptions!$C$70 -> 0 | D24: =IF(D$3>Assumptions!$H$15,0,0) -> 0 | E24: =IF(E$3>Assumptions!$H$15,0,0) -> 0 | F24: =IF(F$3>Assumptions!$H$15,0,0) -> 0 | G24: =IF(G$3>Assumptions!$H$15,0,0) -> 0 | H24: =IF(H$3>Assumptions!$H$15,0,0) -> 0 | I24: =IF(I$3>Assumptions!$H$15,0,0) -> 0 | J24: =IF(J$3>Assumptions!$H$15,0,0) -> 0 | K24: =IF(K$3>Assumptions!$H$15,0,0) -> 0 | ... M24: =IF(M$3>Assumptions!$H$15,0,0) -> 0
B25: + Return Accrual | C25: =0 -> 0 | D25: =IF(D$3>Assumptions!$H$15,0,D23*Assumptions!$C$80) -> 0 | E25: =IF(E$3>Assumptions!$H$15,0,E23*Assumptions!$C$80) -> 0 | F25: =IF(F$3>Assumptions!$H$15,0,F23*Assumptions!$C$80) -> 0 | G25: =IF(G$3>Assumptions!$H$15,0,G23*Assumptions!$C$80) -> 0 | H25: =IF(H$3>Assumptions!$H$15,0,H23*Assumptions!$C$80) -> 0 | I25: =IF(I$3>Assumptions!$H$15,0,I23*Assumptions!$C$80) -> 0 | J25: =IF(J$3>Assumptions!$H$15,0,J23*Assumptions!$C$80) -> 0 | K25: =IF(K$3>Assumptions!$H$15,0,K23*Assumptions!$C$80) -> 0 | ... M25: =IF(M$3>Assumptions!$H$15,0,M23*Assumptions!$C$80) -> 0
B26: − Prev Tier Investor Distributions | C26: =0 -> 0 | D26: =IF(D$3>Assumptions!$H$15,0,D17) -> 0 | E26: =IF(E$3>Assumptions!$H$15,0,E17) -> 0 | F26: =IF(F$3>Assumptions!$H$15,0,F17) -> 0 | G26: =IF(G$3>Assumptions!$H$15,0,G17) -> 0 | H26: =IF(H$3>Assumptions!$H$15,0,H17) -> 0 | I26: =IF(I$3>Assumptions!$H$15,0,I17) -> 0 | J26: =IF(J$3>Assumptions!$H$15,0,J17) -> 0 | K26: =IF(K$3>Assumptions!$H$15,0,K17) -> 0 | ... M26: =IF(M$3>Assumptions!$H$15,0,M17) -> 0
B27: − Current Tier Distributions | C27: =0 -> 0 | D27: =IF(D$3>Assumptions!$H$15,0,IF(Assumptions!$C$81>=1,0,MIN(D20,MAX(0,D23+D25-D26)/(1-Assumptions!$C$81)))) -> 0 | E27: =IF(E$3>Assumptions!$H$15,0,IF(Assumptions!$C$81>=1,0,MIN(E20,MAX(0,E23+E25-E26)/(1-Assumptions!$C$81)))) -> 0 | F27: =IF(F$3>Assumptions!$H$15,0,IF(Assumptions!$C$81>=1,0,MIN(F20,MAX(0,F23+F25-F26)/(1-Assumptions!$C$81)))) -> 0 | G27: =IF(G$3>Assumptions!$H$15,0,IF(Assumptions!$C$81>=1,0,MIN(G20,MAX(0,G23+G25-G26)/(1-Assumptions!$C$81)))) -> 0 | H27: =IF(H$3>Assumptions!$H$15,0,IF(Assumptions!$C$81>=1,0,MIN(H20,MAX(0,H23+H25-H26)/(1-Assumptions!$C$81)))) -> 0 | I27: =IF(I$3>Assumptions!$H$15,0,IF(Assumptions!$C$81>=1,0,MIN(I20,MAX(0,I23+I25-I26)/(1-Assumptions!$C$81)))) -> 0 | J27: =IF(J$3>Assumptions!$H$15,0,IF(Assumptions!$C$81>=1,0,MIN(J20,MAX(0,J23+J25-J26)/(1-Assumptions!$C$81)))) -> 0 | K27: =IF(K$3>Assumptions!$H$15,0,IF(Assumptions!$C$81>=1,0,MIN(K20,MAX(0,K23+K25-K26)/(1-Assumptions!$C$81)))) -> 0 | ... M27: =IF(M$3>Assumptions!$H$15,0,IF(Assumptions!$C$81>=1,0,MIN(M20,MAX(0,M23+M25-M26)/(1-Assumptions!$C$81)))) -> 0
B28: EOP Equity Balance | C28: =C23+C24+C25-C26-C27 -> 0 | D28: =IF(D$3>Assumptions!$H$15,0,MAX(0,D23+D25-D26-D27*(1-Assumptions!$C$81))) -> 0 | E28: =IF(E$3>Assumptions!$H$15,0,MAX(0,E23+E25-E26-E27*(1-Assumptions!$C$81))) -> 0 | F28: =IF(F$3>Assumptions!$H$15,0,MAX(0,F23+F25-F26-F27*(1-Assumptions!$C$81))) -> 0 | G28: =IF(G$3>Assumptions!$H$15,0,MAX(0,G23+G25-G26-G27*(1-Assumptions!$C$81))) -> 0 | H28: =IF(H$3>Assumptions!$H$15,0,MAX(0,H23+H25-H26-H27*(1-Assumptions!$C$81))) -> 0 | I28: =IF(I$3>Assumptions!$H$15,0,MAX(0,I23+I25-I26-I27*(1-Assumptions!$C$81))) -> 0 | J28: =IF(J$3>Assumptions!$H$15,0,MAX(0,J23+J25-J26-J27*(1-Assumptions!$C$81))) -> 0 | K28: =IF(K$3>Assumptions!$H$15,0,MAX(0,K23+K25-K26-K27*(1-Assumptions!$C$81))) -> 0 | ... M28: =IF(M$3>Assumptions!$H$15,0,MAX(0,M23+M25-M26-M27*(1-Assumptions!$C$81))) -> 0
B30: Investor Distributions | C30: =0 -> 0 | D30: =IF(D$3>Assumptions!$H$15,0,D27*(1-Assumptions!$C$81)) -> 0 | E30: =IF(E$3>Assumptions!$H$15,0,E27*(1-Assumptions!$C$81)) -> 0 | F30: =IF(F$3>Assumptions!$H$15,0,F27*(1-Assumptions!$C$81)) -> 0 | G30: =IF(G$3>Assumptions!$H$15,0,G27*(1-Assumptions!$C$81)) -> 0 | H30: =IF(H$3>Assumptions!$H$15,0,H27*(1-Assumptions!$C$81)) -> 0 | I30: =IF(I$3>Assumptions!$H$15,0,I27*(1-Assumptions!$C$81)) -> 0 | J30: =IF(J$3>Assumptions!$H$15,0,J27*(1-Assumptions!$C$81)) -> 0 | K30: =IF(K$3>Assumptions!$H$15,0,K27*(1-Assumptions!$C$81)) -> 0 | ... M30: =IF(M$3>Assumptions!$H$15,0,M27*(1-Assumptions!$C$81)) -> 0
B31: Promote Distributions | C31: =0 -> 0 | D31: =IF(D$3>Assumptions!$H$15,0,D27*Assumptions!$C$81) -> 0 | E31: =IF(E$3>Assumptions!$H$15,0,E27*Assumptions!$C$81) -> 0 | F31: =IF(F$3>Assumptions!$H$15,0,F27*Assumptions!$C$81) -> 0 | G31: =IF(G$3>Assumptions!$H$15,0,G27*Assumptions!$C$81) -> 0 | H31: =IF(H$3>Assumptions!$H$15,0,H27*Assumptions!$C$81) -> 0 | I31: =IF(I$3>Assumptions!$H$15,0,I27*Assumptions!$C$81) -> 0 | J31: =IF(J$3>Assumptions!$H$15,0,J27*Assumptions!$C$81) -> 0 | K31: =IF(K$3>Assumptions!$H$15,0,K27*Assumptions!$C$81) -> 0 | ... M31: =IF(M$3>Assumptions!$H$15,0,M27*Assumptions!$C$81) -> 0
B32: Investor CF (for IRR) | C32: =-Assumptions!$C$70 -> 0 | D32: =IF(D$3>Assumptions!$H$15,0,D17+D30) -> 0 | E32: =IF(E$3>Assumptions!$H$15,0,E17+E30) -> 0 | F32: =IF(F$3>Assumptions!$H$15,0,F17+F30) -> 0 | G32: =IF(G$3>Assumptions!$H$15,0,G17+G30) -> 0 | H32: =IF(H$3>Assumptions!$H$15,0,H17+H30) -> 0 | I32: =IF(I$3>Assumptions!$H$15,0,I17+I30) -> 0 | J32: =IF(J$3>Assumptions!$H$15,0,J17+J30) -> 0 | K32: =IF(K$3>Assumptions!$H$15,0,K17+K30) -> 0 | ... M32: =IF(M$3>Assumptions!$H$15,0,M17+M30) -> 0
B33: IRR Check | C33: ="" | D33: =IF(D$3=Assumptions!$H$15,IFERROR(IRR($C$32:D32),"—"),"") | E33: =IF(E$3=Assumptions!$H$15,IFERROR(IRR($C$32:E32),"—"),"") | F33: =IF(F$3=Assumptions!$H$15,IFERROR(IRR($C$32:F32),"—"),"") | G33: =IF(G$3=Assumptions!$H$15,IFERROR(IRR($C$32:G32),"—"),"") | H33: =IF(H$3=Assumptions!$H$15,IFERROR(IRR($C$32:H32),"—"),"") | I33: =IF(I$3=Assumptions!$H$15,IFERROR(IRR($C$32:I32),"—"),"") | J33: =IF(J$3=Assumptions!$H$15,IFERROR(IRR($C$32:J32),"—"),"") | K33: =IF(K$3=Assumptions!$H$15,IFERROR(IRR($C$32:K32),"—"),"") | ... M33: =IF(M$3=Assumptions!$H$15,IFERROR(IRR($C$32:M32),"—"),"")
B34: Cash to Next Tier | C34: =0 -> 0 | D34: =IF(D$3>Assumptions!$H$15,0,D20-D27) -> 0 | E34: =IF(E$3>Assumptions!$H$15,0,E20-E27) -> 0 | F34: =IF(F$3>Assumptions!$H$15,0,F20-F27) -> 0 | G34: =IF(G$3>Assumptions!$H$15,0,G20-G27) -> 0 | H34: =IF(H$3>Assumptions!$H$15,0,H20-H27) -> 0 | I34: =IF(I$3>Assumptions!$H$15,0,I20-I27) -> 0 | J34: =IF(J$3>Assumptions!$H$15,0,J20-J27) -> 0 | K34: =IF(K$3>Assumptions!$H$15,0,K20-K27) -> 0 | ... M34: =IF(M$3>Assumptions!$H$15,0,M20-M27) -> 0
B36: ="TIER 3 — SECOND PROMOTE ("&TEXT(Assumptions!$C$82,"0%")&" IRR / "&TEXT(Assumptions!$C$83,"0%")&" Promote)" -> TIER 3 — SECOND PROMOTE (0% IRR / 0% Promote)
B37: BOP Equity Balance | C37: =0 -> 0 | D37: =IF(D$3>Assumptions!$H$15,0,C42) -> 0 | E37: =IF(E$3>Assumptions!$H$15,0,D42) -> 0 | F37: =IF(F$3>Assumptions!$H$15,0,E42) -> 0 | G37: =IF(G$3>Assumptions!$H$15,0,F42) -> 0 | H37: =IF(H$3>Assumptions!$H$15,0,G42) -> 0 | I37: =IF(I$3>Assumptions!$H$15,0,H42) -> 0 | J37: =IF(J$3>Assumptions!$H$15,0,I42) -> 0 | K37: =IF(K$3>Assumptions!$H$15,0,J42) -> 0 | ... M37: =IF(M$3>Assumptions!$H$15,0,L42) -> 0
B38: + Contributions | C38: =Assumptions!$C$70 -> 0 | D38: =IF(D$3>Assumptions!$H$15,0,0) -> 0 | E38: =IF(E$3>Assumptions!$H$15,0,0) -> 0 | F38: =IF(F$3>Assumptions!$H$15,0,0) -> 0 | G38: =IF(G$3>Assumptions!$H$15,0,0) -> 0 | H38: =IF(H$3>Assumptions!$H$15,0,0) -> 0 | I38: =IF(I$3>Assumptions!$H$15,0,0) -> 0 | J38: =IF(J$3>Assumptions!$H$15,0,0) -> 0 | K38: =IF(K$3>Assumptions!$H$15,0,0) -> 0 | ... M38: =IF(M$3>Assumptions!$H$15,0,0) -> 0
B39: + Return Accrual | C39: =0 -> 0 | D39: =IF(D$3>Assumptions!$H$15,0,D37*Assumptions!$C$82) -> 0 | E39: =IF(E$3>Assumptions!$H$15,0,E37*Assumptions!$C$82) -> 0 | F39: =IF(F$3>Assumptions!$H$15,0,F37*Assumptions!$C$82) -> 0 | G39: =IF(G$3>Assumptions!$H$15,0,G37*Assumptions!$C$82) -> 0 | H39: =IF(H$3>Assumptions!$H$15,0,H37*Assumptions!$C$82) -> 0 | I39: =IF(I$3>Assumptions!$H$15,0,I37*Assumptions!$C$82) -> 0 | J39: =IF(J$3>Assumptions!$H$15,0,J37*Assumptions!$C$82) -> 0 | K39: =IF(K$3>Assumptions!$H$15,0,K37*Assumptions!$C$82) -> 0 | ... M39: =IF(M$3>Assumptions!$H$15,0,M37*Assumptions!$C$82) -> 0
B40: − Prev Tier Investor Distributions | C40: =0 -> 0 | D40: =IF(D$3>Assumptions!$H$15,0,D17+D30) -> 0 | E40: =IF(E$3>Assumptions!$H$15,0,E17+E30) -> 0 | F40: =IF(F$3>Assumptions!$H$15,0,F17+F30) -> 0 | G40: =IF(G$3>Assumptions!$H$15,0,G17+G30) -> 0 | H40: =IF(H$3>Assumptions!$H$15,0,H17+H30) -> 0 | I40: =IF(I$3>Assumptions!$H$15,0,I17+I30) -> 0 | J40: =IF(J$3>Assumptions!$H$15,0,J17+J30) -> 0 | K40: =IF(K$3>Assumptions!$H$15,0,K17+K30) -> 0 | ... M40: =IF(M$3>Assumptions!$H$15,0,M17+M30) -> 0
B41: − Current Tier Distributions | C41: =0 -> 0 | D41: =IF(D$3>Assumptions!$H$15,0,IF(Assumptions!$C$83>=1,0,MIN(D34,MAX(0,D37+D39-D40)/(1-Assumptions!$C$83)))) -> 0 | E41: =IF(E$3>Assumptions!$H$15,0,IF(Assumptions!$C$83>=1,0,MIN(E34,MAX(0,E37+E39-E40)/(1-Assumptions!$C$83)))) -> 0 | F41: =IF(F$3>Assumptions!$H$15,0,IF(Assumptions!$C$83>=1,0,MIN(F34,MAX(0,F37+F39-F40)/(1-Assumptions!$C$83)))) -> 0 | G41: =IF(G$3>Assumptions!$H$15,0,IF(Assumptions!$C$83>=1,0,MIN(G34,MAX(0,G37+G39-G40)/(1-Assumptions!$C$83)))) -> 0 | H41: =IF(H$3>Assumptions!$H$15,0,IF(Assumptions!$C$83>=1,0,MIN(H34,MAX(0,H37+H39-H40)/(1-Assumptions!$C$83)))) -> 0 | I41: =IF(I$3>Assumptions!$H$15,0,IF(Assumptions!$C$83>=1,0,MIN(I34,MAX(0,I37+I39-I40)/(1-Assumptions!$C$83)))) -> 0 | J41: =IF(J$3>Assumptions!$H$15,0,IF(Assumptions!$C$83>=1,0,MIN(J34,MAX(0,J37+J39-J40)/(1-Assumptions!$C$83)))) -> 0 | K41: =IF(K$3>Assumptions!$H$15,0,IF(Assumptions!$C$83>=1,0,MIN(K34,MAX(0,K37+K39-K40)/(1-Assumptions!$C$83)))) -> 0 | ... M41: =IF(M$3>Assumptions!$H$15,0,IF(Assumptions!$C$83>=1,0,MIN(M34,MAX(0,M37+M39-M40)/(1-Assumptions!$C$83)))) -> 0
B42: EOP Equity Balance | C42: =C37+C38+C39-C40-C41 -> 0 | D42: =IF(D$3>Assumptions!$H$15,0,MAX(0,D37+D39-D40-D41*(1-Assumptions!$C$83))) -> 0 | E42: =IF(E$3>Assumptions!$H$15,0,MAX(0,E37+E39-E40-E41*(1-Assumptions!$C$83))) -> 0 | F42: =IF(F$3>Assumptions!$H$15,0,MAX(0,F37+F39-F40-F41*(1-Assumptions!$C$83))) -> 0 | G42: =IF(G$3>Assumptions!$H$15,0,MAX(0,G37+G39-G40-G41*(1-Assumptions!$C$83))) -> 0 | H42: =IF(H$3>Assumptions!$H$15,0,MAX(0,H37+H39-H40-H41*(1-Assumptions!$C$83))) -> 0 | I42: =IF(I$3>Assumptions!$H$15,0,MAX(0,I37+I39-I40-I41*(1-Assumptions!$C$83))) -> 0 | J42: =IF(J$3>Assumptions!$H$15,0,MAX(0,J37+J39-J40-J41*(1-Assumptions!$C$83))) -> 0 | K42: =IF(K$3>Assumptions!$H$15,0,MAX(0,K37+K39-K40-K41*(1-Assumptions!$C$83))) -> 0 | ... M42: =IF(M$3>Assumptions!$H$15,0,MAX(0,M37+M39-M40-M41*(1-Assumptions!$C$83))) -> 0
B44: Investor Distributions | C44: =0 -> 0 | D44: =IF(D$3>Assumptions!$H$15,0,D41*(1-Assumptions!$C$83)) -> 0 | E44: =IF(E$3>Assumptions!$H$15,0,E41*(1-Assumptions!$C$83)) -> 0 | F44: =IF(F$3>Assumptions!$H$15,0,F41*(1-Assumptions!$C$83)) -> 0 | G44: =IF(G$3>Assumptions!$H$15,0,G41*(1-Assumptions!$C$83)) -> 0 | H44: =IF(H$3>Assumptions!$H$15,0,H41*(1-Assumptions!$C$83)) -> 0 | I44: =IF(I$3>Assumptions!$H$15,0,I41*(1-Assumptions!$C$83)) -> 0 | J44: =IF(J$3>Assumptions!$H$15,0,J41*(1-Assumptions!$C$83)) -> 0 | K44: =IF(K$3>Assumptions!$H$15,0,K41*(1-Assumptions!$C$83)) -> 0 | ... M44: =IF(M$3>Assumptions!$H$15,0,M41*(1-Assumptions!$C$83)) -> 0
B45: Promote Distributions | C45: =0 -> 0 | D45: =IF(D$3>Assumptions!$H$15,0,D41*Assumptions!$C$83) -> 0 | E45: =IF(E$3>Assumptions!$H$15,0,E41*Assumptions!$C$83) -> 0 | F45: =IF(F$3>Assumptions!$H$15,0,F41*Assumptions!$C$83) -> 0 | G45: =IF(G$3>Assumptions!$H$15,0,G41*Assumptions!$C$83) -> 0 | H45: =IF(H$3>Assumptions!$H$15,0,H41*Assumptions!$C$83) -> 0 | I45: =IF(I$3>Assumptions!$H$15,0,I41*Assumptions!$C$83) -> 0 | J45: =IF(J$3>Assumptions!$H$15,0,J41*Assumptions!$C$83) -> 0 | K45: =IF(K$3>Assumptions!$H$15,0,K41*Assumptions!$C$83) -> 0 | ... M45: =IF(M$3>Assumptions!$H$15,0,M41*Assumptions!$C$83) -> 0
B46: Investor CF (for IRR) | C46: =-Assumptions!$C$70 -> 0 | D46: =IF(D$3>Assumptions!$H$15,0,D17+D30+D44) -> 0 | E46: =IF(E$3>Assumptions!$H$15,0,E17+E30+E44) -> 0 | F46: =IF(F$3>Assumptions!$H$15,0,F17+F30+F44) -> 0 | G46: =IF(G$3>Assumptions!$H$15,0,G17+G30+G44) -> 0 | H46: =IF(H$3>Assumptions!$H$15,0,H17+H30+H44) -> 0 | I46: =IF(I$3>Assumptions!$H$15,0,I17+I30+I44) -> 0 | J46: =IF(J$3>Assumptions!$H$15,0,J17+J30+J44) -> 0 | K46: =IF(K$3>Assumptions!$H$15,0,K17+K30+K44) -> 0 | ... M46: =IF(M$3>Assumptions!$H$15,0,M17+M30+M44) -> 0
B47: IRR Check | C47: ="" | D47: =IF(D$3=Assumptions!$H$15,IFERROR(IRR($C$46:D46),"—"),"") | E47: =IF(E$3=Assumptions!$H$15,IFERROR(IRR($C$46:E46),"—"),"") | F47: =IF(F$3=Assumptions!$H$15,IFERROR(IRR($C$46:F46),"—"),"") | G47: =IF(G$3=Assumptions!$H$15,IFERROR(IRR($C$46:G46),"—"),"") | H47: =IF(H$3=Assumptions!$H$15,IFERROR(IRR($C$46:H46),"—"),"") | I47: =IF(I$3=Assumptions!$H$15,IFERROR(IRR($C$46:I46),"—"),"") | J47: =IF(J$3=Assumptions!$H$15,IFERROR(IRR($C$46:J46),"—"),"") | K47: =IF(K$3=Assumptions!$H$15,IFERROR(IRR($C$46:K46),"—"),"") | ... M47: =IF(M$3=Assumptions!$H$15,IFERROR(IRR($C$46:M46),"—"),"")
B48: Cash to Next Tier | C48: =0 -> 0 | D48: =IF(D$3>Assumptions!$H$15,0,D34-D41) -> 0 | E48: =IF(E$3>Assumptions!$H$15,0,E34-E41) -> 0 | F48: =IF(F$3>Assumptions!$H$15,0,F34-F41) -> 0 | G48: =IF(G$3>Assumptions!$H$15,0,G34-G41) -> 0 | H48: =IF(H$3>Assumptions!$H$15,0,H34-H41) -> 0 | I48: =IF(I$3>Assumptions!$H$15,0,I34-I41) -> 0 | J48: =IF(J$3>Assumptions!$H$15,0,J34-J41) -> 0 | K48: =IF(K$3>Assumptions!$H$15,0,K34-K41) -> 0 | ... M48: =IF(M$3>Assumptions!$H$15,0,M34-M41) -> 0
B50: ="TIER 4 — RESIDUAL ("&TEXT(Assumptions!$C$84,"0%")&" Promote)" -> TIER 4 — RESIDUAL (0% Promote)
B51: Investor Distributions | C51: =0 -> 0 | D51: =IF(D$3>Assumptions!$H$15,0,D48*(1-Assumptions!$C$84)) -> 0 | E51: =IF(E$3>Assumptions!$H$15,0,E48*(1-Assumptions!$C$84)) -> 0 | F51: =IF(F$3>Assumptions!$H$15,0,F48*(1-Assumptions!$C$84)) -> 0 | G51: =IF(G$3>Assumptions!$H$15,0,G48*(1-Assumptions!$C$84)) -> 0 | H51: =IF(H$3>Assumptions!$H$15,0,H48*(1-Assumptions!$C$84)) -> 0 | I51: =IF(I$3>Assumptions!$H$15,0,I48*(1-Assumptions!$C$84)) -> 0 | J51: =IF(J$3>Assumptions!$H$15,0,J48*(1-Assumptions!$C$84)) -> 0 | K51: =IF(K$3>Assumptions!$H$15,0,K48*(1-Assumptions!$C$84)) -> 0 | ... M51: =IF(M$3>Assumptions!$H$15,0,M48*(1-Assumptions!$C$84)) -> 0
B52: Promote Distributions | C52: =0 -> 0 | D52: =IF(D$3>Assumptions!$H$15,0,D48*Assumptions!$C$84) -> 0 | E52: =IF(E$3>Assumptions!$H$15,0,E48*Assumptions!$C$84) -> 0 | F52: =IF(F$3>Assumptions!$H$15,0,F48*Assumptions!$C$84) -> 0 | G52: =IF(G$3>Assumptions!$H$15,0,G48*Assumptions!$C$84) -> 0 | H52: =IF(H$3>Assumptions!$H$15,0,H48*Assumptions!$C$84) -> 0 | I52: =IF(I$3>Assumptions!$H$15,0,I48*Assumptions!$C$84) -> 0 | J52: =IF(J$3>Assumptions!$H$15,0,J48*Assumptions!$C$84) -> 0 | K52: =IF(K$3>Assumptions!$H$15,0,K48*Assumptions!$C$84) -> 0 | ... M52: =IF(M$3>Assumptions!$H$15,0,M48*Assumptions!$C$84) -> 0
B55: LP CASH FLOW
C56: Year 0 | D56: Year 1 | E56: Year 2 | F56: Year 3 | G56: Year 4 | H56: Year 5 | I56: Year 6 | J56: Year 7 | K56: Year 8 | L56: Year 9 | M56: Year 10
B57: LP Equity Investment | C57: =IF(Assumptions!$C$73="Yes",-Assumptions!$C$70*Assumptions!$C$76,-Assumptions!$C$70) -> 0 | D57: =0 -> 0 | E57: =0 -> 0 | F57: =0 -> 0 | G57: =0 -> 0 | H57: =0 -> 0 | I57: =0 -> 0 | J57: =0 -> 0 | K57: =0 -> 0 | ... M57: =0 -> 0
B58: LP Operating Cash Flow | C58: =0 -> 0 | D58: =IF(D$3>Assumptions!$H$15,0,IF(Assumptions!$C$73="Yes",IF(D$3=Assumptions!$H$15,0,(D17+D30+D44+D51)*Assumptions!$C$76),IF(D$3=Assumptions!$H$15,0,(D17+D30+D44+D51)))) -> 0 | E58: =IF(E$3>Assumptions!$H$15,0,IF(Assumptions!$C$73="Yes",IF(E$3=Assumptions!$H$15,0,(E17+E30+E44+E51)*Assumptions!$C$76),IF(E$3=Assumptions!$H$15,0,(E17+E30+E44+E51)))) -> 0 | F58: =IF(F$3>Assumptions!$H$15,0,IF(Assumptions!$C$73="Yes",IF(F$3=Assumptions!$H$15,0,(F17+F30+F44+F51)*Assumptions!$C$76),IF(F$3=Assumptions!$H$15,0,(F17+F30+F44+F51)))) -> 0 | G58: =IF(G$3>Assumptions!$H$15,0,IF(Assumptions!$C$73="Yes",IF(G$3=Assumptions!$H$15,0,(G17+G30+G44+G51)*Assumptions!$C$76),IF(G$3=Assumptions!$H$15,0,(G17+G30+G44+G51)))) -> 0 | H58: =IF(H$3>Assumptions!$H$15,0,IF(Assumptions!$C$73="Yes",IF(H$3=Assumptions!$H$15,0,(H17+H30+H44+H51)*Assumptions!$C$76),IF(H$3=Assumptions!$H$15,0,(H17+H30+H44+H51)))) -> 0 | I58: =IF(I$3>Assumptions!$H$15,0,IF(Assumptions!$C$73="Yes",IF(I$3=Assumptions!$H$15,0,(I17+I30+I44+I51)*Assumptions!$C$76),IF(I$3=Assumptions!$H$15,0,(I17+I30+I44+I51)))) -> 0 | J58: =IF(J$3>Assumptions!$H$15,0,IF(Assumptions!$C$73="Yes",IF(J$3=Assumptions!$H$15,0,(J17+J30+J44+J51)*Assumptions!$C$76),IF(J$3=Assumptions!$H$15,0,(J17+J30+J44+J51)))) -> 0 | K58: =IF(K$3>Assumptions!$H$15,0,IF(Assumptions!$C$73="Yes",IF(K$3=Assumptions!$H$15,0,(K17+K30+K44+K51)*Assumptions!$C$76),IF(K$3=Assumptions!$H$15,0,(K17+K30+K44+K51)))) -> 0 | ... M58: =IF(M$3>Assumptions!$H$15,0,IF(Assumptions!$C$73="Yes",IF(M$3=Assumptions!$H$15,0,(M17+M30+M44+M51)*Assumptions!$C$76),IF(M$3=Assumptions!$H$15,0,(M17+M30+M44+M51)))) -> 0
B59: LP Sale Proceeds | C59: =0 -> 0 | D59: =IF(D$3>Assumptions!$H$15,0,IF(Assumptions!$C$73="Yes",IF(D$3=Assumptions!$H$15,(D17+D30+D44+D51)*Assumptions!$C$76,0),IF(D$3=Assumptions!$H$15,(D17+D30+D44+D51),0))) -> 0 | E59: =IF(E$3>Assumptions!$H$15,0,IF(Assumptions!$C$73="Yes",IF(E$3=Assumptions!$H$15,(E17+E30+E44+E51)*Assumptions!$C$76,0),IF(E$3=Assumptions!$H$15,(E17+E30+E44+E51),0))) -> 0 | F59: =IF(F$3>Assumptions!$H$15,0,IF(Assumptions!$C$73="Yes",IF(F$3=Assumptions!$H$15,(F17+F30+F44+F51)*Assumptions!$C$76,0),IF(F$3=Assumptions!$H$15,(F17+F30+F44+F51),0))) -> 0 | G59: =IF(G$3>Assumptions!$H$15,0,IF(Assumptions!$C$73="Yes",IF(G$3=Assumptions!$H$15,(G17+G30+G44+G51)*Assumptions!$C$76,0),IF(G$3=Assumptions!$H$15,(G17+G30+G44+G51),0))) -> 0 | H59: =IF(H$3>Assumptions!$H$15,0,IF(Assumptions!$C$73="Yes",IF(H$3=Assumptions!$H$15,(H17+H30+H44+H51)*Assumptions!$C$76,0),IF(H$3=Assumptions!$H$15,(H17+H30+H44+H51),0))) -> 0 | I59: =IF(I$3>Assumptions!$H$15,0,IF(Assumptions!$C$73="Yes",IF(I$3=Assumptions!$H$15,(I17+I30+I44+I51)*Assumptions!$C$76,0),IF(I$3=Assumptions!$H$15,(I17+I30+I44+I51),0))) -> 0 | J59: =IF(J$3>Assumptions!$H$15,0,IF(Assumptions!$C$73="Yes",IF(J$3=Assumptions!$H$15,(J17+J30+J44+J51)*Assumptions!$C$76,0),IF(J$3=Assumptions!$H$15,(J17+J30+J44+J51),0))) -> 0 | K59: =IF(K$3>Assumptions!$H$15,0,IF(Assumptions!$C$73="Yes",IF(K$3=Assumptions!$H$15,(K17+K30+K44+K51)*Assumptions!$C$76,0),IF(K$3=Assumptions!$H$15,(K17+K30+K44+K51),0))) -> 0 | ... M59: =IF(M$3>Assumptions!$H$15,0,IF(Assumptions!$C$73="Yes",IF(M$3=Assumptions!$H$15,(M17+M30+M44+M51)*Assumptions!$C$76,0),IF(M$3=Assumptions!$H$15,(M17+M30+M44+M51),0))) -> 0
B60: Total LP Cash Flow | C60: =C57+C58+C59 -> 0 | D60: =IF(D$3>Assumptions!$H$15,0,D57+D58+D59) -> 0 | E60: =IF(E$3>Assumptions!$H$15,0,E57+E58+E59) -> 0 | F60: =IF(F$3>Assumptions!$H$15,0,F57+F58+F59) -> 0 | G60: =IF(G$3>Assumptions!$H$15,0,G57+G58+G59) -> 0 | H60: =IF(H$3>Assumptions!$H$15,0,H57+H58+H59) -> 0 | I60: =IF(I$3>Assumptions!$H$15,0,I57+I58+I59) -> 0 | J60: =IF(J$3>Assumptions!$H$15,0,J57+J58+J59) -> 0 | K60: =IF(K$3>Assumptions!$H$15,0,K57+K58+K59) -> 0 | ... M60: =IF(M$3>Assumptions!$H$15,0,M57+M58+M59) -> 0
B62: GP CASH FLOW
B63: GP CASH FLOW
C64: Year 0 | D64: Year 1 | E64: Year 2 | F64: Year 3 | G64: Year 4 | H64: Year 5 | I64: Year 6 | J64: Year 7 | K64: Year 8 | L64: Year 9 | M64: Year 10
B65: GP Equity Investment | C65: =IF(Assumptions!$C$73="Yes",-Assumptions!$C$70*Assumptions!$C$75,0) -> 0 | D65: =0 -> 0 | E65: =0 -> 0 | F65: =0 -> 0 | G65: =0 -> 0 | H65: =0 -> 0 | I65: =0 -> 0 | J65: =0 -> 0 | K65: =0 -> 0 | ... M65: =0 -> 0
B66: GP Co-Invest Operating CF | C66: =0 -> 0 | D66: =IF(D$3>Assumptions!$H$15,0,IF(Assumptions!$C$73="Yes",IF(D$3=Assumptions!$H$15,0,(D17+D30+D44+D51)*Assumptions!$C$75),0)) -> 0 | E66: =IF(E$3>Assumptions!$H$15,0,IF(Assumptions!$C$73="Yes",IF(E$3=Assumptions!$H$15,0,(E17+E30+E44+E51)*Assumptions!$C$75),0)) -> 0 | F66: =IF(F$3>Assumptions!$H$15,0,IF(Assumptions!$C$73="Yes",IF(F$3=Assumptions!$H$15,0,(F17+F30+F44+F51)*Assumptions!$C$75),0)) -> 0 | G66: =IF(G$3>Assumptions!$H$15,0,IF(Assumptions!$C$73="Yes",IF(G$3=Assumptions!$H$15,0,(G17+G30+G44+G51)*Assumptions!$C$75),0)) -> 0 | H66: =IF(H$3>Assumptions!$H$15,0,IF(Assumptions!$C$73="Yes",IF(H$3=Assumptions!$H$15,0,(H17+H30+H44+H51)*Assumptions!$C$75),0)) -> 0 | I66: =IF(I$3>Assumptions!$H$15,0,IF(Assumptions!$C$73="Yes",IF(I$3=Assumptions!$H$15,0,(I17+I30+I44+I51)*Assumptions!$C$75),0)) -> 0 | J66: =IF(J$3>Assumptions!$H$15,0,IF(Assumptions!$C$73="Yes",IF(J$3=Assumptions!$H$15,0,(J17+J30+J44+J51)*Assumptions!$C$75),0)) -> 0 | K66: =IF(K$3>Assumptions!$H$15,0,IF(Assumptions!$C$73="Yes",IF(K$3=Assumptions!$H$15,0,(K17+K30+K44+K51)*Assumptions!$C$75),0)) -> 0 | ... M66: =IF(M$3>Assumptions!$H$15,0,IF(Assumptions!$C$73="Yes",IF(M$3=Assumptions!$H$15,0,(M17+M30+M44+M51)*Assumptions!$C$75),0)) -> 0
B67: GP Co-Invest Sale Proceeds | C67: =0 -> 0 | D67: =IF(D$3>Assumptions!$H$15,0,IF(Assumptions!$C$73="Yes",IF(D$3=Assumptions!$H$15,(D17+D30+D44+D51)*Assumptions!$C$75,0),0)) -> 0 | E67: =IF(E$3>Assumptions!$H$15,0,IF(Assumptions!$C$73="Yes",IF(E$3=Assumptions!$H$15,(E17+E30+E44+E51)*Assumptions!$C$75,0),0)) -> 0 | F67: =IF(F$3>Assumptions!$H$15,0,IF(Assumptions!$C$73="Yes",IF(F$3=Assumptions!$H$15,(F17+F30+F44+F51)*Assumptions!$C$75,0),0)) -> 0 | G67: =IF(G$3>Assumptions!$H$15,0,IF(Assumptions!$C$73="Yes",IF(G$3=Assumptions!$H$15,(G17+G30+G44+G51)*Assumptions!$C$75,0),0)) -> 0 | H67: =IF(H$3>Assumptions!$H$15,0,IF(Assumptions!$C$73="Yes",IF(H$3=Assumptions!$H$15,(H17+H30+H44+H51)*Assumptions!$C$75,0),0)) -> 0 | I67: =IF(I$3>Assumptions!$H$15,0,IF(Assumptions!$C$73="Yes",IF(I$3=Assumptions!$H$15,(I17+I30+I44+I51)*Assumptions!$C$75,0),0)) -> 0 | J67: =IF(J$3>Assumptions!$H$15,0,IF(Assumptions!$C$73="Yes",IF(J$3=Assumptions!$H$15,(J17+J30+J44+J51)*Assumptions!$C$75,0),0)) -> 0 | K67: =IF(K$3>Assumptions!$H$15,0,IF(Assumptions!$C$73="Yes",IF(K$3=Assumptions!$H$15,(K17+K30+K44+K51)*Assumptions!$C$75,0),0)) -> 0 | ... M67: =IF(M$3>Assumptions!$H$15,0,IF(Assumptions!$C$73="Yes",IF(M$3=Assumptions!$H$15,(M17+M30+M44+M51)*Assumptions!$C$75,0),0)) -> 0
B68: GP Promote | C68: =0 -> 0 | D68: =IF(D$3>Assumptions!$H$15,0,IF(Assumptions!$C$73="Yes",(D31+D45+D52),0)) -> 0 | E68: =IF(E$3>Assumptions!$H$15,0,IF(Assumptions!$C$73="Yes",(E31+E45+E52),0)) -> 0 | F68: =IF(F$3>Assumptions!$H$15,0,IF(Assumptions!$C$73="Yes",(F31+F45+F52),0)) -> 0 | G68: =IF(G$3>Assumptions!$H$15,0,IF(Assumptions!$C$73="Yes",(G31+G45+G52),0)) -> 0 | H68: =IF(H$3>Assumptions!$H$15,0,IF(Assumptions!$C$73="Yes",(H31+H45+H52),0)) -> 0 | I68: =IF(I$3>Assumptions!$H$15,0,IF(Assumptions!$C$73="Yes",(I31+I45+I52),0)) -> 0 | J68: =IF(J$3>Assumptions!$H$15,0,IF(Assumptions!$C$73="Yes",(J31+J45+J52),0)) -> 0 | K68: =IF(K$3>Assumptions!$H$15,0,IF(Assumptions!$C$73="Yes",(K31+K45+K52),0)) -> 0 | ... M68: =IF(M$3>Assumptions!$H$15,0,IF(Assumptions!$C$73="Yes",(M31+M45+M52),0)) -> 0
B69: Total GP Cash Flow | C69: =C65+C66+C67+C68 -> 0 | D69: =IF(D$3>Assumptions!$H$15,0,D65+D66+D67+D68) -> 0 | E69: =IF(E$3>Assumptions!$H$15,0,E65+E66+E67+E68) -> 0 | F69: =IF(F$3>Assumptions!$H$15,0,F65+F66+F67+F68) -> 0 | G69: =IF(G$3>Assumptions!$H$15,0,G65+G66+G67+G68) -> 0 | H69: =IF(H$3>Assumptions!$H$15,0,H65+H66+H67+H68) -> 0 | I69: =IF(I$3>Assumptions!$H$15,0,I65+I66+I67+I68) -> 0 | J69: =IF(J$3>Assumptions!$H$15,0,J65+J66+J67+J68) -> 0 | K69: =IF(K$3>Assumptions!$H$15,0,K65+K66+K67+K68) -> 0 | ... M69: =IF(M$3>Assumptions!$H$15,0,M65+M66+M67+M68) -> 0
B71: CHECK: LP + GP = Total Distributable | C71: =IF(ABS(C60+C69-(C6+C7))<1,"PASS","FAIL") -> PASS | D71: =IF(D$3>Assumptions!$H$15,"",IF(ABS(D60+D69-D7)<1,"PASS","FAIL")) | E71: =IF(E$3>Assumptions!$H$15,"",IF(ABS(E60+E69-E7)<1,"PASS","FAIL")) | F71: =IF(F$3>Assumptions!$H$15,"",IF(ABS(F60+F69-F7)<1,"PASS","FAIL")) | G71: =IF(G$3>Assumptions!$H$15,"",IF(ABS(G60+G69-G7)<1,"PASS","FAIL")) | H71: =IF(H$3>Assumptions!$H$15,"",IF(ABS(H60+H69-H7)<1,"PASS","FAIL")) | I71: =IF(I$3>Assumptions!$H$15,"",IF(ABS(I60+I69-I7)<1,"PASS","FAIL")) | J71: =IF(J$3>Assumptions!$H$15,"",IF(ABS(J60+J69-J7)<1,"PASS","FAIL")) | K71: =IF(K$3>Assumptions!$H$15,"",IF(ABS(K60+K69-K7)<1,"PASS","FAIL")) | ... M71: =IF(M$3>Assumptions!$H$15,"",IF(ABS(M60+M69-M7)<1,"PASS","FAIL"))
B73: WATERFALL SUMMARY
C74: LP | D74: GP
B75: Equity Invested | C75: =IF(Assumptions!$C$73="Yes",Assumptions!$C$70*Assumptions!$C$76,Assumptions!$C$70) -> 0 | D75: =IF(Assumptions!$C$73="Yes",Assumptions!$C$70*Assumptions!$C$75,0) -> 0
B76: Total Distributions | C76: =SUM(D58:M58)+SUM(D59:M59) -> 0 | D76: =IF(Assumptions!$C$73="Yes",SUM(D66:M66)+SUM(D67:M67)+SUM(D68:M68),0) -> 0
B77: Net Profit | C77: =C76-C75 -> 0 | D77: =IF(Assumptions!$C$73="Yes",(D76-D75),0) -> 0
B79: IRR | C79: =IFERROR(IRR(C60:M60),0) -> 0 | D79: =IF(Assumptions!$C$73="Yes",IFERROR(IRR(C69:M69),0),0) -> 0
B80: Equity Multiple | C80: =IF(C75=0,0,C76/C75) -> 0 | D80: =IF(Assumptions!$C$73="Yes",IF(D75=0,0,D76/D75),0) -> 0
B81: Avg Cash-on-Cash | C81: =IF(OR(C75=0,Assumptions!$H$15=0),0,SUM(D58:M58)/(Assumptions!$H$15*C75)) -> 0 | D81: =IF(Assumptions!$C$73="Yes",IF(OR(D75=0,Assumptions!$H$15=0),0,SUM(D66:M66)/(Assumptions!$H$15*D75)),0) -> 0
B83: PROMOTE BREAKDOWN
C84: Amount | D84: % of Total
B85: =IF(Assumptions!$C$73="Yes","Tier 2 Promote ("&TEXT(Assumptions!$C$81,"0%")&")","") | C85: =IF(Assumptions!$C$73="Yes",SUM(D31:M31),0) -> 0 | D85: =IF(C88=0,0,C85/C88) -> 0
B86: =IF(Assumptions!$C$73="Yes","Tier 3 Promote ("&TEXT(Assumptions!$C$83,"0%")&")","") | C86: =IF(Assumptions!$C$73="Yes",SUM(D45:M45),0) -> 0 | D86: =IF(C88=0,0,C86/C88) -> 0
B87: =IF(Assumptions!$C$73="Yes","Tier 4 Promote ("&TEXT(Assumptions!$C$84,"0%")&")","") | C87: =IF(Assumptions!$C$73="Yes",SUM(D52:M52),0) -> 0 | D87: =IF(C88=0,0,C87/C88) -> 0
B88: Total Promote | C88: =C85+C86+C87 -> 0 | D88: =IF(C88=0,0,1) -> 0
B90: TIER STATUS
C91: Cleared? | D91: IRR at Exit
B92: =IF(Assumptions!$C$73="Yes","Tier 1 — Preferred Return ("&TEXT(Assumptions!$C$79,"0%")&")","") | C92: =IF(Assumptions!$C$73="Yes",IF(CHOOSE(Assumptions!$H$15,C15,D15,E15,F15,G15,H15,I15,J15,K15,L15)<=1,"Yes","No"),"") | D92: =IF(Assumptions!$C$73="Yes",CHOOSE(Assumptions!$H$15,D19,E19,F19,G19,H19,I19,J19,K19,L19,M19),"")
B93: =IF(Assumptions!$C$73="Yes","Tier 2 — First Promote ("&TEXT(Assumptions!$C$80,"0%")&" IRR)","") | C93: =IF(Assumptions!$C$73="Yes",IF(CHOOSE(Assumptions!$H$15,C28,D28,E28,F28,G28,H28,I28,J28,K28,L28)<=1,"Yes","No"),"") | D93: =IF(Assumptions!$C$73="Yes",CHOOSE(Assumptions!$H$15,D33,E33,F33,G33,H33,I33,J33,K33,L33,M33),"")
B94: =IF(Assumptions!$C$73="Yes","Tier 3 — Second Promote ("&TEXT(Assumptions!$C$82,"0%")&" IRR)","") | C94: =IF(Assumptions!$C$73="Yes",IF(CHOOSE(Assumptions!$H$15,C42,D42,E42,F42,G42,H42,I42,J42,K42,L42)<=1,"Yes","No"),"") | D94: =IF(Assumptions!$C$73="Yes",CHOOSE(Assumptions!$H$15,D47,E47,F47,G47,H47,I47,J47,K47,L47,M47),"")
B95: =IF(Assumptions!$C$73="Yes","Tier 4 — Residual ("&TEXT(Assumptions!$C$84,"0%")&")","") | C95: =IF(Assumptions!$C$73="Yes",IF(C87>0,"Active","N/A"),"") | D95: =""

Sheet Sensitivity
B1: Sensitivity Analysis
B2: All values compute automatically — no manual steps required
B4: TABLE 1: Levered IRR — Exit Cap vs. Rent Growth
B5: Exit Cap ↓ Rent Gr → | C5: =Assumptions!$H$16-0.015 -> -0.015 | D5: =Assumptions!$H$16-0.01 -> -0.01 | E5: =Assumptions!$H$16-0.005 -> -0.005 | F5: =Assumptions!$H$16 -> 0 | G5: =Assumptions!$H$16+0.005 -> 0.005 | H5: =Assumptions!$H$16+0.01 -> 0.01
B6: =Assumptions!$C$22-0.005 -> -0.005 | C6: =_SensCalc!N55 -> 0 | D6: =_SensCalc!N3 -> 0 | E6: =_SensCalc!N4 -> 0 | F6: =_SensCalc!N5 -> 0 | G6: =_SensCalc!N6 -> 0 | H6: =_SensCalc!N7 -> 0
B7: =Assumptions!$C$22-0.0025 -> -0.0025 | C7: =_SensCalc!N56 -> 0 | D7: =_SensCalc!N8 -> 0 | E7: =_SensCalc!N9 -> 0 | F7: =_SensCalc!N10 -> 0 | G7: =_SensCalc!N11 -> 0 | H7: =_SensCalc!N12 -> 0
B8: =Assumptions!$C$22 -> 0 | C8: =_SensCalc!N57 -> 0 | D8: =_SensCalc!N13 -> 0 | E8: =_SensCalc!N14 -> 0 | F8: =_SensCalc!N15 -> 0 | G8: =_SensCalc!N16 -> 0 | H8: =_SensCalc!N17 -> 0
B9: =Assumptions!$C$22+0.0025 -> 0.0025 | C9: =_SensCalc!N58 -> 0 | D9: =_SensCalc!N18 -> 0 | E9: =_SensCalc!N19 -> 0 | F9: =_SensCalc!N20 -> 0 | G9: =_SensCalc!N21 -> 0 | H9: =_SensCalc!N22 -> 0
B10: =Assumptions!$C$22+0.005 -> 0.005 | C10: =_SensCalc!N59 -> 0 | D10: =_SensCalc!N23 -> 0 | E10: =_SensCalc!N24 -> 0 | F10: =_SensCalc!N25 -> 0 | G10: =_SensCalc!N26 -> 0 | H10: =_SensCalc!N27 -> 0
B13: TABLE 2: Equity Multiple — Exit Cap vs. Rent Growth
B14: Exit Cap ↓ Rent Gr → | C14: =Assumptions!$H$16-0.015 -> -0.015 | D14: =Assumptions!$H$16-0.01 -> -0.01 | E14: =Assumptions!$H$16-0.005 -> -0.005 | F14: =Assumptions!$H$16 -> 0 | G14: =Assumptions!$H$16+0.005 -> 0.005 | H14: =Assumptions!$H$16+0.01 -> 0.01
B15: =Assumptions!$C$22-0.005 -> -0.005 | C15: =_SensCalc!A55 -> 0 | D15: =_SensCalc!A30 -> 0 | E15: =_SensCalc!A31 -> 0 | F15: =_SensCalc!A32 -> 0 | G15: =_SensCalc!A33 -> 0 | H15: =_SensCalc!A34 -> 0
B16: =Assumptions!$C$22-0.0025 -> -0.0025 | C16: =_SensCalc!A56 -> 0 | D16: =_SensCalc!A35 -> 0 | E16: =_SensCalc!A36 -> 0 | F16: =_SensCalc!A37 -> 0 | G16: =_SensCalc!A38 -> 0 | H16: =_SensCalc!A39 -> 0
B17: =Assumptions!$C$22 -> 0 | C17: =_SensCalc!A57 -> 0 | D17: =_SensCalc!A40 -> 0 | E17: =_SensCalc!A41 -> 0 | F17: =_SensCalc!A42 -> 0 | G17: =_SensCalc!A43 -> 0 | H17: =_SensCalc!A44 -> 0
B18: =Assumptions!$C$22+0.0025 -> 0.0025 | C18: =_SensCalc!A58 -> 0 | D18: =_SensCalc!A45 -> 0 | E18: =_SensCalc!A46 -> 0 | F18: =_SensCalc!A47 -> 0 | G18: =_SensCalc!A48 -> 0 | H18: =_SensCalc!A49 -> 0
B19: =Assumptions!$C$22+0.005 -> 0.005 | C19: =_SensCalc!A59 -> 0 | D19: =_SensCalc!A50 -> 0 | E19: =_SensCalc!A51 -> 0 | F19: =_SensCalc!A52 -> 0 | G19: =_SensCalc!A53 -> 0 | H19: =_SensCalc!A54 -> 0
B22: TABLE 3: Levered IRR — Purchase Price vs. LTV
B23: Price ↓ LTV → | C23: =Assumptions!$C$38-0.15 -> -0.15 | D23: =Assumptions!$C$38-0.1 -> -0.1 | E23: =Assumptions!$C$38-0.05 -> -0.05 | F23: =Assumptions!$C$38 -> 0 | G23: =Assumptions!$C$38+0.05 -> 0.05 | H23: =Assumptions!$C$38+0.1 -> 0.1
B24: =Assumptions!$C$15*(1-0.1) -> 0 | C24: =_SensCalc!N85 -> 0 | D24: =_SensCalc!N60 -> 0 | E24: =_SensCalc!N61 -> 0 | F24: =_SensCalc!N62 -> 0 | G24: =_SensCalc!N63 -> 0 | H24: =_SensCalc!N64 -> 0
B25: =Assumptions!$C$15*(1-0.05) -> 0 | C25: =_SensCalc!N86 -> 0 | D25: =_SensCalc!N65 -> 0 | E25: =_SensCalc!N66 -> 0 | F25: =_SensCalc!N67 -> 0 | G25: =_SensCalc!N68 -> 0 | H25: =_SensCalc!N69 -> 0
B26: =Assumptions!$C$15 -> 0 | C26: =_SensCalc!N87 -> 0 | D26: =_SensCalc!N70 -> 0 | E26: =_SensCalc!N71 -> 0 | F26: =_SensCalc!N72 -> 0 | G26: =_SensCalc!N73 -> 0 | H26: =_SensCalc!N74 -> 0
B27: =Assumptions!$C$15*(1+0.05) -> 0 | C27: =_SensCalc!N88 -> 0 | D27: =_SensCalc!N75 -> 0 | E27: =_SensCalc!N76 -> 0 | F27: =_SensCalc!N77 -> 0 | G27: =_SensCalc!N78 -> 0 | H27: =_SensCalc!N79 -> 0
B28: =Assumptions!$C$15*(1+0.1) -> 0 | C28: =_SensCalc!N89 -> 0 | D28: =_SensCalc!N80 -> 0 | E28: =_SensCalc!N81 -> 0 | F28: =_SensCalc!N82 -> 0 | G28: =_SensCalc!N83 -> 0 | H28: =_SensCalc!N84 -> 0

Sheet Summary
B1: Investment Summary
B2: One-page overview — all values linked to model
B4: PROPERTY | E4: T12 OPERATING
B5: Property Name | C5: =Assumptions!$C$5 -> 0 | E5: Effective Gross Income | F5: =Assumptions!$H$38 -> 0
B6: Location | C6: =Assumptions!$C$7 -> 0 | E6: Total OpEx | F6: =Assumptions!$H$50 -> 0
B7: Property Type | C7: =Assumptions!$C$8 -> 0 | E7: Net Operating Income | F7: =Assumptions!$H$52 -> 0
B8: Units | C8: =Assumptions!$C$9 -> 0 | E8: OpEx Ratio | F8: =Assumptions!$H$60 -> 0
B9: Rentable SF | C9: =Assumptions!$C$10 -> 0 | E9: NOI / Unit | F9: =Assumptions!$H$57 -> 0
B10: Year Built | C10: =Assumptions!$C$11 -> 0
B11: Year Renovated | C11: =Assumptions!$C$12 -> 0
B13: ACQUISITION | E13: CAPITAL STRUCTURE
B14: Purchase Price | C14: =Assumptions!$C$15 -> 0 | E14: Senior Debt | F14: =Assumptions!$C$61 -> 0
B15: Price / Unit | C15: =Assumptions!$C$16 -> 0 | E15: Mezzanine Debt | F15: =Assumptions!$C$62 -> 0
B16: Price / SF | C16: =Assumptions!$C$17 -> 0 | E16: Total Equity | F16: =Assumptions!$C$64 -> 0
B17: Total Basis | C17: =Assumptions!$C$19 -> 0 | E17: Combined LTV | F17: =Assumptions!$C$66 -> 0
B19: FINANCING | E19: HOLD PERIOD & EXIT
B20: Loan Structure | C20: =Assumptions!$C$36 -> Interest Only | E20: Hold Period | F20: =Assumptions!$H$15&" Years" -> Years
B21: Loan Amount | C21: =Assumptions!$C$39 -> 0 | E21: Rent Growth | F21: =Assumptions!$H$16 -> 0
B22: LTV | C22: =Assumptions!$C$38 -> 0 | E22: Expense Growth | F22: =Assumptions!$H$17 -> 0
B23: Interest Rate | C23: =Assumptions!$C$40 -> 0 | E23: Exit Cap Rate | F23: =Assumptions!$C$22 -> 0
B24: IO Period | C24: =IF(Assumptions!$C$37=3,Assumptions!$C$41&" years","N/A") -> N/A | E24: Exit Value | F24: ='Returns Summary'!C$7 -> 0
B25: Amortization | C25: =IF(Assumptions!$C$37=1,"N/A",Assumptions!$C$42&" years") -> N/A | E25: Net Sale Proceeds | F25: ='Returns Summary'!C$11 -> 0
B27: ENTRY METRICS | E27: LEVERED RETURNS
B28: T12 Cap Rate | C28: =Assumptions!$H$5 -> 0 | E28: IRR | F28: ='Returns Summary'!C$21 -> 0
B29: Year 1 Cap Rate | C29: =Assumptions!$H$6 -> 0 | E29: Equity Multiple | F29: ='Returns Summary'!C$22 -> 0
B30: Going-In DSCR | C30: =Assumptions!$C$50 -> 0 | E30: Avg Cash-on-Cash | F30: ='Returns Summary'!C$24 -> 0
B31: Debt Yield | C31: =Assumptions!$C$51 -> 0 | E31: Avg DSCR | F31: ='Returns Summary'!C$26 -> 0
B32: Breakeven Occupancy | C32: =Assumptions!$C$52 -> 0 | E32: Total Profit | F32: ='Returns Summary'!C$23 -> 0
B34: UNLEVERED RETURNS | E34: WATERFALL (if Co-Invest)
B35: IRR | C35: ='Returns Summary'!C$15 -> 0 | E35: LP IRR | F35: =IF(Assumptions!$C$73="Yes",Waterfall!C$79,"N/A") -> N/A
B36: Equity Multiple | C36: ='Returns Summary'!C$16 -> 0 | E36: GP IRR | F36: =IF(Assumptions!$C$73="Yes",Waterfall!D$79,"N/A") -> N/A
B37: Avg Cash-on-Cash | C37: ='Returns Summary'!C$18 -> 0 | E37: GP Promote | F37: =IF(Assumptions!$C$73="Yes",Waterfall!C$88,0) -> 0

Sheet _SensCalc
C2: 0 | D2: =C2+1 -> 1 | E2: =D2+1 -> 2 | F2: =E2+1 -> 3 | G2: =F2+1 -> 4 | H2: =G2+1 -> 5 | I2: =H2+1 -> 6 | J2: =I2+1 -> 7 | K2: =J2+1 -> 8 | ... M2: =L2+1 -> 10
C3: =-Assumptions!$C$70 -> 0 | D3: {=IF(D$2>Assumptions!$H$15,0,(INDEX('Pro Forma'!$D$26:$M$26,D$2)+INDEX('Pro Forma'!$D$9:$M$9,D$2)*(((1+Assumptions!$H$16+$O3)/(1+Assumptions!$H$16))^D$2-1))-IF(Assumptions!$C$37=1,Assumptions!$C$68,IF(Assumptions!$C$37=2,Assumptions!$C$69,IF(D$2<=Assumptions!$C$41,Assumptions!$C$68,Assumptions!$C$69)))-Assumptions!$C$58-IF(Assumptions!$C$28=1,IF(D$2=1,Assumptions!$C$26,0),Assumptions!$C$26/Assumptions!$H$15)-Assumptions!$C$33+IF(D$2=Assumptions!$H$15,(INDEX('Pro Forma'!$D$26:$M$26,Assumptions!$H$15)+INDEX('Pro Forma'!$D$9:$M$9,Assumptions!$H$15)*(((1+Assumptions!$H$16+$O3)/(1+Assumptions!$H$16))^Assumptions!$H$15-1))/IF((Assumptions!$C$22+$P3)=0,1,Assumptions!$C$22+$P3)*(1-Assumptions!$C$23)-INDEX('Debt Schedule'!$C$8:$L$8,Assumptions!$H$15)-INDEX('Debt Schedule'!$C$19:$L$19,Assumptions!$H$15),0))} -> 0 | E3: {=IF(E$2>Assumptions!$H$15,0,(INDEX('Pro Forma'!$D$26:$M$26,E$2)+INDEX('Pro Forma'!$D$9:$M$9,E$2)*(((1+Assumptions!$H$16+$O3)/(1+Assumptions!$H$16))^E$2-1))-IF(Assumptions!$C$37=1,Assumptions!$C$68,IF(Assumptions!$C$37=2,Assumptions!$C$69,IF(E$2<=Assumptions!$C$41,Assumptions!$C$68,Assumptions!$C$69)))-Assumptions!$C$58-IF(Assumptions!$C$28=1,IF(E$2=1,Assumptions!$C$26,0),Assumptions!$C$26/Assumptions!$H$15)-Assumptions!$C$33+IF(E$2=Assumptions!$H$15,(INDEX('Pro Forma'!$D$26:$M$26,Assumptions!$H$15)+INDEX('Pro Forma'!$D$9:$M$9,Assumptions!$H$15)*(((1+Assumptions!$H$16+$O3)/(1+Assumptions!$H$16))^Assumptions!$H$15-1))/IF((Assumptions!$C$22+$P3)=0,1,Assumptions!$C$22+$P3)*(1-Assumptions!$C$23)-INDEX('Debt Schedule'!$C$8:$L$8,Assumptions!$H$15)-INDEX('Debt Schedule'!$C$19:$L$19,Assumptions!$H$15),0))} -> 0 | F3: {=IF(F$2>Assumptions!$H$15,0,(INDEX('Pro Forma'!$D$26:$M$26,F$2)+INDEX('Pro Forma'!$D$9:$M$9,F$2)*(((1+Assumptions!$H$16+$O3)/(1+Assumptions!$H$16))^F$2-1))-IF(Assumptions!$C$37=1,Assumptions!$C$68,IF(Assumptions!$C$37=2,Assumptions!$C$69,IF(F$2<=Assumptions!$C$41,Assumptions!$C$68,Assumptions!$C$69)))-Assumptions!$C$58-IF(Assumptions!$C$28=1,IF(F$2=1,Assumptions!$C$26,0),Assumptions!$C$26/Assumptions!$H$15)-Assumptions!$C$33+IF(F$2=Assumptions!$H$15,(INDEX('Pro Forma'!$D$26:$M$26,Assumptions!$H$15)+INDEX('Pro Forma'!$D$9:$M$9,Assumptions!$H$15)*(((1+Assumptions!$H$16+$O3)/(1+Assumptions!$H$16))^Assumptions!$H$15-1))/IF((Assumptions!$C$22+$P3)=0,1,Assumptions!$C$22+$P3)*(1-Assumptions!$C$23)-INDEX('Debt Schedule'!$C$8:$L$8,Assumptions!$H$15)-INDEX('Debt Schedule'!$C$19:$L$19,Assumptions!$H$15),0))} -> 0 | G3: {=IF(G$2>Assumptions!$H$15,0,(INDEX('Pro Forma'!$D$26:$M$26,G$2)+INDEX('Pro Forma'!$D$9:$M$9,G$2)*(((1+Assumptions!$H$16+$O3)/(1+Assumptions!$H$16))^G$2-1))-IF(Assumptions!$C$37=1,Assumptions!$C$68,IF(Assumptions!$C$37=2,Assumptions!$C$69,IF(G$2<=Assumptions!$C$41,Assumptions!$C$68,Assumptions!$C$69)))-Assumptions!$C$58-IF(Assumptions!$C$28=1,IF(G$2=1,Assumptions!$C$26,0),Assumptions!$C$26/Assumptions!$H$15)-Assumptions!$C$33+IF(G$2=Assumptions!$H$15,(INDEX('Pro Forma'!$D$26:$M$26,Assumptions!$H$15)+INDEX('Pro Forma'!$D$9:$M$9,Assumptions!$H$15)*(((1+Assumptions!$H$16+$O3)/(1+Assumptions!$H$16))^Assumptions!$H$15-1))/IF((Assumptions!$C$22+$P3)=0,1,Assumptions!$C$22+$P3)*(1-Assumptions!$C$23)-INDEX('Debt Schedule'!$C$8:$L$8,Assumptions!$H$15)-INDEX('Debt Schedule'!$C$19:$L$19,Assumptions!$H$15),0))} -> 0 | H3: {=IF(H$2>Assumptions!$H$15,0,(INDEX('Pro Forma'!$D$26:$M$26,H$2)+INDEX('Pro Forma'!$D$9:$M$9,H$2)*(((1+Assumptions!$H$16+$O3)/(1+Assumptions!$H$16))^H$2-1))-IF(Assumptions!$C$37=1,Assumptions!$C$68,IF(Assumptions!$C$37=2,Assumptions!$C$69,IF(H$2<=Assumptions!$C$41,Assumptions!$C$68,Assumptions!$C$69)))-Assumptions!$C$58-IF(Assumptions!$C$28=1,IF(H$2=1,Assumptions!$C$26,0),Assumptions!$C$26/Assumptions!$H$15)-Assumptions!$C$33+IF(H$2=Assumptions!$H$15,(INDEX('Pro Forma'!$D$26:$M$26,Assumptions!$H$15)+INDEX('Pro Forma'!$D$9:$M$9,Assumptions!$H$15)*(((1+Assumptions!$H$16+$O3)/(1+Assumptions!$H$16))^Assumptions!$H$15-1))/IF((Assumptions!$C$22+$P3)=0,1,Assumptions!$C$22+$P3)*(1-Assumptions!$C$23)-INDEX('Debt Schedule'!$C$8:$L$8,Assumptions!$H$15)-INDEX('Debt Schedule'!$C$19:$L$19,Assumptions!$H$15),0))} -> 0 | I3: {=IF(I$2>Assumptions!$H$15,0,(INDEX('Pro Forma'!$D$26:$M$26,I$2)+INDEX('Pro Forma'!$D$9:$M$9,I$2)*(((1+Assumptions!$H$16+$O3)/(1+Assumptions!$H$16))^I$2-1))-IF(Assumptions!$C$37=1,Assumptions!$C$68,IF(Assumptions!$C$37=2,Assumptions!$C$69,IF(I$2<=Assumptions!$C$41,Assumptions!$C$68,Assumptions!$C$69)))-Assumptions!$C$58-IF(Assumptions!$C$28=1,IF(I$2=1,Assumptions!$C$26,0),Assumptions!$C$26/Assumptions!$H$15)-Assumptions!$C$33+IF(I$2=Assumptions!$H$15,(INDEX('Pro Forma'!$D$26:$M$26,Assumptions!$H$15)+INDEX('Pro Forma'!$D$9:$M$9,Assumptions!$H$15)*(((1+Assumptions!$H$16+$O3)/(1+Assumptions!$H$16))^Assumptions!$H$15-1))/IF((Assumptions!$C$22+$P3)=0,1,Assumptions!$C$22+$P3)*(1-Assumptions!$C$23)-INDEX('Debt Schedule'!$C$8:$L$8,Assumptions!$H$15)-INDEX('Debt Schedule'!$C$19:$L$19,Assumptions!$H$15),0))} -> 0 | J3: {=IF(J$2>Assumptions!$H$15,0,(INDEX('Pro Forma'!$D$26:$M$26,J$2)+INDEX('Pro Forma'!$D$9:$M$9,J$2)*(((1+Assumptions!$H$16+$O3)/(1+Assumptions!$H$16))^J$2-1))-IF(Assumptions!$C$37=1,Assumptions!$C$68,IF(Assumptions!$C$37=2,Assumptions!$C$69,IF(J$2<=Assumptions!$C$41,Assumptions!$C$68,Assumptions!$C$69)))-Assumptions!$C$58-IF(Assumptions!$C$28=1,IF(J$2=1,Assumptions!$C$26,0),Assumptions!$C$26/Assumptions!$H$15)-Assumptions!$C$33+IF(J$2=Assumptions!$H$15,(INDEX('Pro Forma'!$D$26:$M$26,Assumptions!$H$15)+INDEX('Pro Forma'!$D$9:$M$9,Assumptions!$H$15)*(((1+Assumptions!$H$16+$O3)/(1+Assumptions!$H$16))^Assumptions!$H$15-1))/IF((Assumptions!$C$22+$P3)=0,1,Assumptions!$C$22+$P3)*(1-Assumptions!$C$23)-INDEX('Debt Schedule'!$C$8:$L$8,Assumptions!$H$15)-INDEX('Debt Schedule'!$C$19:$L$19,Assumptions!$H$15),0))} -> 0 | K3: {=IF(K$2>Assumptions!$H$15,0,(INDEX('Pro Forma'!$D$26:$M$26,K$2)+INDEX('Pro Forma'!$D$9:$M$9,K$2)*(((1+Assumptions!$H$16+$O3)/(1+Assumptions!$H$16))^K$2-1))-IF(Assumptions!$C$37=1,Assumptions!$C$68,IF(Assumptions!$C$37=2,Assumptions!$C$69,IF(K$2<=Assumptions!$C$41,Assumptions!$C$68,Assumptions!$C$69)))-Assumptions!$C$58-IF(Assumptions!$C$28=1,IF(K$2=1,Assumptions!$C$26,0),Assumptions!$C$26/Assumptions!$H$15)-Assumptions!$C$33+IF(K$2=Assumptions!$H$15,(INDEX('Pro Forma'!$D$26:$M$26,Assumptions!$H$15)+INDEX('Pro Forma'!$D$9:$M$9,Assumptions!$H$15)*(((1+Assumptions!$H$16+$O3)/(1+Assumptions!$H$16))^Assumptions!$H$15-1))/IF((Assumptions!$C$22+$P3)=0,1,Assumptions!$C$22+$P3)*(1-Assumptions!$C$23)-INDEX('Debt Schedule'!$C$8:$L$8,Assumptions!$H$15)-INDEX('Debt Schedule'!$C$19:$L$19,Assumptions!$H$15),0))} -> 0 | ... M3: {=IF(M$2>Assumptions!$H$15,0,(INDEX('Pro Forma'!$D$26:$M$26,M$2)+INDEX('Pro Forma'!$D$9:$M$9,M$2)*(((1+Assumptions!$H$16+$O3)/(1+Assumptions!$H$16))^M$2-1))-IF(Assumptions!$C$37=1,Assumptions!$C$68,IF(Assumptions!$C$37=2,Assumptions!$C$69,IF(M$2<=Assumptions!$C$41,Assumptions!$C$68,Assumptions!$C$69)))-Assumptions!$C$58-IF(Assumptions!$C$28=1,IF(M$2=1,Assumptions!$C$26,0),Assumptions!$C$26/Assumptions!$H$15)-Assumptions!$C$33+IF(M$2=Assumptions!$H$15,(INDEX('Pro Forma'!$D$26:$M$26,Assumptions!$H$15)+INDEX('Pro Forma'!$D$9:$M$9,Assumptions!$H$15)*(((1+Assumptions!$H$16+$O3)/(1+Assumptions!$H$16))^Assumptions!$H$15-1))/IF((Assumptions!$C$22+$P3)=0,1,Assumptions!$C$22+$P3)*(1-Assumptions!$C$23)-INDEX('Debt Schedule'!$C$8:$L$8,Assumptions!$H$15)-INDEX('Debt Schedule'!$C$19:$L$19,Assumptions!$H$15),0))} -> 0 | N3: =IFERROR(IRR(C3:M3),0) -> 0 | O3: =(MOD(ROW()-3,5)-2)*0.005 -> -0.01 | P3: =(INT((ROW()-3)/5)-2)*0.0025 -> -0.005
C4: =-Assumptions!$C$70 -> 0 | D4: {=IF(D$2>Assumptions!$H$15,0,(INDEX('Pro Forma'!$D$26:$M$26,D$2)+INDEX('Pro Forma'!$D$9:$M$9,D$2)*(((1+Assumptions!$H$16+$O4)/(1+Assumptions!$H$16))^D$2-1))-IF(Assumptions!$C$37=1,Assumptions!$C$68,IF(Assumptions!$C$37=2,Assumptions!$C$69,IF(D$2<=Assumptions!$C$41,Assumptions!$C$68,Assumptions!$C$69)))-Assumptions!$C$58-IF(Assumptions!$C$28=1,IF(D$2=1,Assumptions!$C$26,0),Assumptions!$C$26/Assumptions!$H$15)-Assumptions!$C$33+IF(D$2=Assumptions!$H$15,(INDEX('Pro Forma'!$D$26:$M$26,Assumptions!$H$15)+INDEX('Pro Forma'!$D$9:$M$9,Assumptions!$H$15)*(((1+Assumptions!$H$16+$O4)/(1+Assumptions!$H$16))^Assumptions!$H$15-1))/IF((Assumptions!$C$22+$P4)=0,1,Assumptions!$C$22+$P4)*(1-Assumptions!$C$23)-INDEX('Debt Schedule'!$C$8:$L$8,Assumptions!$H$15)-INDEX('Debt Schedule'!$C$19:$L$19,Assumptions!$H$15),0))} -> 0 | E4: {=IF(E$2>Assumptions!$H$15,0,(INDEX('Pro Forma'!$D$26:$M$26,E$2)+INDEX('Pro Forma'!$D$9:$M$9,E$2)*(((1+Assumptions!$H$16+$O4)/(1+Assumptions!$H$16))^E$2-1))-IF(Assumptions!$C$37=1,Assumptions!$C$68,IF(Assumptions!$C$37=2,Assumptions!$C$69,IF(E$2<=Assumptions!$C$41,Assumptions!$C$68,Assumptions!$C$69)))-Assumptions!$C$58-IF(Assumptions!$C$28=1,IF(E$2=1,Assumptions!$C$26,0),Assumptions!$C$26/Assumptions!$H$15)-Assumptions!$C$33+IF(E$2=Assumptions!$H$15,(INDEX('Pro Forma'!$D$26:$M$26,Assumptions!$H$15)+INDEX('Pro Forma'!$D$9:$M$9,Assumptions!$H$15)*(((1+Assumptions!$H$16+$O4)/(1+Assumptions!$H$16))^Assumptions!$H$15-1))/IF((Assumptions!$C$22+$P4)=0,1,Assumptions!$C$22+$P4)*(1-Assumptions!$C$23)-INDEX('Debt Schedule'!$C$8:$L$8,Assumptions!$H$15)-INDEX('Debt Schedule'!$C$19:$L$19,Assumptions!$H$15),0))} -> 0 | F4: {=IF(F$2>Assumptions!$H$15,0,(INDEX('Pro Forma'!$D$26:$M$26,F$2)+INDEX('Pro Forma'!$D$9:$M$9,F$2)*(((1+Assumptions!$H$16+$O4)/(1+Assumptions!$H$16))^F$2-1))-IF(Assumptions!$C$37=1,Assumptions!$C$68,IF(Assumptions!$C$37=2,Assumptions!$C$69,IF(F$2<=Assumptions!$C$41,Assumptions!$C$68,Assumptions!$C$69)))-Assumptions!$C$58-IF(Assumptions!$C$28=1,IF(F$2=1,Assumptions!$C$26,0),Assumptions!$C$26/Assumptions!$H$15)-Assumptions!$C$33+IF(F$2=Assumptions!$H$15,(INDEX('Pro Forma'!$D$26:$M$26,Assumptions!$H$15)+INDEX('Pro Forma'!$D$9:$M$9,Assumptions!$H$15)*(((1+Assumptions!$H$16+$O4)/(1+Assumptions!$H$16))^Assumptions!$H$15-1))/IF((Assumptions!$C$22+$P4)=0,1,Assumptions!$C$22+$P4)*(1-Assumptions!$C$23)-INDEX('Debt Schedule'!$C$8:$L$8,Assumptions!$H$15)-INDEX('Debt Schedule'!$C$19:$L$19,Assumptions!$H$15),0))} -> 0 | G4: {=IF(G$2>Assumptions!$H$15,0,(INDEX('Pro Forma'!$D$26:$M$26,G$2)+INDEX('Pro Forma'!$D$9:$M$9,G$2)*(((1+Assumptions!$H$16+$O4)/(1+Assumptions!$H$16))^G$2-1))-IF(Assumptions!$C$37=1,Assumptions!$C$68,IF(Assumptions!$C$37=2,Assumptions!$C$69,IF(G$2<=Assumptions!$C$41,Assumptions!$C$68,Assumptions!$C$69)))-Assumptions!$C$58-IF(Assumptions!$C$28=1,IF(G$2=1,Assumptions!$C$26,0),Assumptions!$C$26/Assumptions!$H$15)-Assumptions!$C$33+IF(G$2=Assumptions!$H$15,(INDEX('Pro Forma'!$D$26:$M$26,Assumptions!$H$15)+INDEX('Pro Forma'!$D$9:$M$9,Assumptions!$H$15)*(((1+Assumptions!$H$16+$O4)/(1+Assumptions!$H$16))^Assumptions!$H$15-1))/IF((Assumptions!$C$22+$P4)=0,1,Assumptions!$C$22+$P4)*(1-Assumptions!$C$23)-INDEX('Debt Schedule'!$C$8:$L$8,Assumptions!$H$15)-INDEX('Debt Schedule'!$C$19:$L$19,Assumptions!$H$15),0))} -> 0 | H4: {=IF(H$2>Assumptions!$H$15,0,(INDEX('Pro Forma'!$D$26:$M$26,H$2)+INDEX('Pro Forma'!$D$9:$M$9,H$2)*(((1+Assumptions!$H$16+$O4)/(1+Assumptions!$H$16))^H$2-1))-IF(Assumptions!$C$37=1,Assumptions!$C$68,IF(Assumptions!$C$37=2,Assumptions!$C$69,IF(H$2<=Assumptions!$C$41,Assumptions!$C$68,Assumptions!$C$69)))-Assumptions!$C$58-IF(Assumptions!$C$28=1,IF(H$2=1,Assumptions!$C$26,0),Assumptions!$C$26/Assumptions!$H$15)-Assumptions!$C$33+IF(H$2=Assumptions!$H$15,(INDEX('Pro Forma'!$D$26:$M$26,Assumptions!$H$15)+INDEX('Pro Forma'!$D$9:$M$9,Assumptions!$H$15)*(((1+Assumptions!$H$16+$O4)/(1+Assumptions!$H$16))^Assumptions!$H$15-1))/IF((Assumptions!$C$22+$P4)=0,1,Assumptions!$C$22+$P4)*(1-Assumptions!$C$23)-INDEX('Debt Schedule'!$C$8:$L$8,Assumptions!$H$15)-INDEX('Debt Schedule'!$C$19:$L$19,Assumptions!$H$15),0))} -> 0 | I4: {=IF(I$2>Assumptions!$H$15,0,(INDEX('Pro Forma'!$D$26:$M$26,I$2)+INDEX('Pro Forma'!$D$9:$M$9,I$2)*(((1+Assumptions!$H$16+$O4)/(1+Assumptions!$H$16))^I$2-1))-IF(Assumptions!$C$37=1,Assumptions!$C$68,IF(Assumptions!$C$37=2,Assumptions!$C$69,IF(I$2<=Assumptions!$C$41,Assumptions!$C$68,Assumptions!$C$69)))-Assumptions!$C$58-IF(Assumptions!$C$28=1,IF(I$2=1,Assumptions!$C$26,0),Assumptions!$C$26/Assumptions!$H$15)-Assumptions!$C$33+IF(I$2=Assumptions!$H$15,(INDEX('Pro Forma'!$D$26:$M$26,Assumptions!$H$15)+INDEX('Pro Forma'!$D$9:$M$9,Assumptions!$H$15)*(((1+Assumptions!$H$16+$O4)/(1+Assumptions!$H$16))^Assumptions!$H$15-1))/IF((Assumptions!$C$22+$P4)=0,1,Assumptions!$C$22+$P4)*(1-Assumptions!$C$23)-INDEX('Debt Schedule'!$C$8:$L$8,Assumptions!$H$15)-INDEX('Debt Schedule'!$C$19:$L$19,Assumptions!$H$15),0))} -> 0 | J4: {=IF(J$2>Assumptions!$H$15,0,(INDEX('Pro Forma'!$D$26:$M$26,J$2)+INDEX('Pro Forma'!$D$9:$M$9,J$2)*(((1+Assumptions!$H$16+$O4)/(1+Assumptions!$H$16))^J$2-1))-IF(Assumptions!$C$37=1,Assumptions!$C$68,IF(Assumptions!$C$37=2,Assumptions!$C$69,IF(J$2<=Assumptions!$C$41,Assumptions!$C$68,Assumptions!$C$69)))-Assumptions!$C$58-IF(Assumptions!$C$28=1,IF(J$2=1,Assumptions!$C$26,0),Assumptions!$C$26/Assumptions!$H$15)-Assumptions!$C$33+IF(J$2=Assumptions!$H$15,(INDEX('Pro Forma'!$D$26:$M$26,Assumptions!$H$15)+INDEX('Pro Forma'!$D$9:$M$9,Assumptions!$H$15)*(((1+Assumptions!$H$16+$O4)/(1+Assumptions!$H$16))^Assumptions!$H$15-1))/IF((Assumptions!$C$22+$P4)=0,1,Assumptions!$C$22+$P4)*(1-Assumptions!$C$23)-INDEX('Debt Schedule'!$C$8:$L$8,Assumptions!$H$15)-INDEX('Debt Schedule'!$C$19:$L$19,Assumptions!$H$15),0))} -> 0 | K4: {=IF(K$2>Assumptions!$H$15,0,(INDEX('Pro Forma'!$D$26:$M$26,K$2)+INDEX('Pro Forma'!$D$9:$M$9,K$2)*(((1+Assumptions!$H$16+$O4)/(1+Assumptions!$H$16))^K$2-1))-IF(Assumptions!$C$37=1,Assumptions!$C$68,IF(Assumptions!$C$37=2,Assumptions!$C$69,IF(K$2<=Assumptions!$C$41,Assumptions!$C$68,Assumptions!$C$69)))-Assumptions!$C$58-IF(Assumptions!$C$28=1,IF(K$2=1,Assumptions!$C$26,0),Assumptions!$C$26/Assumptions!$H$15)-Assumptions!$C$33+IF(K$2=Assumptions!$H$15,(INDEX('Pro Forma'!$D$26:$M$26,Assumptions!$H$15)+INDEX('Pro Forma'!$D$9:$M$9,Assumptions!$H$15)*(((1+Assumptions!$H$16+$O4)/(1+Assumptions!$H$16))^Assumptions!$H$15-1))/IF((Assumptions!$C$22+$P4)=0,1,Assumptions!$C$22+$P4)*(1-Assumptions!$C$23)-INDEX('Debt Schedule'!$C$8:$L$8,Assumptions!$H$15)-INDEX('Debt Schedule'!$C$19:$L$19,Assumptions!$H$15),0))} -> 0 | ... M4: {=IF(M$2>Assumptions!$H$15,0,(INDEX('Pro Forma'!$D$26:$M$26,M$2)+INDEX('Pro Forma'!$D$9:$M$9,M$2)*(((1+Assumptions!$H$16+$O4)/(1+Assumptions!$H$16))^M$2-1))-IF(Assumptions!$C$37=1,Assumptions!$C$68,IF(Assumptions!$C$37=2,Assumptions!$C$69,IF(M$2<=Assumptions!$C$41,Assumptions!$C$68,Assumptions!$C$69)))-Assumptions!$C$58-IF(Assumptions!$C$28=1,IF(M$2=1,Assumptions!$C$26,0),Assumptions!$C$26/Assumptions!$H$15)-Assumptions!$C$33+IF(M$2=Assumptions!$H$15,(INDEX('Pro Forma'!$D$26:$M$26,Assumptions!$H$15)+INDEX('Pro Forma'!$D$9:$M$9,Assumptions!$H$15)*(((1+Assumptions!$H$16+$O4)/(1+Assumptions!$H$16))^Assumptions!$H$15-1))/IF((Assumptions!$C$22+$P4)=0,1,Assumptions!$C$22+$P4)*(1-Assumptions!$C$23)-INDEX('Debt Schedule'!$C$8:$L$8,Assumptions!$H$15)-INDEX('Debt Schedule'!$C$19:$L$19,Assumptions!$H$15),0))} -> 0 | N4: =IFERROR(IRR(C4:M4),0) -> 0 | O4: =(MOD(ROW()-3,5)-2)*0.005 -> -0.005 | P4: =(INT((ROW()-3)/5)-2)*0.0025 -> -0.005
C5: =-Assumptions!$C$70 -> 0 | D5: {=IF(D$2>Assumptions!$H$15,0,(INDEX('Pro Forma'!$D$26:$M$26,D$2)+INDEX('Pro Forma'!$D$9:$M$9,D$2)*(((1+Assumptions!$H$16+$O5)/(1+Assumptions!$H$16))^D$2-1))-IF(Assumptions!$C$37=1,Assumptions!$C$68,IF(Assumptions!$C$37=2,Assumptions!$C$69,IF(D$2<=Assumptions!$C$41,Assumptions!$C$68,Assumptions!$C$69)))-Assumptions!$C$58-IF(Assumptions!$C$28=1,IF(D$2=1,Assumptions!$C$26,0),Assumptions!$C$26/Assumptions!$H$15)-Assumptions!$C$33+IF(D$2=Assumptions!$H$15,(INDEX('Pro Forma'!$D$26:$M$26,Assumptions!$H$15)+INDEX('Pro Forma'!$D$9:$M$9,Assumptions!$H$15)*(((1+Assumptions!$H$16+$O5)/(1+Assumptions!$H$16))^Assumptions!$H$15-1))/IF((Assumptions!$C$22+$P5)=0,1,Assumptions!$C$22+$P5)*(1-Assumptions!$C$23)-INDEX('Debt Schedule'!$C$8:$L$8,Assumptions!$H$15)-INDEX('Debt Schedule'!$C$19:$L$19,Assumptions!$H$15),0))} -> 0 | E5: {=IF(E$2>Assumptions!$H$15,0,(INDEX('Pro Forma'!$D$26:$M$26,E$2)+INDEX('Pro Forma'!$D$9:$M$9,E$2)*(((1+Assumptions!$H$16+$O5)/(1+Assumptions!$H$16))^E$2-1))-IF(Assumptions!$C$37=1,Assumptions!$C$68,IF(Assumptions!$C$37=2,Assumptions!$C$69,IF(E$2<=Assumptions!$C$41,Assumptions!$C$68,Assumptions!$C$69)))-Assumptions!$C$58-IF(Assumptions!$C$28=1,IF(E$2=1,Assumptions!$C$26,0),Assumptions!$C$26/Assumptions!$H$15)-Assumptions!$C$33+IF(E$2=Assumptions!$H$15,(INDEX('Pro Forma'!$D$26:$M$26,Assumptions!$H$15)+INDEX('Pro Forma'!$D$9:$M$9,Assumptions!$H$15)*(((1+Assumptions!$H$16+$O5)/(1+Assumptions!$H$16))^Assumptions!$H$15-1))/IF((Assumptions!$C$22+$P5)=0,1,Assumptions!$C$22+$P5)*(1-Assumptions!$C$23)-INDEX('Debt Schedule'!$C$8:$L$8,Assumptions!$H$15)-INDEX('Debt Schedule'!$C$19:$L$19,Assumptions!$H$15),0))} -> 0 | F5: {=IF(F$2>Assumptions!$H$15,0,(INDEX('Pro Forma'!$D$26:$M$26,F$2)+INDEX('Pro Forma'!$D$9:$M$9,F$2)*(((1+Assumptions!$H$16+$O5)/(1+Assumptions!$H$16))^F$2-1))-IF(Assumptions!$C$37=1,Assumptions!$C$68,IF(Assumptions!$C$37=2,Assumptions!$C$69,IF(F$2<=Assumptions!$C$41,Assumptions!$C$68,Assumptions!$C$69)))-Assumptions!$C$58-IF(Assumptions!$C$28=1,IF(F$2=1,Assumptions!$C$26,0),Assumptions!$C$26/Assumptions!$H$15)-Assumptions!$C$33+IF(F$2=Assumptions!$H$15,(INDEX('Pro Forma'!$D$26:$M$26,Assumptions!$H$15)+INDEX('Pro Forma'!$D$9:$M$9,Assumptions!$H$15)*(((1+Assumptions!$H$16+$O5)/(1+Assumptions!$H$16))^Assumptions!$H$15-1))/IF((Assumptions!$C$22+$P5)=0,1,Assumptions!$C$22+$P5)*(1-Assumptions!$C$23)-INDEX('Debt Schedule'!$C$8:$L$8,Assumptions!$H$15)-INDEX('Debt Schedule'!$C$19:$L$19,Assumptions!$H$15),0))} -> 0 | G5: {=IF(G$2>Assumptions!$H$15,0,(INDEX('Pro Forma'!$D$26:$M$26,G$2)+INDEX('Pro Forma'!$D$9:$M$9,G$2)*(((1+Assumptions!$H$16+$O5)/(1+Assumptions!$H$16))^G$2-1))-IF(Assumptions!$C$37=1,Assumptions!$C$68,IF(Assumptions!$C$37=2,Assumptions!$C$69,IF(G$2<=Assumptions!$C$41,Assumptions!$C$68,Assumptions!$C$69)))-Assumptions!$C$58-IF(Assumptions!$C$28=1,IF(G$2=1,Assumptions!$C$26,0),Assumptions!$C$26/Assumptions!$H$15)-Assumptions!$C$33+IF(G$2=Assumptions!$H$15,(INDEX('Pro Forma'!$D$26:$M$26,Assumptions!$H$15)+INDEX('Pro Forma'!$D$9:$M$9,Assumptions!$H$15)*(((1+Assumptions!$H$16+$O5)/(1+Assumptions!$H$16))^Assumptions!$H$15-1))/IF((Assumptions!$C$22+$P5)=0,1,Assumptions!$C$22+$P5)*(1-Assumptions!$C$23)-INDEX('Debt Schedule'!$C$8:$L$8,Assumptions!$H$15)-INDEX('Debt Schedule'!$C$19:$L$19,Assumptions!$H$15),0))} -> 0 | H5: {=IF(H$2>Assumptions!$H$15,0,(INDEX('Pro Forma'!$D$26:$M$26,H$2)+INDEX('Pro Forma'!$D$9:$M$9,H$2)*(((1+Assumptions!$H$16+$O5)/(1+Assumptions!$H$16))^H$2-1))-IF(Assumptions!$C$37=1,Assumptions!$C$68,IF(Assumptions!$C$37=2,Assumptions!$C$69,IF(H$2<=Assumptions!$C$41,Assumptions!$C$68,Assumptions!$C$69)))-Assumptions!$C$58-IF(Assumptions!$C$28=1,IF(H$2=1,Assumptions!$C$26,0),Assumptions!$C$26/Assumptions!$H$15)-Assumptions!$C$33+IF(H$2=Assumptions!$H$15,(INDEX('Pro Forma'!$D$26:$M$26,Assumptions!$H$15)+INDEX('Pro Forma'!$D$9:$M$9,Assumptions!$H$15)*(((1+Assumptions!$H$16+$O5)/(1+Assumptions!$H$16))^Assumptions!$H$15-1))/IF((Assumptions!$C$22+$P5)=0,1,Assumptions!$C$22+$P5)*(1-Assumptions!$C$23)-INDEX('Debt Schedule'!$C$8:$L$8,Assumptions!$H$15)-INDEX('Debt Schedule'!$C$19:$L$19,Assumptions!$H$15),0))} -> 0 | I5: {=IF(I$2>Assumptions!$H$15,0,(INDEX('Pro Forma'!$D$26:$M$26,I$2)+INDEX('Pro Forma'!$D$9:$M$9,I$2)*(((1+Assumptions!$H$16+$O5)/(1+Assumptions!$H$16))^I$2-1))-IF(Assumptions!$C$37=1,Assumptions!$C$68,IF(Assumptions!$C$37=2,Assumptions!$C$69,IF(I$2<=Assumptions!$C$41,Assumptions!$C$68,Assumptions!$C$69)))-Assumptions!$C$58-IF(Assumptions!$C$28=1,IF(I$2=1,Assumptions!$C$26,0),Assumptions!$C$26/Assumptions!$H$15)-Assumptions!$C$33+IF(I$2=Assumptions!$H$15,(INDEX('Pro Forma'!$D$26:$M$26,Assumptions!$H$15)+INDEX('Pro Forma'!$D$9:$M$9,Assumptions!$H$15)*(((1+Assumptions!$H$16+$O5)/(1+Assumptions!$H$16))^Assumptions!$H$15-1))/IF((Assumptions!$C$22+$P5)=0,1,Assumptions!$C$22+$P5)*(1-Assumptions!$C$23)-INDEX('Debt Schedule'!$C$8:$L$8,Assumptions!$H$15)-INDEX('Debt Schedule'!$C$19:$L$19,Assumptions!$H$15),0))} -> 0 | J5: {=IF(J$2>Assumptions!$H$15,0,(INDEX('Pro Forma'!$D$26:$M$26,J$2)+INDEX('Pro Forma'!$D$9:$M$9,J$2)*(((1+Assumptions!$H$16+$O5)/(1+Assumptions!$H$16))^J$2-1))-IF(Assumptions!$C$37=1,Assumptions!$C$68,IF(Assumptions!$C$37=2,Assumptions!$C$69,IF(J$2<=Assumptions!$C$41,Assumptions!$C$68,Assumptions!$C$69)))-Assumptions!$C$58-IF(Assumptions!$C$28=1,IF(J$2=1,Assumptions!$C$26,0),Assumptions!$C$26/Assumptions!$H$15)-Assumptions!$C$33+IF(J$2=Assumptions!$H$15,(INDEX('Pro Forma'!$D$26:$M$26,Assumptions!$H$15)+INDEX('Pro Forma'!$D$9:$M$9,Assumptions!$H$15)*(((1+Assumptions!$H$16+$O5)/(1+Assumptions!$H$16))^Assumptions!$H$15-1))/IF((Assumptions!$C$22+$P5)=0,1,Assumptions!$C$22+$P5)*(1-Assumptions!$C$23)-INDEX('Debt Schedule'!$C$8:$L$8,Assumptions!$H$15)-INDEX('Debt Schedule'!$C$19:$L$19,Assumptions!$H$15),0))} -> 0 | K5: {=IF(K$2>Assumptions!$H$15,0,(INDEX('Pro Forma'!$D$26:$M$26,K$2)+INDEX('Pro Forma'!$D$9:$M$9,K$2)*(((1+Assumptions!$H$16+$O5)/(1+Assumptions!$H$16))^K$2-1))-IF(Assumptions!$C$37=1,Assumptions!$C$68,IF(Assumptions!$C$37=2,Assumptions!$C$69,IF(K$2<=Assumptions!$C$41,Assumptions!$C$68,Assumptions!$C$69)))-Assumptions!$C$58-IF(Assumptions!$C$28=1,IF(K$2=1,Assumptions!$C$26,0),Assumptions!$C$26/Assumptions!$H$15)-Assumptions!$C$33+IF(K$2=Assumptions!$H$15,(INDEX('Pro Forma'!$D$26:$M$26,Assumptions!$H$15)+INDEX('Pro Forma'!$D$9:$M$9,Assumptions!$H$15)*(((1+Assumptions!$H$16+$O5)/(1+Assumptions!$H$16))^Assumptions!$H$15-1))/IF((Assumptions!$C$22+$P5)=0,1,Assumptions!$C$22+$P5)*(1-Assumptions!$C$23)-INDEX('Debt Schedule'!$C$8:$L$8,Assumptions!$H$15)-INDEX('Debt Schedule'!$C$19:$L$19,Assumptions!$H$15),0))} -> 0 | ... M5: {=IF(M$2>Assumptions!$H$15,0,(INDEX('Pro Forma'!$D$26:$M$26,M$2)+INDEX('Pro Forma'!$D$9:$M$9,M$2)*(((1+Assumptions!$H$16+$O5)/(1+Assumptions!$H$16))^M$2-1))-IF(Assumptions!$C$37=1,Assumptions!$C$68,IF(Assumptions!$C$37=2,Assumptions!$C$69,IF(M$2<=Assumptions!$C$41,Assumptions!$C$68,Assumptions!$C$69)))-Assumptions!$C$58-IF(Assumptions!$C$28=1,IF(M$2=1,Assumptions!$C$26,0),Assumptions!$C$26/Assumptions!$H$15)-Assumptions!$C$33+IF(M$2=Assumptions!$H$15,(INDEX('Pro Forma'!$D$26:$M$26,Assumptions!$H$15)+INDEX('Pro Forma'!$D$9:$M$9,Assumptions!$H$15)*(((1+Assumptions!$H$16+$O5)/(1+Assumptions!$H$16))^Assumptions!$H$15-1))/IF((Assumptions!$C$22+$P5)=0,1,Assumptions!$C$22+$P5)*(1-Assumptions!$C$23)-INDEX('Debt Schedule'!$C$8:$L$8,Assumptions!$H$15)-INDEX('Debt Schedule'!$C$19:$L$19,Assumptions!$H$15),0))} -> 0 | N5: =IFERROR(IRR(C5:M5),0) -> 0 | O5: =(MOD(ROW()-3,5)-2)*0.005 -> 0 | P5: =(INT((ROW()-3)/5)-2)*0.0025 -> -0.005
C6: =-Assumptions!$C$70 -> 0 | D6: {=IF(D$2>Assumptions!$H$15,0,(INDEX('Pro Forma'!$D$26:$M$26,D$2)+INDEX('Pro Forma'!$D$9:$M$9,D$2)*(((1+Assumptions!$H$16+$O6)/(1+Assumptions!$H$16))^D$2-1))-IF(Assumptions!$C$37=1,Assumptions!$C$68,IF(Assumptions!$C$37=2,Assumptions!$C$69,IF(D$2<=Assumptions!$C$41,Assumptions!$C$68,Assumptions!$C$69)))-Assumptions!$C$58-IF(Assumptions!$C$28=1,IF(D$2=1,Assumptions!$C$26,0),Assumptions!$C$26/Assumptions!$H$15)-Assumptions!$C$33+IF(D$2=Assumptions!$H$15,(INDEX('Pro Forma'!$D$26:$M$26,Assumptions!$H$15)+INDEX('Pro Forma'!$D$9:$M$9,Assumptions!$H$15)*(((1+Assumptions!$H$16+$O6)/(1+Assumptions!$H$16))^Assumptions!$H$15-1))/IF((Assumptions!$C$22+$P6)=0,1,Assumptions!$C$22+$P6)*(1-Assumptions!$C$23)-INDEX('Debt Schedule'!$C$8:$L$8,Assumptions!$H$15)-INDEX('Debt Schedule'!$C$19:$L$19,Assumptions!$H$15),0))} -> 0 | E6: {=IF(E$2>Assumptions!$H$15,0,(INDEX('Pro Forma'!$D$26:$M$26,E$2)+INDEX('Pro Forma'!$D$9:$M$9,E$2)*(((1+Assumptions!$H$16+$O6)/(1+Assumptions!$H$16))^E$2-1))-IF(Assumptions!$C$37=1,Assumptions!$C$68,IF(Assumptions!$C$37=2,Assumptions!$C$69,IF(E$2<=Assumptions!$C$41,Assumptions!$C$68,Assumptions!$C$69)))-Assumptions!$C$58-IF(Assumptions!$C$28=1,IF(E$2=1,Assumptions!$C$26,0),Assumptions!$C$26/Assumptions!$H$15)-Assumptions!$C$33+IF(E$2=Assumptions!$H$15,(INDEX('Pro Forma'!$D$26:$M$26,Assumptions!$H$15)+INDEX('Pro Forma'!$D$9:$M$9,Assumptions!$H$15)*(((1+Assumptions!$H$16+$O6)/(1+Assumptions!$H$16))^Assumptions!$H$15-1))/IF((Assumptions!$C$22+$P6)=0,1,Assumptions!$C$22+$P6)*(1-Assumptions!$C$23)-INDEX('Debt Schedule'!$C$8:$L$8,Assumptions!$H$15)-INDEX('Debt Schedule'!$C$19:$L$19,Assumptions!$H$15),0))} -> 0 | F6: {=IF(F$2>Assumptions!$H$15,0,(INDEX('Pro Forma'!$D$26:$M$26,F$2)+INDEX('Pro Forma'!$D$9:$M$9,F$2)*(((1+Assumptions!$H$16+$O6)/(1+Assumptions!$H$16))^F$2-1))-IF(Assumptions!$C$37=1,Assumptions!$C$68,IF(Assumptions!$C$37=2,Assumptions!$C$69,IF(F$2<=Assumptions!$C$41,Assumptions!$C$68,Assumptions!$C$69)))-Assumptions!$C$58-IF(Assumptions!$C$28=1,IF(F$2=1,Assumptions!$C$26,0),Assumptions!$C$26/Assumptions!$H$15)-Assumptions!$C$33+IF(F$2=Assumptions!$H$15,(INDEX('Pro Forma'!$D$26:$M$26,Assumptions!$H$15)+INDEX('Pro Forma'!$D$9:$M$9,Assumptions!$H$15)*(((1+Assumptions!$H$16+$O6)/(1+Assumptions!$H$16))^Assumptions!$H$15-1))/IF((Assumptions!$C$22+$P6)=0,1,Assumptions!$C$22+$P6)*(1-Assumptions!$C$23)-INDEX('Debt Schedule'!$C$8:$L$8,Assumptions!$H$15)-INDEX('Debt Schedule'!$C$19:$L$19,Assumptions!$H$15),0))} -> 0 | G6: {=IF(G$2>Assumptions!$H$15,0,(INDEX('Pro Forma'!$D$26:$M$26,G$2)+INDEX('Pro Forma'!$D$9:$M$9,G$2)*(((1+Assumptions!$H$16+$O6)/(1+Assumptions!$H$16))^G$2-1))-IF(Assumptions!$C$37=1,Assumptions!$C$68,IF(Assumptions!$C$37=2,Assumptions!$C$69,IF(G$2<=Assumptions!$C$41,Assumptions!$C$68,Assumptions!$C$69)))-Assumptions!$C$58-IF(Assumptions!$C$28=1,IF(G$2=1,Assumptions!$C$26,0),Assumptions!$C$26/Assumptions!$H$15)-Assumptions!$C$33+IF(G$2=Assumptions!$H$15,(INDEX('Pro Forma'!$D$26:$M$26,Assumptions!$H$15)+INDEX('Pro Forma'!$D$9:$M$9,Assumptions!$H$15)*(((1+Assumptions!$H$16+$O6)/(1+Assumptions!$H$16))^Assumptions!$H$15-1))/IF((Assumptions!$C$22+$P6)=0,1,Assumptions!$C$22+$P6)*(1-Assumptions!$C$23)-INDEX('Debt Schedule'!$C$8:$L$8,Assumptions!$H$15)-INDEX('Debt Schedule'!$C$19:$L$19,Assumptions!$H$15),0))} -> 0 | H6: {=IF(H$2>Assumptions!$H$15,0,(INDEX('Pro Forma'!$D$26:$M$26,H$2)+INDEX('Pro Forma'!$D$9:$M$9,H$2)*(((1+Assumptions!$H$16+$O6)/(1+Assumptions!$H$16))^H$2-1))-IF(Assumptions!$C$37=1,Assumptions!$C$68,IF(Assumptions!$C$37=2,Assumptions!$C$69,IF(H$2<=Assumptions!$C$41,Assumptions!$C$68,Assumptions!$C$69)))-Assumptions!$C$58-IF(Assumptions!$C$28=1,IF(H$2=1,Assumptions!$C$26,0),Assumptions!$C$26/Assumptions!$H$15)-Assumptions!$C$33+IF(H$2=Assumptions!$H$15,(INDEX('Pro Forma'!$D$26:$M$26,Assumptions!$H$15)+INDEX('Pro Forma'!$D$9:$M$9,Assumptions!$H$15)*(((1+Assumptions!$H$16+$O6)/(1+Assumptions!$H$16))^Assumptions!$H$15-1))/IF((Assumptions!$C$22+$P6)=0,1,Assumptions!$C$22+$P6)*(1-Assumptions!$C$23)-INDEX('Debt Schedule'!$C$8:$L$8,Assumptions!$H$15)-INDEX('Debt Schedule'!$C$19:$L$19,Assumptions!$H$15),0))} -> 0 | I6: {=IF(I$2>Assumptions!$H$15,0,(INDEX('Pro Forma'!$D$26:$M$26,I$2)+INDEX('Pro Forma'!$D$9:$M$9,I$2)*(((1+Assumptions!$H$16+$O6)/(1+Assumptions!$H$16))^I$2-1))-IF(Assumptions!$C$37=1,Assumptions!$C$68,IF(Assumptions!$C$37=2,Assumptions!$C$69,IF(I$2<=Assumptions!$C$41,Assumptions!$C$68,Assumptions!$C$69)))-Assumptions!$C$58-IF(Assumptions!$C$28=1,IF(I$2=1,Assumptions!$C$26,0),Assumptions!$C$26/Assumptions!$H$15)-Assumptions!$C$33+IF(I$2=Assumptions!$H$15,(INDEX('Pro Forma'!$D$26:$M$26,Assumptions!$H$15)+INDEX('Pro Forma'!$D$9:$M$9,Assumptions!$H$15)*(((1+Assumptions!$H$16+$O6)/(1+Assumptions!$H$16))^Assumptions!$H$15-1))/IF((Assumptions!$C$22+$P6)=0,1,Assumptions!$C$22+$P6)*(1-Assumptions!$C$23)-INDEX('Debt Schedule'!$C$8:$L$8,Assumptions!$H$15)-INDEX('Debt Schedule'!$C$19:$L$19,Assumptions!$H$15),0))} -> 0 | J6: {=IF(J$2>Assumptions!$H$15,0,(INDEX('Pro Forma'!$D$26:$M$26,J$2)+INDEX('Pro Forma'!$D$9:$M$9,J$2)*(((1+Assumptions!$H$16+$O6)/(1+Assumptions!$H$16))^J$2-1))-IF(Assumptions!$C$37=1,Assumptions!$C$68,IF(Assumptions!$C$37=2,Assumptions!$C$69,IF(J$2<=Assumptions!$C$41,Assumptions!$C$68,Assumptions!$C$69)))-Assumptions!$C$58-IF(Assumptions!$C$28=1,IF(J$2=1,Assumptions!$C$26,0),Assumptions!$C$26/Assumptions!$H$15)-Assumptions!$C$33+IF(J$2=Assumptions!$H$15,(INDEX('Pro Forma'!$D$26:$M$26,Assumptions!$H$15)+INDEX('Pro Forma'!$D$9:$M$9,Assumptions!$H$15)*(((1+Assumptions!$H$16+$O6)/(1+Assumptions!$H$16))^Assumptions!$H$15-1))/IF((Assumptions!$C$22+$P6)=0,1,Assumptions!$C$22+$P6)*(1-Assumptions!$C$23)-INDEX('Debt Schedule'!$C$8:$L$8,Assumptions!$H$15)-INDEX('Debt Schedule'!$C$19:$L$19,Assumptions!$H$15),0))} -> 0 | K6: {=IF(K$2>Assumptions!$H$15,0,(INDEX('Pro Forma'!$D$26:$M$26,K$2)+INDEX('Pro Forma'!$D$9:$M$9,K$2)*(((1+Assumptions!$H$16+$O6)/(1+Assumptions!$H$16))^K$2-1))-IF(Assumptions!$C$37=1,Assumptions!$C$68,IF(Assumptions!$C$37=2,Assumptions!$C$69,IF(K$2<=Assumptions!$C$41,Assumptions!$C$68,Assumptions!$C$69)))-Assumptions!$C$58-IF(Assumptions!$C$28=1,IF(K$2=1,Assumptions!$C$26,0),Assumptions!$C$26/Assumptions!$H$15)-Assumptions!$C$33+IF(K$2=Assumptions!$H$15,(INDEX('Pro Forma'!$D$26:$M$26,Assumptions!$H$15)+INDEX('Pro Forma'!$D$9:$M$9,Assumptions!$H$15)*(((1+Assumptions!$H$16+$O6)/(1+Assumptions!$H$16))^Assumptions!$H$15-1))/IF((Assumptions!$C$22+$P6)=0,1,Assumptions!$C$22+$P6)*(1-Assumptions!$C$23)-INDEX('Debt Schedule'!$C$8:$L$8,Assumptions!$H$15)-INDEX('Debt Schedule'!$C$19:$L$19,Assumptions!$H$15),0))} -> 0 | ... M6: {=IF(M$2>Assumptions!$H$15,0,(INDEX('Pro Forma'!$D$26:$M$26,M$2)+INDEX('Pro Forma'!$D$9:$M$9,M$2)*(((1+Assumptions!$H$16+$O6)/(1+Assumptions!$H$16))^M$2-1))-IF(Assumptions!$C$37=1,Assumptions!$C$68,IF(Assumptions!$C$37=2,Assumptions!$C$69,IF(M$2<=Assumptions!$C$41,Assumptions!$C$68,Assumptions!$C$69)))-Assumptions!$C$58-IF(Assumptions!$C$28=1,IF(M$2=1,Assumptions!$C$26,0),Assumptions!$C$26/Assumptions!$H$15)-Assumptions!$C$33+IF(M$2=Assumptions!$H$15,(INDEX('Pro Forma'!$D$26:$M$26,Assumptions!$H$15)+INDEX('Pro Forma'!$D$9:$M$9,Assumptions!$H$15)*(((1+Assumptions!$H$16+$O6)/(1+Assumptions!$H$16))^Assumptions!$H$15-1))/IF((Assumptions!$C$22+$P6)=0,1,Assumptions!$C$22+$P6)*(1-Assumptions!$C$23)-INDEX('Debt Schedule'!$C$8:$L$8,Assumptions!$H$15)-INDEX('Debt Schedule'!$C$19:$L$19,Assumptions!$H$15),0))} -> 0 | N6: =IFERROR(IRR(C6:M6),0) -> 0 | O6: =(MOD(ROW()-3,5)-2)*0.005 -> 0.005 | P6: =(INT((ROW()-3)/5)-2)*0.0025 -> -0.005
C7: =-Assumptions!$C$70 -> 0 | D7: {=IF(D$2>Assumptions!$H$15,0,(INDEX('Pro Forma'!$D$26:$M$26,D$2)+INDEX('Pro Forma'!$D$9:$M$9,D$2)*(((1+Assumptions!$H$16+$O7)/(1+Assumptions!$H$16))^D$2-1))-IF(Assumptions!$C$37=1,Assumptions!$C$68,IF(Assumptions!$C$37=2,Assumptions!$C$69,IF(D$2<=Assumptions!$C$41,Assumptions!$C$68,Assumptions!$C$69)))-Assumptions!$C$58-IF(Assumptions!$C$28=1,IF(D$2=1,Assumptions!$C$26,0),Assumptions!$C$26/Assumptions!$H$15)-Assumptions!$C$33+IF(D$2=Assumptions!$H$15,(INDEX('Pro Forma'!$D$26:$M$26,Assumptions!$H$15)+INDEX('Pro Forma'!$D$9:$M$9,Assumptions!$H$15)*(((1+Assumptions!$H$16+$O7)/(1+Assumptions!$H$16))^Assumptions!$H$15-1))/IF((Assumptions!$C$22+$P7)=0,1,Assumptions!$C$22+$P7)*(1-Assumptions!$C$23)-INDEX('Debt Schedule'!$C$8:$L$8,Assumptions!$H$15)-INDEX('Debt Schedule'!$C$19:$L$19,Assumptions!$H$15),0))} -> 0 | E7: {=IF(E$2>Assumptions!$H$15,0,(INDEX('Pro Forma'!$D$26:$M$26,E$2)+INDEX('Pro Forma'!$D$9:$M$9,E$2)*(((1+Assumptions!$H$16+$O7)/(1+Assumptions!$H$16))^E$2-1))-IF(Assumptions!$C$37=1,Assumptions!$C$68,IF(Assumptions!$C$37=2,Assumptions!$C$69,IF(E$2<=Assumptions!$C$41,Assumptions!$C$68,Assumptions!$C$69)))-Assumptions!$C$58-IF(Assumptions!$C$28=1,IF(E$2=1,Assumptions!$C$26,0),Assumptions!$C$26/Assumptions!$H$15)-Assumptions!$C$33+IF(E$2=Assumptions!$H$15,(INDEX('Pro Forma'!$D$26:$M$26,Assumptions!$H$15)+INDEX('Pro Forma'!$D$9:$M$9,Assumptions!$H$15)*(((1+Assumptions!$H$16+$O7)/(1+Assumptions!$H$16))^Assumptions!$H$15-1))/IF((Assumptions!$C$22+$P7)=0,1,Assumptions!$C$22+$P7)*(1-Assumptions!$C$23)-INDEX('Debt Schedule'!$C$8:$L$8,Assumptions!$H$15)-INDEX('Debt Schedule'!$C$19:$L$19,Assumptions!$H$15),0))} -> 0 | F7: {=IF(F$2>Assumptions!$H$15,0,(INDEX('Pro Forma'!$D$26:$M$26,F$2)+INDEX('Pro Forma'!$D$9:$M$9,F$2)*(((1+Assumptions!$H$16+$O7)/(1+Assumptions!$H$16))^F$2-1))-IF(Assumptions!$C$37=1,Assumptions!$C$68,IF(Assumptions!$C$37=2,Assumptions!$C$69,IF(F$2<=Assumptions!$C$41,Assumptions!$C$68,Assumptions!$C$69)))-Assumptions!$C$58-IF(Assumptions!$C$28=1,IF(F$2=1,Assumptions!$C$26,0),Assumptions!$C$26/Assumptions!$H$15)-Assumptions!$C$33+IF(F$2=Assumptions!$H$15,(INDEX('Pro Forma'!$D$26:$M$26,Assumptions!$H$15)+INDEX('Pro Forma'!$D$9:$M$9,Assumptions!$H$15)*(((1+Assumptions!$H$16+$O7)/(1+Assumptions!$H$16))^Assumptions!$H$15-1))/IF((Assumptions!$C$22+$P7)=0,1,Assumptions!$C$22+$P7)*(1-Assumptions!$C$23)-INDEX('Debt Schedule'!$C$8:$L$8,Assumptions!$H$15)-INDEX('Debt Schedule'!$C$19:$L$19,Assumptions!$H$15),0))} -> 0 | G7: {=IF(G$2>Assumptions!$H$15,0,(INDEX('Pro Forma'!$D$26:$M$26,G$2)+INDEX('Pro Forma'!$D$9:$M$9,G$2)*(((1+Assumptions!$H$16+$O7)/(1+Assumptions!$H$16))^G$2-1))-IF(Assumptions!$C$37=1,Assumptions!$C$68,IF(Assumptions!$C$37=2,Assumptions!$C$69,IF(G$2<=Assumptions!$C$41,Assumptions!$C$68,Assumptions!$C$69)))-Assumptions!$C$58-IF(Assumptions!$C$28=1,IF(G$2=1,Assumptions!$C$26,0),Assumptions!$C$26/Assumptions!$H$15)-Assumptions!$C$33+IF(G$2=Assumptions!$H$15,(INDEX('Pro Forma'!$D$26:$M$26,Assumptions!$H$15)+INDEX('Pro Forma'!$D$9:$M$9,Assumptions!$H$15)*(((1+Assumptions!$H$16+$O7)/(1+Assumptions!$H$16))^Assumptions!$H$15-1))/IF((Assumptions!$C$22+$P7)=0,1,Assumptions!$C$22+$P7)*(1-Assumptions!$C$23)-INDEX('Debt Schedule'!$C$8:$L$8,Assumptions!$H$15)-INDEX('Debt Schedule'!$C$19:$L$19,Assumptions!$H$15),0))} -> 0 | H7: {=IF(H$2>Assumptions!$H$15,0,(INDEX('Pro Forma'!$D$26:$M$26,H$2)+INDEX('Pro Forma'!$D$9:$M$9,H$2)*(((1+Assumptions!$H$16+$O7)/(1+Assumptions!$H$16))^H$2-1))-IF(Assumptions!$C$37=1,Assumptions!$C$68,IF(Assumptions!$C$37=2,Assumptions!$C$69,IF(H$2<=Assumptions!$C$41,Assumptions!$C$68,Assumptions!$C$69)))-Assumptions!$C$58-IF(Assumptions!$C$28=1,IF(H$2=1,Assumptions!$C$26,0),Assumptions!$C$26/Assumptions!$H$15)-Assumptions!$C$33+IF(H$2=Assumptions!$H$15,(INDEX('Pro Forma'!$D$26:$M$26,Assumptions!$H$15)+INDEX('Pro Forma'!$D$9:$M$9,Assumptions!$H$15)*(((1+Assumptions!$H$16+$O7)/(1+Assumptions!$H$16))^Assumptions!$H$15-1))/IF((Assumptions!$C$22+$P7)=0,1,Assumptions!$C$22+$P7)*(1-Assumptions!$C$23)-INDEX('Debt Schedule'!$C$8:$L$8,Assumptions!$H$15)-INDEX('Debt Schedule'!$C$19:$L$19,Assumptions!$H$15),0))} -> 0 | I7: {=IF(I$2>Assumptions!$H$15,0,(INDEX('Pro Forma'!$D$26:$M$26,I$2)+INDEX('Pro Forma'!$D$9:$M$9,I$2)*(((1+Assumptions!$H$16+$O7)/(1+Assumptions!$H$16))^I$2-1))-IF(Assumptions!$C$37=1,Assumptions!$C$68,IF(Assumptions!$C$37=2,Assumptions!$C$69,IF(I$2<=Assumptions!$C$41,Assumptions!$C$68,Assumptions!$C$69)))-Assumptions!$C$58-IF(Assumptions!$C$28=1,IF(I$2=1,Assumptions!$C$26,0),Assumptions!$C$26/Assumptions!$H$15)-Assumptions!$C$33+IF(I$2=Assumptions!$H$15,(INDEX('Pro Forma'!$D$26:$M$26,Assumptions!$H$15)+INDEX('Pro Forma'!$D$9:$M$9,Assumptions!$H$15)*(((1+Assumptions!$H$16+$O7)/(1+Assumptions!$H$16))^Assumptions!$H$15-1))/IF((Assumptions!$C$22+$P7)=0,1,Assumptions!$C$22+$P7)*(1-Assumptions!$C$23)-INDEX('Debt Schedule'!$C$8:$L$8,Assumptions!$H$15)-INDEX('Debt Schedule'!$C$19:$L$19,Assumptions!$H$15),0))} -> 0 | J7: {=IF(J$2>Assumptions!$H$15,0,(INDEX('Pro Forma'!$D$26:$M$26,J$2)+INDEX('Pro Forma'!$D$9:$M$9,J$2)*(((1+Assumptions!$H$16+$O7)/(1+Assumptions!$H$16))^J$2-1))-IF(Assumptions!$C$37=1,Assumptions!$C$68,IF(Assumptions!$C$37=2,Assumptions!$C$69,IF(J$2<=Assumptions!$C$41,Assumptions!$C$68,Assumptions!$C$69)))-Assumptions!$C$58-IF(Assumptions!$C$28=1,IF(J$2=1,Assumptions!$C$26,0),Assumptions!$C$26/Assumptions!$H$15)-Assumptions!$C$33+IF(J$2=Assumptions!$H$15,(INDEX('Pro Forma'!$D$26:$M$26,Assumptions!$H$15)+INDEX('Pro Forma'!$D$9:$M$9,Assumptions!$H$15)*(((1+Assumptions!$H$16+$O7)/(1+Assumptions!$H$16))^Assumptions!$H$15-1))/IF((Assumptions!$C$22+$P7)=0,1,Assumptions!$C$22+$P7)*(1-Assumptions!$C$23)-INDEX('Debt Schedule'!$C$8:$L$8,Assumptions!$H$15)-INDEX('Debt Schedule'!$C$19:$L$19,Assumptions!$H$15),0))} -> 0 | K7: {=IF(K$2>Assumptions!$H$15,0,(INDEX('Pro Forma'!$D$26:$M$26,K$2)+INDEX('Pro Forma'!$D$9:$M$9,K$2)*(((1+Assumptions!$H$16+$O7)/(1+Assumptions!$H$16))^K$2-1))-IF(Assumptions!$C$37=1,Assumptions!$C$68,IF(Assumptions!$C$37=2,Assumptions!$C$69,IF(K$2<=Assumptions!$C$41,Assumptions!$C$68,Assumptions!$C$69)))-Assumptions!$C$58-IF(Assumptions!$C$28=1,IF(K$2=1,Assumptions!$C$26,0),Assumptions!$C$26/Assumptions!$H$15)-Assumptions!$C$33+IF(K$2=Assumptions!$H$15,(INDEX('Pro Forma'!$D$26:$M$26,Assumptions!$H$15)+INDEX('Pro Forma'!$D$9:$M$9,Assumptions!$H$15)*(((1+Assumptions!$H$16+$O7)/(1+Assumptions!$H$16))^Assumptions!$H$15-1))/IF((Assumptions!$C$22+$P7)=0,1,Assumptions!$C$22+$P7)*(1-Assumptions!$C$23)-INDEX('Debt Schedule'!$C$8:$L$8,Assumptions!$H$15)-INDEX('Debt Schedule'!$C$19:$L$19,Assumptions!$H$15),0))} -> 0 | ... M7: {=IF(M$2>Assumptions!$H$15,0,(INDEX('Pro Forma'!$D$26:$M$26,M$2)+INDEX('Pro Forma'!$D$9:$M$9,M$2)*(((1+Assumptions!$H$16+$O7)/(1+Assumptions!$H$16))^M$2-1))-IF(Assumptions!$C$37=1,Assumptions!$C$68,IF(Assumptions!$C$37=2,Assumptions!$C$69,IF(M$2<=Assumptions!$C$41,Assumptions!$C$68,Assumptions!$C$69)))-Assumptions!$C$58-IF(Assumptions!$C$28=1,IF(M$2=1,Assumptions!$C$26,0),Assumptions!$C$26/Assumptions!$H$15)-Assumptions!$C$33+IF(M$2=Assumptions!$H$15,(INDEX('Pro Forma'!$D$26:$M$26,Assumptions!$H$15)+INDEX('Pro Forma'!$D$9:$M$9,Assumptions!$H$15)*(((1+Assumptions!$H$16+$O7)/(1+Assumptions!$H$16))^Assumptions!$H$15-1))/IF((Assumptions!$C$22+$P7)=0,1,Assumptions!$C$22+$P7)*(1-Assumptions!$C$23)-INDEX('Debt Schedule'!$C$8:$L$8,Assumptions!$H$15)-INDEX('Debt Schedule'!$C$19:$L$19,Assumptions!$H$15),0))} -> 0 | N7: =IFERROR(IRR(C7:M7),0) -> 0 | O7: =(MOD(ROW()-3,5)-2)*0.005 -> 0.01 | P7: =(INT((ROW()-3)/5)-2)*0.0025 -> -0.005
C8: =-Assumptions!$C$70 -> 0 | D8: {=IF(D$2>Assumptions!$H$15,0,(INDEX('Pro Forma'!$D$26:$M$26,D$2)+INDEX('Pro Forma'!$D$9:$M$9,D$2)*(((1+Assumptions!$H$16+$O8)/(1+Assumptions!$H$16))^D$2-1))-IF(Assumptions!$C$37=1,Assumptions!$C$68,IF(Assumptions!$C$37=2,Assumptions!$C$69,IF(D$2<=Assumptions!$C$41,Assumptions!$C$68,Assumptions!$C$69)))-Assumptions!$C$58-IF(Assumptions!$C$28=1,IF(D$2=1,Assumptions!$C$26,0),Assumptions!$C$26/Assumptions!$H$15)-Assumptions!$C$33+IF(D$2=Assumptions!$H$15,(INDEX('Pro Forma'!$D$26:$M$26,Assumptions!$H$15)+INDEX('Pro Forma'!$D$9:$M$9,Assumptions!$H$15)*(((1+Assumptions!$H$16+$O8)/(1+Assumptions!$H$16))^Assumptions!$H$15-1))/IF((Assumptions!$C$22+$P8)=0,1,Assumptions!$C$22+$P8)*(1-Assumptions!$C$23)-INDEX('Debt Schedule'!$C$8:$L$8,Assumptions!$H$15)-INDEX('Debt Schedule'!$C$19:$L$19,Assumptions!$H$15),0))} -> 0 | E8: {=IF(E$2>Assumptions!$H$15,0,(INDEX('Pro Forma'!$D$26:$M$26,E$2)+INDEX('Pro Forma'!$D$9:$M$9,E$2)*(((1+Assumptions!$H$16+$O8)/(1+Assumptions!$H$16))^E$2-1))-IF(Assumptions!$C$37=1,Assumptions!$C$68,IF(Assumptions!$C$37=2,Assumptions!$C$69,IF(E$2<=Assumptions!$C$41,Assumptions!$C$68,Assumptions!$C$69)))-Assumptions!$C$58-IF(Assumptions!$C$28=1,IF(E$2=1,Assumptions!$C$26,0),Assumptions!$C$26/Assumptions!$H$15)-Assumptions!$C$33+IF(E$2=Assumptions!$H$15,(INDEX('Pro Forma'!$D$26:$M$26,Assumptions!$H$15)+INDEX('Pro Forma'!$D$9:$M$9,Assumptions!$H$15)*(((1+Assumptions!$H$16+$O8)/(1+Assumptions!$H$16))^Assumptions!$H$15-1))/IF((Assumptions!$C$22+$P8)=0,1,Assumptions!$C$22+$P8)*(1-Assumptions!$C$23)-INDEX('Debt Schedule'!$C$8:$L$8,Assumptions!$H$15)-INDEX('Debt Schedule'!$C$19:$L$19,Assumptions!$H$15),0))} -> 0 | F8: {=IF(F$2>Assumptions!$H$15,0,(INDEX('Pro Forma'!$D$26:$M$26,F$2)+INDEX('Pro Forma'!$D$9:$M$9,F$2)*(((1+Assumptions!$H$16+$O8)/(1+Assumptions!$H$16))^F$2-1))-IF(Assumptions!$C$37=1,Assumptions!$C$68,IF(Assumptions!$C$37=2,Assumptions!$C$69,IF(F$2<=Assumptions!$C$41,Assumptions!$C$68,Assumptions!$C$69)))-Assumptions!$C$58-IF(Assumptions!$C$28=1,IF(F$2=1,Assumptions!$C$26,0),Assumptions!$C$26/Assumptions!$H$15)-Assumptions!$C$33+IF(F$2=Assumptions!$H$15,(INDEX('Pro Forma'!$D$26:$M$26,Assumptions!$H$15)+INDEX('Pro Forma'!$D$9:$M$9,Assumptions!$H$15)*(((1+Assumptions!$H$16+$O8)/(1+Assumptions!$H$16))^Assumptions!$H$15-1))/IF((Assumptions!$C$22+$P8)=0,1,Assumptions!$C$22+$P8)*(1-Assumptions!$C$23)-INDEX('Debt Schedule'!$C$8:$L$8,Assumptions!$H$15)-INDEX('Debt Schedule'!$C$19:$L$19,Assumptions!$H$15),0))} -> 0 | G8: {=IF(G$2>Assumptions!$H$15,0,(INDEX('Pro Forma'!$D$26:$M$26,G$2)+INDEX('Pro Forma'!$D$9:$M$9,G$2)*(((1+Assumptions!$H$16+$O8)/(1+Assumptions!$H$16))^G$2-1))-IF(Assumptions!$C$37=1,Assumptions!$C$68,IF(Assumptions!$C$37=2,Assumptions!$C$69,IF(G$2<=Assumptions!$C$41,Assumptions!$C$68,Assumptions!$C$69)))-Assumptions!$C$58-IF(Assumptions!$C$28=1,IF(G$2=1,Assumptions!$C$26,0),Assumptions!$C$26/Assumptions!$H$15)-Assumptions!$C$33+IF(G$2=Assumptions!$H$15,(INDEX('Pro Forma'!$D$26:$M$26,Assumptions!$H$15)+INDEX('Pro Forma'!$D$9:$M$9,Assumptions!$H$15)*(((1+Assumptions!$H$16+$O8)/(1+Assumptions!$H$16))^Assumptions!$H$15-1))/IF((Assumptions!$C$22+$P8)=0,1,Assumptions!$C$22+$P8)*(1-Assumptions!$C$23)-INDEX('Debt Schedule'!$C$8:$L$8,Assumptions!$H$15)-INDEX('Debt Schedule'!$C$19:$L$19,Assumptions!$H$15),0))} -> 0 | H8: {=IF(H$2>Assumptions!$H$15,0,(INDEX('Pro Forma'!$D$26:$M$26,H$2)+INDEX('Pro Forma'!$D$9:$M$9,H$2)*(((1+Assumptions!$H$16+$O8)/(1+Assumptions!$H$16))^H$2-1))-IF(Assumptions!$C$37=1,Assumptions!$C$68,IF(Assumptions!$C$37=2,Assumptions!$C$69,IF(H$2<=Assumptions!$C$41,Assumptions!$C$68,Assumptions!$C$69)))-Assumptions!$C$58-IF(Assumptions!$C$28=1,IF(H$2=1,Assumptions!$C$26,0),Assumptions!$C$26/Assumptions!$H$15)-Assumptions!$C$33+IF(H$2=Assumptions!$H$15,(INDEX('Pro Forma'!$D$26:$M$26,Assumptions!$H$15)+INDEX('Pro Forma'!$D$9:$M$9,Assumptions!$H$15)*(((1+Assumptions!$H$16+$O8)/(1+Assumptions!$H$16))^Assumptions!$H$15-1))/IF((Assumptions!$C$22+$P8)=0,1,Assumptions!$C$22+$P8)*(1-Assumptions!$C$23)-INDEX('Debt Schedule'!$C$8:$L$8,Assumptions!$H$15)-INDEX('Debt Schedule'!$C$19:$L$19,Assumptions!$H$15),0))} -> 0 | I8: {=IF(I$2>Assumptions!$H$15,0,(INDEX('Pro Forma'!$D$26:$M$26,I$2)+INDEX('Pro Forma'!$D$9:$M$9,I$2)*(((1+Assumptions!$H$16+$O8)/(1+Assumptions!$H$16))^I$2-1))-IF(Assumptions!$C$37=1,Assumptions!$C$68,IF(Assumptions!$C$37=2,Assumptions!$C$69,IF(I$2<=Assumptions!$C$41,Assumptions!$C$68,Assumptions!$C$69)))-Assumptions!$C$58-IF(Assumptions!$C$28=1,IF(I$2=1,Assumptions!$C$26,0),Assumptions!$C$26/Assumptions!$H$15)-Assumptions!$C$33+IF(I$2=Assumptions!$H$15,(INDEX('Pro Forma'!$D$26:$M$26,Assumptions!$H$15)+INDEX('Pro Forma'!$D$9:$M$9,Assumptions!$H$15)*(((1+Assumptions!$H$16+$O8)/(1+Assumptions!$H$16))^Assumptions!$H$15-1))/IF((Assumptions!$C$22+$P8)=0,1,Assumptions!$C$22+$P8)*(1-Assumptions!$C$23)-INDEX('Debt Schedule'!$C$8:$L$8,Assumptions!$H$15)-INDEX('Debt Schedule'!$C$19:$L$19,Assumptions!$H$15),0))} -> 0 | J8: {=IF(J$2>Assumptions!$H$15,0,(INDEX('Pro Forma'!$D$26:$M$26,J$2)+INDEX('Pro Forma'!$D$9:$M$9,J$2)*(((1+Assumptions!$H$16+$O8)/(1+Assumptions!$H$16))^J$2-1))-IF(Assumptions!$C$37=1,Assumptions!$C$68,IF(Assumptions!$C$37=2,Assumptions!$C$69,IF(J$2<=Assumptions!$C$41,Assumptions!$C$68,Assumptions!$C$69)))-Assumptions!$C$58-IF(Assumptions!$C$28=1,IF(J$2=1,Assumptions!$C$26,0),Assumptions!$C$26/Assumptions!$H$15)-Assumptions!$C$33+IF(J$2=Assumptions!$H$15,(INDEX('Pro Forma'!$D$26:$M$26,Assumptions!$H$15)+INDEX('Pro Forma'!$D$9:$M$9,Assumptions!$H$15)*(((1+Assumptions!$H$16+$O8)/(1+Assumptions!$H$16))^Assumptions!$H$15-1))/IF((Assumptions!$C$22+$P8)=0,1,Assumptions!$C$22+$P8)*(1-Assumptions!$C$23)-INDEX('Debt Schedule'!$C$8:$L$8,Assumptions!$H$15)-INDEX('Debt Schedule'!$C$19:$L$19,Assumptions!$H$15),0))} -> 0 | K8: {=IF(K$2>Assumptions!$H$15,0,(INDEX('Pro Forma'!$D$26:$M$26,K$2)+INDEX('Pro Forma'!$D$9:$M$9,K$2)*(((1+Assumptions!$H$16+$O8)/(1+Assumptions!$H$16))^K$2-1))-IF(Assumptions!$C$37=1,Assumptions!$C$68,IF(Assumptions!$C$37=2,Assumptions!$C$69,IF(K$2<=Assumptions!$C$41,Assumptions!$C$68,Assumptions!$C$69)))-Assumptions!$C$58-IF(Assumptions!$C$28=1,IF(K$2=1,Assumptions!$C$26,0),Assumptions!$C$26/Assumptions!$H$15)-Assumptions!$C$33+IF(K$2=Assumptions!$H$15,(INDEX('Pro Forma'!$D$26:$M$26,Assumptions!$H$15)+INDEX('Pro Forma'!$D$9:$M$9,Assumptions!$H$15)*(((1+Assumptions!$H$16+$O8)/(1+Assumptions!$H$16))^Assumptions!$H$15-1))/IF((Assumptions!$C$22+$P8)=0,1,Assumptions!$C$22+$P8)*(1-Assumptions!$C$23)-INDEX('Debt Schedule'!$C$8:$L$8,Assumptions!$H$15)-INDEX('Debt Schedule'!$C$19:$L$19,Assumptions!$H$15),0))} -> 0 | ... M8: {=IF(M$2>Assumptions!$H$15,0,(INDEX('Pro Forma'!$D$26:$M$26,M$2)+INDEX('Pro Forma'!$D$9:$M$9,M$2)*(((1+Assumptions!$H$16+$O8)/(1+Assumptions!$H$16))^M$2-1))-IF(Assumptions!$C$37=1,Assumptions!$C$68,IF(Assumptions!$C$37=2,Assumptions!$C$69,IF(M$2<=Assumptions!$C$41,Assumptions!$C$68,Assumptions!$C$69)))-Assumptions!$C$58-IF(Assumptions!$C$28=1,IF(M$2=1,Assumptions!$C$26,0),Assumptions!$C$26/Assumptions!$H$15)-Assumptions!$C$33+IF(M$2=Assumptions!$H$15,(INDEX('Pro Forma'!$D$26:$M$26,Assumptions!$H$15)+INDEX('Pro Forma'!$D$9:$M$9,Assumptions!$H$15)*(((1+Assumptions!$H$16+$O8)/(1+Assumptions!$H$16))^Assumptions!$H$15-1))/IF((Assumptions!$C$22+$P8)=0,1,Assumptions!$C$22+$P8)*(1-Assumptions!$C$23)-INDEX('Debt Schedule'!$C$8:$L$8,Assumptions!$H$15)-INDEX('Debt Schedule'!$C$19:$L$19,Assumptions!$H$15),0))} -> 0 | N8: =IFERROR(IRR(C8:M8),0) -> 0 | O8: =(MOD(ROW()-3,5)-2)*0.005 -> -0.01 | P8: =(INT((ROW()-3)/5)-2)*0.0025 -> -0.0025
C9: =-Assumptions!$C$70 -> 0 | D9: {=IF(D$2>Assumptions!$H$15,0,(INDEX('Pro Forma'!$D$26:$M$26,D$2)+INDEX('Pro Forma'!$D$9:$M$9,D$2)*(((1+Assumptions!$H$16+$O9)/(1+Assumptions!$H$16))^D$2-1))-IF(Assumptions!$C$37=1,Assumptions!$C$68,IF(Assumptions!$C$37=2,Assumptions!$C$69,IF(D$2<=Assumptions!$C$41,Assumptions!$C$68,Assumptions!$C$69)))-Assumptions!$C$58-IF(Assumptions!$C$28=1,IF(D$2=1,Assumptions!$C$26,0),Assumptions!$C$26/Assumptions!$H$15)-Assumptions!$C$33+IF(D$2=Assumptions!$H$15,(INDEX('Pro Forma'!$D$26:$M$26,Assumptions!$H$15)+INDEX('Pro Forma'!$D$9:$M$9,Assumptions!$H$15)*(((1+Assumptions!$H$16+$O9)/(1+Assumptions!$H$16))^Assumptions!$H$15-1))/IF((Assumptions!$C$22+$P9)=0,1,Assumptions!$C$22+$P9)*(1-Assumptions!$C$23)-INDEX('Debt Schedule'!$C$8:$L$8,Assumptions!$H$15)-INDEX('Debt Schedule'!$C$19:$L$19,Assumptions!$H$15),0))} -> 0 | E9: {=IF(E$2>Assumptions!$H$15,0,(INDEX('Pro Forma'!$D$26:$M$26,E$2)+INDEX('Pro Forma'!$D$9:$M$9,E$2)*(((1+Assumptions!$H$16+$O9)/(1+Assumptions!$H$16))^E$2-1))-IF(Assumptions!$C$37=1,Assumptions!$C$68,IF(Assumptions!$C$37=2,Assumptions!$C$69,IF(E$2<=Assumptions!$C$41,Assumptions!$C$68,Assumptions!$C$69)))-Assumptions!$C$58-IF(Assumptions!$C$28=1,IF(E$2=1,Assumptions!$C$26,0),Assumptions!$C$26/Assumptions!$H$15)-Assumptions!$C$33+IF(E$2=Assumptions!$H$15,(INDEX('Pro Forma'!$D$26:$M$26,Assumptions!$H$15)+INDEX('Pro Forma'!$D$9:$M$9,Assumptions!$H$15)*(((1+Assumptions!$H$16+$O9)/(1+Assumptions!$H$16))^Assumptions!$H$15-1))/IF((Assumptions!$C$22+$P9)=0,1,Assumptions!$C$22+$P9)*(1-Assumptions!$C$23)-INDEX('Debt Schedule'!$C$8:$L$8,Assumptions!$H$15)-INDEX('Debt Schedule'!$C$19:$L$19,Assumptions!$H$15),0))} -> 0 | F9: {=IF(F$2>Assumptions!$H$15,0,(INDEX('Pro Forma'!$D$26:$M$26,F$2)+INDEX('Pro Forma'!$D$9:$M$9,F$2)*(((1+Assumptions!$H$16+$O9)/(1+Assumptions!$H$16))^F$2-1))-IF(Assumptions!$C$37=1,Assumptions!$C$68,IF(Assumptions!$C$37=2,Assumptions!$C$69,IF(F$2<=Assumptions!$C$41,Assumptions!$C$68,Assumptions!$C$69)))-Assumptions!$C$58-IF(Assumptions!$C$28=1,IF(F$2=1,Assumptions!$C$26,0),Assumptions!$C$26/Assumptions!$H$15)-Assumptions!$C$33+IF(F$2=Assumptions!$H$15,(INDEX('Pro Forma'!$D$26:$M$26,Assumptions!$H$15)+INDEX('Pro Forma'!$D$9:$M$9,Assumptions!$H$15)*(((1+Assumptions!$H$16+$O9)/(1+Assumptions!$H$16))^Assumptions!$H$15-1))/IF((Assumptions!$C$22+$P9)=0,1,Assumptions!$C$22+$P9)*(1-Assumptions!$C$23)-INDEX('Debt Schedule'!$C$8:$L$8,Assumptions!$H$15)-INDEX('Debt Schedule'!$C$19:$L$19,Assumptions!$H$15),0))} -> 0 | G9: {=IF(G$2>Assumptions!$H$15,0,(INDEX('Pro Forma'!$D$26:$M$26,G$2)+INDEX('Pro Forma'!$D$9:$M$9,G$2)*(((1+Assumptions!$H$16+$O9)/(1+Assumptions!$H$16))^G$2-1))-IF(Assumptions!$C$37=1,Assumptions!$C$68,IF(Assumptions!$C$37=2,Assumptions!$C$69,IF(G$2<=Assumptions!$C$41,Assumptions!$C$68,Assumptions!$C$69)))-Assumptions!$C$58-IF(Assumptions!$C$28=1,IF(G$2=1,Assumptions!$C$26,0),Assumptions!$C$26/Assumptions!$H$15)-Assumptions!$C$33+IF(G$2=Assumptions!$H$15,(INDEX('Pro Forma'!$D$26:$M$26,Assumptions!$H$15)+INDEX('Pro Forma'!$D$9:$M$9,Assumptions!$H$15)*(((1+Assumptions!$H$16+$O9)/(1+Assumptions!$H$16))^Assumptions!$H$15-1))/IF((Assumptions!$C$22+$P9)=0,1,Assumptions!$C$22+$P9)*(1-Assumptions!$C$23)-INDEX('Debt Schedule'!$C$8:$L$8,Assumptions!$H$15)-INDEX('Debt Schedule'!$C$19:$L$19,Assumptions!$H$15),0))} -> 0 | H9: {=IF(H$2>Assumptions!$H$15,0,(INDEX('Pro Forma'!$D$26:$M$26,H$2)+INDEX('Pro Forma'!$D$9:$M$9,H$2)*(((1+Assumptions!$H$16+$O9)/(1+Assumptions!$H$16))^H$2-1))-IF(Assumptions!$C$37=1,Assumptions!$C$68,IF(Assumptions!$C$37=2,Assumptions!$C$69,IF(H$2<=Assumptions!$C$41,Assumptions!$C$68,Assumptions!$C$69)))-Assumptions!$C$58-IF(Assumptions!$C$28=1,IF(H$2=1,Assumptions!$C$26,0),Assumptions!$C$26/Assumptions!$H$15)-Assumptions!$C$33+IF(H$2=Assumptions!$H$15,(INDEX('Pro Forma'!$D$26:$M$26,Assumptions!$H$15)+INDEX('Pro Forma'!$D$9:$M$9,Assumptions!$H$15)*(((1+Assumptions!$H$16+$O9)/(1+Assumptions!$H$16))^Assumptions!$H$15-1))/IF((Assumptions!$C$22+$P9)=0,1,Assumptions!$C$22+$P9)*(1-Assumptions!$C$23)-INDEX('Debt Schedule'!$C$8:$L$8,Assumptions!$H$15)-INDEX('Debt Schedule'!$C$19:$L$19,Assumptions!$H$15),0))} -> 0 | I9: {=IF(I$2>Assumptions!$H$15,0,(INDEX('Pro Forma'!$D$26:$M$26,I$2)+INDEX('Pro Forma'!$D$9:$M$9,I$2)*(((1+Assumptions!$H$16+$O9)/(1+Assumptions!$H$16))^I$2-1))-IF(Assumptions!$C$37=1,Assumptions!$C$68,IF(Assumptions!$C$37=2,Assumptions!$C$69,IF(I$2<=Assumptions!$C$41,Assumptions!$C$68,Assumptions!$C$69)))-Assumptions!$C$58-IF(Assumptions!$C$28=1,IF(I$2=1,Assumptions!$C$26,0),Assumptions!$C$26/Assumptions!$H$15)-Assumptions!$C$33+IF(I$2=Assumptions!$H$15,(INDEX('Pro Forma'!$D$26:$M$26,Assumptions!$H$15)+INDEX('Pro Forma'!$D$9:$M$9,Assumptions!$H$15)*(((1+Assumptions!$H$16+$O9)/(1+Assumptions!$H$16))^Assumptions!$H$15-1))/IF((Assumptions!$C$22+$P9)=0,1,Assumptions!$C$22+$P9)*(1-Assumptions!$C$23)-INDEX('Debt Schedule'!$C$8:$L$8,Assumptions!$H$15)-INDEX('Debt Schedule'!$C$19:$L$19,Assumptions!$H$15),0))} -> 0 | J9: {=IF(J$2>Assumptions!$H$15,0,(INDEX('Pro Forma'!$D$26:$M$26,J$2)+INDEX('Pro Forma'!$D$9:$M$9,J$2)*(((1+Assumptions!$H$16+$O9)/(1+Assumptions!$H$16))^J$2-1))-IF(Assumptions!$C$37=1,Assumptions!$C$68,IF(Assumptions!$C$37=2,Assumptions!$C$69,IF(J$2<=Assumptions!$C$41,Assumptions!$C$68,Assumptions!$C$69)))-Assumptions!$C$58-IF(Assumptions!$C$28=1,IF(J$2=1,Assumptions!$C$26,0),Assumptions!$C$26/Assumptions!$H$15)-Assumptions!$C$33+IF(J$2=Assumptions!$H$15,(INDEX('Pro Forma'!$D$26:$M$26,Assumptions!$H$15)+INDEX('Pro Forma'!$D$9:$M$9,Assumptions!$H$15)*(((1+Assumptions!$H$16+$O9)/(1+Assumptions!$H$16))^Assumptions!$H$15-1))/IF((Assumptions!$C$22+$P9)=0,1,Assumptions!$C$22+$P9)*(1-Assumptions!$C$23)-INDEX('Debt Schedule'!$C$8:$L$8,Assumptions!$H$15)-INDEX('Debt Schedule'!$C$19:$L$19,Assumptions!$H$15),0))} -> 0 | K9: {=IF(K$2>Assumptions!$H$15,0,(INDEX('Pro Forma'!$D$26:$M$26,K$2)+INDEX('Pro Forma'!$D$9:$M$9,K$2)*(((1+Assumptions!$H$16+$O9)/(1+Assumptions!$H$16))^K$2-1))-IF(Assumptions!$C$37=1,Assumptions!$C$68,IF(Assumptions!$C$37=2,Assumptions!$C$69,IF(K$2<=Assumptions!$C$41,Assumptions!$C$68,Assumptions!$C$69)))-Assumptions!$C$58-IF(Assumptions!$C$28=1,IF(K$2=1,Assumptions!$C$26,0),Assumptions!$C$26/Assumptions!$H$15)-Assumptions!$C$33+IF(K$2=Assumptions!$H$15,(INDEX('Pro Forma'!$D$26:$M$26,Assumptions!$H$15)+INDEX('Pro Forma'!$D$9:$M$9,Assumptions!$H$15)*(((1+Assumptions!$H$16+$O9)/(1+Assumptions!$H$16))^Assumptions!$H$15-1))/IF((Assumptions!$C$22+$P9)=0,1,Assumptions!$C$22+$P9)*(1-Assumptions!$C$23)-INDEX('Debt Schedule'!$C$8:$L$8,Assumptions!$H$15)-INDEX('Debt Schedule'!$C$19:$L$19,Assumptions!$H$15),0))} -> 0 | ... M9: {=IF(M$2>Assumptions!$H$15,0,(INDEX('Pro Forma'!$D$26:$M$26,M$2)+INDEX('Pro Forma'!$D$9:$M$9,M$2)*(((1+Assumptions!$H$16+$O9)/(1+Assumptions!$H$16))^M$2-1))-IF(Assumptions!$C$37=1,Assumptions!$C$68,IF(Assumptions!$C$37=2,Assumptions!$C$69,IF(M$2<=Assumptions!$C$41,Assumptions!$C$68,Assumptions!$C$69)))-Assumptions!$C$58-IF(Assumptions!$C$28=1,IF(M$2=1,Assumptions!$C$26,0),Assumptions!$C$26/Assumptions!$H$15)-Assumptions!$C$33+IF(M$2=Assumptions!$H$15,(INDEX('Pro Forma'!$D$26:$M$26,Assumptions!$H$15)+INDEX('Pro Forma'!$D$9:$M$9,Assumptions!$H$15)*(((1+Assumptions!$H$16+$O9)/(1+Assumptions!$H$16))^Assumptions!$H$15-1))/IF((Assumptions!$C$22+$P9)=0,1,Assumptions!$C$22+$P9)*(1-Assumptions!$C$23)-INDEX('Debt Schedule'!$C$8:$L$8,Assumptions!$H$15)-INDEX('Debt Schedule'!$C$19:$L$19,Assumptions!$H$15),0))} -> 0 | N9: =IFERROR(IRR(C9:M9),0) -> 0 | O9: =(MOD(ROW()-3,5)-2)*0.005 -> -0.005 | P9: =(INT((ROW()-3)/5)-2)*0.0025 -> -0.0025
C10: =-Assumptions!$C$70 -> 0 | D10: {=IF(D$2>Assumptions!$H$15,0,(INDEX('Pro Forma'!$D$26:$M$26,D$2)+INDEX('Pro Forma'!$D$9:$M$9,D$2)*(((1+Assumptions!$H$16+$O10)/(1+Assumptions!$H$16))^D$2-1))-IF(Assumptions!$C$37=1,Assumptions!$C$68,IF(Assumptions!$C$37=2,Assumptions!$C$69,IF(D$2<=Assumptions!$C$41,Assumptions!$C$68,Assumptions!$C$69)))-Assumptions!$C$58-IF(Assumptions!$C$28=1,IF(D$2=1,Assumptions!$C$26,0),Assumptions!$C$26/Assumptions!$H$15)-Assumptions!$C$33+IF(D$2=Assumptions!$H$15,(INDEX('Pro Forma'!$D$26:$M$26,Assumptions!$H$15)+INDEX('Pro Forma'!$D$9:$M$9,Assumptions!$H$15)*(((1+Assumptions!$H$16+$O10)/(1+Assumptions!$H$16))^Assumptions!$H$15-1))/IF((Assumptions!$C$22+$P10)=0,1,Assumptions!$C$22+$P10)*(1-Assumptions!$C$23)-INDEX('Debt Schedule'!$C$8:$L$8,Assumptions!$H$15)-INDEX('Debt Schedule'!$C$19:$L$19,Assumptions!$H$15),0))} -> 0 | E10: {=IF(E$2>Assumptions!$H$15,0,(INDEX('Pro Forma'!$D$26:$M$26,E$2)+INDEX('Pro Forma'!$D$9:$M$9,E$2)*(((1+Assumptions!$H$16+$O10)/(1+Assumptions!$H$16))^E$2-1))-IF(Assumptions!$C$37=1,Assumptions!$C$68,IF(Assumptions!$C$37=2,Assumptions!$C$69,IF(E$2<=Assumptions!$C$41,Assumptions!$C$68,Assumptions!$C$69)))-Assumptions!$C$58-IF(Assumptions!$C$28=1,IF(E$2=1,Assumptions!$C$26,0),Assumptions!$C$26/Assumptions!$H$15)-Assumptions!$C$33+IF(E$2=Assumptions!$H$15,(INDEX('Pro Forma'!$D$26:$M$26,Assumptions!$H$15)+INDEX('Pro Forma'!$D$9:$M$9,Assumptions!$H$15)*(((1+Assumptions!$H$16+$O10)/(1+Assumptions!$H$16))^Assumptions!$H$15-1))/IF((Assumptions!$C$22+$P10)=0,1,Assumptions!$C$22+$P10)*(1-Assumptions!$C$23)-INDEX('Debt Schedule'!$C$8:$L$8,Assumptions!$H$15)-INDEX('Debt Schedule'!$C$19:$L$19,Assumptions!$H$15),0))} -> 0 | F10: {=IF(F$2>Assumptions!$H$15,0,(INDEX('Pro Forma'!$D$26:$M$26,F$2)+INDEX('Pro Forma'!$D$9:$M$9,F$2)*(((1+Assumptions!$H$16+$O10)/(1+Assumptions!$H$16))^F$2-1))-IF(Assumptions!$C$37=1,Assumptions!$C$68,IF(Assumptions!$C$37=2,Assumptions!$C$69,IF(F$2<=Assumptions!$C$41,Assumptions!$C$68,Assumptions!$C$69)))-Assumptions!$C$58-IF(Assumptions!$C$28=1,IF(F$2=1,Assumptions!$C$26,0),Assumptions!$C$26/Assumptions!$H$15)-Assumptions!$C$33+IF(F$2=Assumptions!$H$15,(INDEX('Pro Forma'!$D$26:$M$26,Assumptions!$H$15)+INDEX('Pro Forma'!$D$9:$M$9,Assumptions!$H$15)*(((1+Assumptions!$H$16+$O10)/(1+Assumptions!$H$16))^Assumptions!$H$15-1))/IF((Assumptions!$C$22+$P10)=0,1,Assumptions!$C$22+$P10)*(1-Assumptions!$C$23)-INDEX('Debt Schedule'!$C$8:$L$8,Assumptions!$H$15)-INDEX('Debt Schedule'!$C$19:$L$19,Assumptions!$H$15),0))} -> 0 | G10: {=IF(G$2>Assumptions!$H$15,0,(INDEX('Pro Forma'!$D$26:$M$26,G$2)+INDEX('Pro Forma'!$D$9:$M$9,G$2)*(((1+Assumptions!$H$16+$O10)/(1+Assumptions!$H$16))^G$2-1))-IF(Assumptions!$C$37=1,Assumptions!$C$68,IF(Assumptions!$C$37=2,Assumptions!$C$69,IF(G$2<=Assumptions!$C$41,Assumptions!$C$68,Assumptions!$C$69)))-Assumptions!$C$58-IF(Assumptions!$C$28=1,IF(G$2=1,Assumptions!$C$26,0),Assumptions!$C$26/Assumptions!$H$15)-Assumptions!$C$33+IF(G$2=Assumptions!$H$15,(INDEX('Pro Forma'!$D$26:$M$26,Assumptions!$H$15)+INDEX('Pro Forma'!$D$9:$M$9,Assumptions!$H$15)*(((1+Assumptions!$H$16+$O10)/(1+Assumptions!$H$16))^Assumptions!$H$15-1))/IF((Assumptions!$C$22+$P10)=0,1,Assumptions!$C$22+$P10)*(1-Assumptions!$C$23)-INDEX('Debt Schedule'!$C$8:$L$8,Assumptions!$H$15)-INDEX('Debt Schedule'!$C$19:$L$19,Assumptions!$H$15),0))} -> 0 | H10: {=IF(H$2>Assumptions!$H$15,0,(INDEX('Pro Forma'!$D$26:$M$26,H$2)+INDEX('Pro Forma'!$D$9:$M$9,H$2)*(((1+Assumptions!$H$16+$O10)/(1+Assumptions!$H$16))^H$2-1))-IF(Assumptions!$C$37=1,Assumptions!$C$68,IF(Assumptions!$C$37=2,Assumptions!$C$69,IF(H$2<=Assumptions!$C$41,Assumptions!$C$68,Assumptions!$C$69)))-Assumptions!$C$58-IF(Assumptions!$C$28=1,IF(H$2=1,Assumptions!$C$26,0),Assumptions!$C$26/Assumptions!$H$15)-Assumptions!$C$33+IF(H$2=Assumptions!$H$15,(INDEX('Pro Forma'!$D$26:$M$26,Assumptions!$H$15)+INDEX('Pro Forma'!$D$9:$M$9,Assumptions!$H$15)*(((1+Assumptions!$H$16+$O10)/(1+Assumptions!$H$16))^Assumptions!$H$15-1))/IF((Assumptions!$C$22+$P10)=0,1,Assumptions!$C$22+$P10)*(1-Assumptions!$C$23)-INDEX('Debt Schedule'!$C$8:$L$8,Assumptions!$H$15)-INDEX('Debt Schedule'!$C$19:$L$19,Assumptions!$H$15),0))} -> 0 | I10: {=IF(I$2>Assumptions!$H$15,0,(INDEX('Pro Forma'!$D$26:$M$26,I$2)+INDEX('Pro Forma'!$D$9:$M$9,I$2)*(((1+Assumptions!$H$16+$O10)/(1+Assumptions!$H$16))^I$2-1))-IF(Assumptions!$C$37=1,Assumptions!$C$68,IF(Assumptions!$C$37=2,Assumptions!$C$69,IF(I$2<=Assumptions!$C$41,Assumptions!$C$68,Assumptions!$C$69)))-Assumptions!$C$58-IF(Assumptions!$C$28=1,IF(I$2=1,Assumptions!$C$26,0),Assumptions!$C$26/Assumptions!$H$15)-Assumptions!$C$33+IF(I$2=Assumptions!$H$15,(INDEX('Pro Forma'!$D$26:$M$26,Assumptions!$H$15)+INDEX('Pro Forma'!$D$9:$M$9,Assumptions!$H$15)*(((1+Assumptions!$H$16+$O10)/(1+Assumptions!$H$16))^Assumptions!$H$15-1))/IF((Assumptions!$C$22+$P10)=0,1,Assumptions!$C$22+$P10)*(1-Assumptions!$C$23)-INDEX('Debt Schedule'!$C$8:$L$8,Assumptions!$H$15)-INDEX('Debt Schedule'!$C$19:$L$19,Assumptions!$H$15),0))} -> 0 | J10: {=IF(J$2>Assumptions!$H$15,0,(INDEX('Pro Forma'!$D$26:$M$26,J$2)+INDEX('Pro Forma'!$D$9:$M$9,J$2)*(((1+Assumptions!$H$16+$O10)/(1+Assumptions!$H$16))^J$2-1))-IF(Assumptions!$C$37=1,Assumptions!$C$68,IF(Assumptions!$C$37=2,Assumptions!$C$69,IF(J$2<=Assumptions!$C$41,Assumptions!$C$68,Assumptions!$C$69)))-Assumptions!$C$58-IF(Assumptions!$C$28=1,IF(J$2=1,Assumptions!$C$26,0),Assumptions!$C$26/Assumptions!$H$15)-Assumptions!$C$33+IF(J$2=Assumptions!$H$15,(INDEX('Pro Forma'!$D$26:$M$26,Assumptions!$H$15)+INDEX('Pro Forma'!$D$9:$M$9,Assumptions!$H$15)*(((1+Assumptions!$H$16+$O10)/(1+Assumptions!$H$16))^Assumptions!$H$15-1))/IF((Assumptions!$C$22+$P10)=0,1,Assumptions!$C$22+$P10)*(1-Assumptions!$C$23)-INDEX('Debt Schedule'!$C$8:$L$8,Assumptions!$H$15)-INDEX('Debt Schedule'!$C$19:$L$19,Assumptions!$H$15),0))} -> 0 | K10: {=IF(K$2>Assumptions!$H$15,0,(INDEX('Pro Forma'!$D$26:$M$26,K$2)+INDEX('Pro Forma'!$D$9:$M$9,K$2)*(((1+Assumptions!$H$16+$O10)/(1+Assumptions!$H$16))^K$2-1))-IF(Assumptions!$C$37=1,Assumptions!$C$68,IF(Assumptions!$C$37=2,Assumptions!$C$69,IF(K$2<=Assumptions!$C$41,Assumptions!$C$68,Assumptions!$C$69)))-Assumptions!$C$58-IF(Assumptions!$C$28=1,IF(K$2=1,Assumptions!$C$26,0),Assumptions!$C$26/Assumptions!$H$15)-Assumptions!$C$33+IF(K$2=Assumptions!$H$15,(INDEX('Pro Forma'!$D$26:$M$26,Assumptions!$H$15)+INDEX('Pro Forma'!$D$9:$M$9,Assumptions!$H$15)*(((1+Assumptions!$H$16+$O10)/(1+Assumptions!$H$16))^Assumptions!$H$15-1))/IF((Assumptions!$C$22+$P10)=0,1,Assumptions!$C$22+$P10)*(1-Assumptions!$C$23)-INDEX('Debt Schedule'!$C$8:$L$8,Assumptions!$H$15)-INDEX('Debt Schedule'!$C$19:$L$19,Assumptions!$H$15),0))} -> 0 | ... M10: {=IF(M$2>Assumptions!$H$15,0,(INDEX('Pro Forma'!$D$26:$M$26,M$2)+INDEX('Pro Forma'!$D$9:$M$9,M$2)*(((1+Assumptions!$H$16+$O10)/(1+Assumptions!$H$16))^M$2-1))-IF(Assumptions!$C$37=1,Assumptions!$C$68,IF(Assumptions!$C$37=2,Assumptions!$C$69,IF(M$2<=Assumptions!$C$41,Assumptions!$C$68,Assumptions!$C$69)))-Assumptions!$C$58-IF(Assumptions!$C$28=1,IF(M$2=1,Assumptions!$C$26,0),Assumptions!$C$26/Assumptions!$H$15)-Assumptions!$C$33+IF(M$2=Assumptions!$H$15,(INDEX('Pro Forma'!$D$26:$M$26,Assumptions!$H$15)+INDEX('Pro Forma'!$D$9:$M$9,Assumptions!$H$15)*(((1+Assumptions!$H$16+$O10)/(1+Assumptions!$H$16))^Assumptions!$H$15-1))/IF((Assumptions!$C$22+$P10)=0,1,Assumptions!$C$22+$P10)*(1-Assumptions!$C$23)-INDEX('Debt Schedule'!$C$8:$L$8,Assumptions!$H$15)-INDEX('Debt Schedule'!$C$19:$L$19,Assumptions!$H$15),0))} -> 0 | N10: =IFERROR(IRR(C10:M10),0) -> 0 | O10: =(MOD(ROW()-3,5)-2)*0.005 -> 0 | P10: =(INT((ROW()-3)/5)-2)*0.0025 -> -0.0025
C11: =-Assumptions!$C$70 -> 0 | D11: {=IF(D$2>Assumptions!$H$15,0,(INDEX('Pro Forma'!$D$26:$M$26,D$2)+INDEX('Pro Forma'!$D$9:$M$9,D$2)*(((1+Assumptions!$H$16+$O11)/(1+Assumptions!$H$16))^D$2-1))-IF(Assumptions!$C$37=1,Assumptions!$C$68,IF(Assumptions!$C$37=2,Assumptions!$C$69,IF(D$2<=Assumptions!$C$41,Assumptions!$C$68,Assumptions!$C$69)))-Assumptions!$C$58-IF(Assumptions!$C$28=1,IF(D$2=1,Assumptions!$C$26,0),Assumptions!$C$26/Assumptions!$H$15)-Assumptions!$C$33+IF(D$2=Assumptions!$H$15,(INDEX('Pro Forma'!$D$26:$M$26,Assumptions!$H$15)+INDEX('Pro Forma'!$D$9:$M$9,Assumptions!$H$15)*(((1+Assumptions!$H$16+$O11)/(1+Assumptions!$H$16))^Assumptions!$H$15-1))/IF((Assumptions!$C$22+$P11)=0,1,Assumptions!$C$22+$P11)*(1-Assumptions!$C$23)-INDEX('Debt Schedule'!$C$8:$L$8,Assumptions!$H$15)-INDEX('Debt Schedule'!$C$19:$L$19,Assumptions!$H$15),0))} -> 0 | E11: {=IF(E$2>Assumptions!$H$15,0,(INDEX('Pro Forma'!$D$26:$M$26,E$2)+INDEX('Pro Forma'!$D$9:$M$9,E$2)*(((1+Assumptions!$H$16+$O11)/(1+Assumptions!$H$16))^E$2-1))-IF(Assumptions!$C$37=1,Assumptions!$C$68,IF(Assumptions!$C$37=2,Assumptions!$C$69,IF(E$2<=Assumptions!$C$41,Assumptions!$C$68,Assumptions!$C$69)))-Assumptions!$C$58-IF(Assumptions!$C$28=1,IF(E$2=1,Assumptions!$C$26,0),Assumptions!$C$26/Assumptions!$H$15)-Assumptions!$C$33+IF(E$2=Assumptions!$H$15,(INDEX('Pro Forma'!$D$26:$M$26,Assumptions!$H$15)+INDEX('Pro Forma'!$D$9:$M$9,Assumptions!$H$15)*(((1+Assumptions!$H$16+$O11)/(1+Assumptions!$H$16))^Assumptions!$H$15-1))/IF((Assumptions!$C$22+$P11)=0,1,Assumptions!$C$22+$P11)*(1-Assumptions!$C$23)-INDEX('Debt Schedule'!$C$8:$L$8,Assumptions!$H$15)-INDEX('Debt Schedule'!$C$19:$L$19,Assumptions!$H$15),0))} -> 0 | F11: {=IF(F$2>Assumptions!$H$15,0,(INDEX('Pro Forma'!$D$26:$M$26,F$2)+INDEX('Pro Forma'!$D$9:$M$9,F$2)*(((1+Assumptions!$H$16+$O11)/(1+Assumptions!$H$16))^F$2-1))-IF(Assumptions!$C$37=1,Assumptions!$C$68,IF(Assumptions!$C$37=2,Assumptions!$C$69,IF(F$2<=Assumptions!$C$41,Assumptions!$C$68,Assumptions!$C$69)))-Assumptions!$C$58-IF(Assumptions!$C$28=1,IF(F$2=1,Assumptions!$C$26,0),Assumptions!$C$26/Assumptions!$H$15)-Assumptions!$C$33+IF(F$2=Assumptions!$H$15,(INDEX('Pro Forma'!$D$26:$M$26,Assumptions!$H$15)+INDEX('Pro Forma'!$D$9:$M$9,Assumptions!$H$15)*(((1+Assumptions!$H$16+$O11)/(1+Assumptions!$H$16))^Assumptions!$H$15-1))/IF((Assumptions!$C$22+$P11)=0,1,Assumptions!$C$22+$P11)*(1-Assumptions!$C$23)-INDEX('Debt Schedule'!$C$8:$L$8,Assumptions!$H$15)-INDEX('Debt Schedule'!$C$19:$L$19,Assumptions!$H$15),0))} -> 0 | G11: {=IF(G$2>Assumptions!$H$15,0,(INDEX('Pro Forma'!$D$26:$M$26,G$2)+INDEX('Pro Forma'!$D$9:$M$9,G$2)*(((1+Assumptions!$H$16+$O11)/(1+Assumptions!$H$16))^G$2-1))-IF(Assumptions!$C$37=1,Assumptions!$C$68,IF(Assumptions!$C$37=2,Assumptions!$C$69,IF(G$2<=Assumptions!$C$41,Assumptions!$C$68,Assumptions!$C$69)))-Assumptions!$C$58-IF(Assumptions!$C$28=1,IF(G$2=1,Assumptions!$C$26,0),Assumptions!$C$26/Assumptions!$H$15)-Assumptions!$C$33+IF(G$2=Assumptions!$H$15,(INDEX('Pro Forma'!$D$26:$M$26,Assumptions!$H$15)+INDEX('Pro Forma'!$D$9:$M$9,Assumptions!$H$15)*(((1+Assumptions!$H$16+$O11)/(1+Assumptions!$H$16))^Assumptions!$H$15-1))/IF((Assumptions!$C$22+$P11)=0,1,Assumptions!$C$22+$P11)*(1-Assumptions!$C$23)-INDEX('Debt Schedule'!$C$8:$L$8,Assumptions!$H$15)-INDEX('Debt Schedule'!$C$19:$L$19,Assumptions!$H$15),0))} -> 0 | H11: {=IF(H$2>Assumptions!$H$15,0,(INDEX('Pro Forma'!$D$26:$M$26,H$2)+INDEX('Pro Forma'!$D$9:$M$9,H$2)*(((1+Assumptions!$H$16+$O11)/(1+Assumptions!$H$16))^H$2-1))-IF(Assumptions!$C$37=1,Assumptions!$C$68,IF(Assumptions!$C$37=2,Assumptions!$C$69,IF(H$2<=Assumptions!$C$41,Assumptions!$C$68,Assumptions!$C$69)))-Assumptions!$C$58-IF(Assumptions!$C$28=1,IF(H$2=1,Assumptions!$C$26,0),Assumptions!$C$26/Assumptions!$H$15)-Assumptions!$C$33+IF(H$2=Assumptions!$H$15,(INDEX('Pro Forma'!$D$26:$M$26,Assumptions!$H$15)+INDEX('Pro Forma'!$D$9:$M$9,Assumptions!$H$15)*(((1+Assumptions!$H$16+$O11)/(1+Assumptions!$H$16))^Assumptions!$H$15-1))/IF((Assumptions!$C$22+$P11)=0,1,Assumptions!$C$22+$P11)*(1-Assumptions!$C$23)-INDEX('Debt Schedule'!$C$8:$L$8,Assumptions!$H$15)-INDEX('Debt Schedule'!$C$19:$L$19,Assumptions!$H$15),0))} -> 0 | I11: {=IF(I$2>Assumptions!$H$15,0,(INDEX('Pro Forma'!$D$26:$M$26,I$2)+INDEX('Pro Forma'!$D$9:$M$9,I$2)*(((1+Assumptions!$H$16+$O11)/(1+Assumptions!$H$16))^I$2-1))-IF(Assumptions!$C$37=1,Assumptions!$C$68,IF(Assumptions!$C$37=2,Assumptions!$C$69,IF(I$2<=Assumptions!$C$41,Assumptions!$C$68,Assumptions!$C$69)))-Assumptions!$C$58-IF(Assumptions!$C$28=1,IF(I$2=1,Assumptions!$C$26,0),Assumptions!$C$26/Assumptions!$H$15)-Assumptions!$C$33+IF(I$2=Assumptions!$H$15,(INDEX('Pro Forma'!$D$26:$M$26,Assumptions!$H$15)+INDEX('Pro Forma'!$D$9:$M$9,Assumptions!$H$15)*(((1+Assumptions!$H$16+$O11)/(1+Assumptions!$H$16))^Assumptions!$H$15-1))/IF((Assumptions!$C$22+$P11)=0,1,Assumptions!$C$22+$P11)*(1-Assumptions!$C$23)-INDEX('Debt Schedule'!$C$8:$L$8,Assumptions!$H$15)-INDEX('Debt Schedule'!$C$19:$L$19,Assumptions!$H$15),0))} -> 0 | J11: {=IF(J$2>Assumptions!$H$15,0,(INDEX('Pro Forma'!$D$26:$M$26,J$2)+INDEX('Pro Forma'!$D$9:$M$9,J$2)*(((1+Assumptions!$H$16+$O11)/(1+Assumptions!$H$16))^J$2-1))-IF(Assumptions!$C$37=1,Assumptions!$C$68,IF(Assumptions!$C$37=2,Assumptions!$C$69,IF(J$2<=Assumptions!$C$41,Assumptions!$C$68,Assumptions!$C$69)))-Assumptions!$C$58-IF(Assumptions!$C$28=1,IF(J$2=1,Assumptions!$C$26,0),Assumptions!$C$26/Assumptions!$H$15)-Assumptions!$C$33+IF(J$2=Assumptions!$H$15,(INDEX('Pro Forma'!$D$26:$M$26,Assumptions!$H$15)+INDEX('Pro Forma'!$D$9:$M$9,Assumptions!$H$15)*(((1+Assumptions!$H$16+$O11)/(1+Assumptions!$H$16))^Assumptions!$H$15-1))/IF((Assumptions!$C$22+$P11)=0,1,Assumptions!$C$22+$P11)*(1-Assumptions!$C$23)-INDEX('Debt Schedule'!$C$8:$L$8,Assumptions!$H$15)-INDEX('Debt Schedule'!$C$19:$L$19,Assumptions!$H$15),0))} -> 0 | K11: {=IF(K$2>Assumptions!$H$15,0,(INDEX('Pro Forma'!$D$26:$M$26,K$2)+INDEX('Pro Forma'!$D$9:$M$9,K$2)*(((1+Assumptions!$H$16+$O11)/(1+Assumptions!$H$16))^K$2-1))-IF(Assumptions!$C$37=1,Assumptions!$C$68,IF(Assumptions!$C$37=2,Assumptions!$C$69,IF(K$2<=Assumptions!$C$41,Assumptions!$C$68,Assumptions!$C$69)))-Assumptions!$C$58-IF(Assumptions!$C$28=1,IF(K$2=1,Assumptions!$C$26,0),Assumptions!$C$26/Assumptions!$H$15)-Assumptions!$C$33+IF(K$2=Assumptions!$H$15,(INDEX('Pro Forma'!$D$26:$M$26,Assumptions!$H$15)+INDEX('Pro Forma'!$D$9:$M$9,Assumptions!$H$15)*(((1+Assumptions!$H$16+$O11)/(1+Assumptions!$H$16))^Assumptions!$H$15-1))/IF((Assumptions!$C$22+$P11)=0,1,Assumptions!$C$22+$P11)*(1-Assumptions!$C$23)-INDEX('Debt Schedule'!$C$8:$L$8,Assumptions!$H$15)-INDEX('Debt Schedule'!$C$19:$L$19,Assumptions!$H$15),0))} -> 0 | ... M11: {=IF(M$2>Assumptions!$H$15,0,(INDEX('Pro Forma'!$D$26:$M$26,M$2)+INDEX('Pro Forma'!$D$9:$M$9,M$2)*(((1+Assumptions!$H$16+$O11)/(1+Assumptions!$H$16))^M$2-1))-IF(Assumptions!$C$37=1,Assumptions!$C$68,IF(Assumptions!$C$37=2,Assumptions!$C$69,IF(M$2<=Assumptions!$C$41,Assumptions!$C$68,Assumptions!$C$69)))-Assumptions!$C$58-IF(Assumptions!$C$28=1,IF(M$2=1,Assumptions!$C$26,0),Assumptions!$C$26/Assumptions!$H$15)-Assumptions!$C$33+IF(M$2=Assumptions!$H$15,(INDEX('Pro Forma'!$D$26:$M$26,Assumptions!$H$15)+INDEX('Pro Forma'!$D$9:$M$9,Assumptions!$H$15)*(((1+Assumptions!$H$16+$O11)/(1+Assumptions!$H$16))^Assumptions!$H$15-1))/IF((Assumptions!$C$22+$P11)=0,1,Assumptions!$C$22+$P11)*(1-Assumptions!$C$23)-INDEX('Debt Schedule'!$C$8:$L$8,Assumptions!$H$15)-INDEX('Debt Schedule'!$C$19:$L$19,Assumptions!$H$15),0))} -> 0 | N11: =IFERROR(IRR(C11:M11),0) -> 0 | O11: =(MOD(ROW()-3,5)-2)*0.005 -> 0.005 | P11: =(INT((ROW()-3)/5)-2)*0.0025 -> -0.0025
C12: =-Assumptions!$C$70 -> 0 | D12: {=IF(D$2>Assumptions!$H$15,0,(INDEX('Pro Forma'!$D$26:$M$26,D$2)+INDEX('Pro Forma'!$D$9:$M$9,D$2)*(((1+Assumptions!$H$16+$O12)/(1+Assumptions!$H$16))^D$2-1))-IF(Assumptions!$C$37=1,Assumptions!$C$68,IF(Assumptions!$C$37=2,Assumptions!$C$69,IF(D$2<=Assumptions!$C$41,Assumptions!$C$68,Assumptions!$C$69)))-Assumptions!$C$58-IF(Assumptions!$C$28=1,IF(D$2=1,Assumptions!$C$26,0),Assumptions!$C$26/Assumptions!$H$15)-Assumptions!$C$33+IF(D$2=Assumptions!$H$15,(INDEX('Pro Forma'!$D$26:$M$26,Assumptions!$H$15)+INDEX('Pro Forma'!$D$9:$M$9,Assumptions!$H$15)*(((1+Assumptions!$H$16+$O12)/(1+Assumptions!$H$16))^Assumptions!$H$15-1))/IF((Assumptions!$C$22+$P12)=0,1,Assumptions!$C$22+$P12)*(1-Assumptions!$C$23)-INDEX('Debt Schedule'!$C$8:$L$8,Assumptions!$H$15)-INDEX('Debt Schedule'!$C$19:$L$19,Assumptions!$H$15),0))} -> 0 | E12: {=IF(E$2>Assumptions!$H$15,0,(INDEX('Pro Forma'!$D$26:$M$26,E$2)+INDEX('Pro Forma'!$D$9:$M$9,E$2)*(((1+Assumptions!$H$16+$O12)/(1+Assumptions!$H$16))^E$2-1))-IF(Assumptions!$C$37=1,Assumptions!$C$68,IF(Assumptions!$C$37=2,Assumptions!$C$69,IF(E$2<=Assumptions!$C$41,Assumptions!$C$68,Assumptions!$C$69)))-Assumptions!$C$58-IF(Assumptions!$C$28=1,IF(E$2=1,Assumptions!$C$26,0),Assumptions!$C$26/Assumptions!$H$15)-Assumptions!$C$33+IF(E$2=Assumptions!$H$15,(INDEX('Pro Forma'!$D$26:$M$26,Assumptions!$H$15)+INDEX('Pro Forma'!$D$9:$M$9,Assumptions!$H$15)*(((1+Assumptions!$H$16+$O12)/(1+Assumptions!$H$16))^Assumptions!$H$15-1))/IF((Assumptions!$C$22+$P12)=0,1,Assumptions!$C$22+$P12)*(1-Assumptions!$C$23)-INDEX('Debt Schedule'!$C$8:$L$8,Assumptions!$H$15)-INDEX('Debt Schedule'!$C$19:$L$19,Assumptions!$H$15),0))} -> 0 | F12: {=IF(F$2>Assumptions!$H$15,0,(INDEX('Pro Forma'!$D$26:$M$26,F$2)+INDEX('Pro Forma'!$D$9:$M$9,F$2)*(((1+Assumptions!$H$16+$O12)/(1+Assumptions!$H$16))^F$2-1))-IF(Assumptions!$C$37=1,Assumptions!$C$68,IF(Assumptions!$C$37=2,Assumptions!$C$69,IF(F$2<=Assumptions!$C$41,Assumptions!$C$68,Assumptions!$C$69)))-Assumptions!$C$58-IF(Assumptions!$C$28=1,IF(F$2=1,Assumptions!$C$26,0),Assumptions!$C$26/Assumptions!$H$15)-Assumptions!$C$33+IF(F$2=Assumptions!$H$15,(INDEX('Pro Forma'!$D$26:$M$26,Assumptions!$H$15)+INDEX('Pro Forma'!$D$9:$M$9,Assumptions!$H$15)*(((1+Assumptions!$H$16+$O12)/(1+Assumptions!$H$16))^Assumptions!$H$15-1))/IF((Assumptions!$C$22+$P12)=0,1,Assumptions!$C$22+$P12)*(1-Assumptions!$C$23)-INDEX('Debt Schedule'!$C$8:$L$8,Assumptions!$H$15)-INDEX('Debt Schedule'!$C$19:$L$19,Assumptions!$H$15),0))} -> 0 | G12: {=IF(G$2>Assumptions!$H$15,0,(INDEX('Pro Forma'!$D$26:$M$26,G$2)+INDEX('Pro Forma'!$D$9:$M$9,G$2)*(((1+Assumptions!$H$16+$O12)/(1+Assumptions!$H$16))^G$2-1))-IF(Assumptions!$C$37=1,Assumptions!$C$68,IF(Assumptions!$C$37=2,Assumptions!$C$69,IF(G$2<=Assumptions!$C$41,Assumptions!$C$68,Assumptions!$C$69)))-Assumptions!$C$58-IF(Assumptions!$C$28=1,IF(G$2=1,Assumptions!$C$26,0),Assumptions!$C$26/Assumptions!$H$15)-Assumptions!$C$33+IF(G$2=Assumptions!$H$15,(INDEX('Pro Forma'!$D$26:$M$26,Assumptions!$H$15)+INDEX('Pro Forma'!$D$9:$M$9,Assumptions!$H$15)*(((1+Assumptions!$H$16+$O12)/(1+Assumptions!$H$16))^Assumptions!$H$15-1))/IF((Assumptions!$C$22+$P12)=0,1,Assumptions!$C$22+$P12)*(1-Assumptions!$C$23)-INDEX('Debt Schedule'!$C$8:$L$8,Assumptions!$H$15)-INDEX('Debt Schedule'!$C$19:$L$19,Assumptions!$H$15),0))} -> 0 | H12: {=IF(H$2>Assumptions!$H$15,0,(INDEX('Pro Forma'!$D$26:$M$26,H$2)+INDEX('Pro Forma'!$D$9:$M$9,H$2)*(((1+Assumptions!$H$16+$O12)/(1+Assumptions!$H$16))^H$2-1))-IF(Assumptions!$C$37=1,Assumptions!$C$68,IF(Assumptions!$C$37=2,Assumptions!$C$69,IF(H$2<=Assumptions!$C$41,Assumptions!$C$68,Assumptions!$C$69)))-Assumptions!$C$58-IF(Assumptions!$C$28=1,IF(H$2=1,Assumptions!$C$26,0),Assumptions!$C$26/Assumptions!$H$15)-Assumptions!$C$33+IF(H$2=Assumptions!$H$15,(INDEX('Pro Forma'!$D$26:$M$26,Assumptions!$H$15)+INDEX('Pro Forma'!$D$9:$M$9,Assumptions!$H$15)*(((1+Assumptions!$H$16+$O12)/(1+Assumptions!$H$16))^Assumptions!$H$15-1))/IF((Assumptions!$C$22+$P12)=0,1,Assumptions!$C$22+$P12)*(1-Assumptions!$C$23)-INDEX('Debt Schedule'!$C$8:$L$8,Assumptions!$H$15)-INDEX('Debt Schedule'!$C$19:$L$19,Assumptions!$H$15),0))} -> 0 | I12: {=IF(I$2>Assumptions!$H$15,0,(INDEX('Pro Forma'!$D$26:$M$26,I$2)+INDEX('Pro Forma'!$D$9:$M$9,I$2)*(((1+Assumptions!$H$16+$O12)/(1+Assumptions!$H$16))^I$2-1))-IF(Assumptions!$C$37=1,Assumptions!$C$68,IF(Assumptions!$C$37=2,Assumptions!$C$69,IF(I$2<=Assumptions!$C$41,Assumptions!$C$68,Assumptions!$C$69)))-Assumptions!$C$58-IF(Assumptions!$C$28=1,IF(I$2=1,Assumptions!$C$26,0),Assumptions!$C$26/Assumptions!$H$15)-Assumptions!$C$33+IF(I$2=Assumptions!$H$15,(INDEX('Pro Forma'!$D$26:$M$26,Assumptions!$H$15)+INDEX('Pro Forma'!$D$9:$M$9,Assumptions!$H$15)*(((1+Assumptions!$H$16+$O12)/(1+Assumptions!$H$16))^Assumptions!$H$15-1))/IF((Assumptions!$C$22+$P12)=0,1,Assumptions!$C$22+$P12)*(1-Assumptions!$C$23)-INDEX('Debt Schedule'!$C$8:$L$8,Assumptions!$H$15)-INDEX('Debt Schedule'!$C$19:$L$19,Assumptions!$H$15),0))} -> 0 | J12: {=IF(J$2>Assumptions!$H$15,0,(INDEX('Pro Forma'!$D$26:$M$26,J$2)+INDEX('Pro Forma'!$D$9:$M$9,J$2)*(((1+Assumptions!$H$16+$O12)/(1+Assumptions!$H$16))^J$2-1))-IF(Assumptions!$C$37=1,Assumptions!$C$68,IF(Assumptions!$C$37=2,Assumptions!$C$69,IF(J$2<=Assumptions!$C$41,Assumptions!$C$68,Assumptions!$C$69)))-Assumptions!$C$58-IF(Assumptions!$C$28=1,IF(J$2=1,Assumptions!$C$26,0),Assumptions!$C$26/Assumptions!$H$15)-Assumptions!$C$33+IF(J$2=Assumptions!$H$15,(INDEX('Pro Forma'!$D$26:$M$26,Assumptions!$H$15)+INDEX('Pro Forma'!$D$9:$M$9,Assumptions!$H$15)*(((1+Assumptions!$H$16+$O12)/(1+Assumptions!$H$16))^Assumptions!$H$15-1))/IF((Assumptions!$C$22+$P12)=0,1,Assumptions!$C$22+$P12)*(1-Assumptions!$C$23)-INDEX('Debt Schedule'!$C$8:$L$8,Assumptions!$H$15)-INDEX('Debt Schedule'!$C$19:$L$19,Assumptions!$H$15),0))} -> 0 | K12: {=IF(K$2>Assumptions!$H$15,0,(INDEX('Pro Forma'!$D$26:$M$26,K$2)+INDEX('Pro Forma'!$D$9:$M$9,K$2)*(((1+Assumptions!$H$16+$O12)/(1+Assumptions!$H$16))^K$2-1))-IF(Assumptions!$C$37=1,Assumptions!$C$68,IF(Assumptions!$C$37=2,Assumptions!$C$69,IF(K$2<=Assumptions!$C$41,Assumptions!$C$68,Assumptions!$C$69)))-Assumptions!$C$58-IF(Assumptions!$C$28=1,IF(K$2=1,Assumptions!$C$26,0),Assumptions!$C$26/Assumptions!$H$15)-Assumptions!$C$33+IF(K$2=Assumptions!$H$15,(INDEX('Pro Forma'!$D$26:$M$26,Assumptions!$H$15)+INDEX('Pro Forma'!$D$9:$M$9,Assumptions!$H$15)*(((1+Assumptions!$H$16+$O12)/(1+Assumptions!$H$16))^Assumptions!$H$15-1))/IF((Assumptions!$C$22+$P12)=0,1,Assumptions!$C$22+$P12)*(1-Assumptions!$C$23)-INDEX('Debt Schedule'!$C$8:$L$8,Assumptions!$H$15)-INDEX('Debt Schedule'!$C$19:$L$19,Assumptions!$H$15),0))} -> 0 | ... M12: {=IF(M$2>Assumptions!$H$15,0,(INDEX('Pro Forma'!$D$26:$M$26,M$2)+INDEX('Pro Forma'!$D$9:$M$9,M$2)*(((1+Assumptions!$H$16+$O12)/(1+Assumptions!$H$16))^M$2-1))-IF(Assumptions!$C$37=1,Assumptions!$C$68,IF(Assumptions!$C$37=2,Assumptions!$C$69,IF(M$2<=Assumptions!$C$41,Assumptions!$C$68,Assumptions!$C$69)))-Assumptions!$C$58-IF(Assumptions!$C$28=1,IF(M$2=1,Assumptions!$C$26,0),Assumptions!$C$26/Assumptions!$H$15)-Assumptions!$C$33+IF(M$2=Assumptions!$H$15,(INDEX('Pro Forma'!$D$26:$M$26,Assumptions!$H$15)+INDEX('Pro Forma'!$D$9:$M$9,Assumptions!$H$15)*(((1+Assumptions!$H$16+$O12)/(1+Assumptions!$H$16))^Assumptions!$H$15-1))/IF((Assumptions!$C$22+$P12)=0,1,Assumptions!$C$22+$P12)*(1-Assumptions!$C$23)-INDEX('Debt Schedule'!$C$8:$L$8,Assumptions!$H$15)-INDEX('Debt Schedule'!$C$19:$L$19,Assumptions!$H$15),0))} -> 0 | N12: =IFERROR(IRR(C12:M12),0) -> 0 | O12: =(MOD(ROW()-3,5)-2)*0.005 -> 0.01 | P12: =(INT((ROW()-3)/5)-2)*0.0025 -> -0.0025
C13: =-Assumptions!$C$70 -> 0 | D13: {=IF(D$2>Assumptions!$H$15,0,(INDEX('Pro Forma'!$D$26:$M$26,D$2)+INDEX('Pro Forma'!$D$9:$M$9,D$2)*(((1+Assumptions!$H$16+$O13)/(1+Assumptions!$H$16))^D$2-1))-IF(Assumptions!$C$37=1,Assumptions!$C$68,IF(Assumptions!$C$37=2,Assumptions!$C$69,IF(D$2<=Assumptions!$C$41,Assumptions!$C$68,Assumptions!$C$69)))-Assumptions!$C$58-IF(Assumptions!$C$28=1,IF(D$2=1,Assumptions!$C$26,0),Assumptions!$C$26/Assumptions!$H$15)-Assumptions!$C$33+IF(D$2=Assumptions!$H$15,(INDEX('Pro Forma'!$D$26:$M$26,Assumptions!$H$15)+INDEX('Pro Forma'!$D$9:$M$9,Assumptions!$H$15)*(((1+Assumptions!$H$16+$O13)/(1+Assumptions!$H$16))^Assumptions!$H$15-1))/IF((Assumptions!$C$22+$P13)=0,1,Assumptions!$C$22+$P13)*(1-Assumptions!$C$23)-INDEX('Debt Schedule'!$C$8:$L$8,Assumptions!$H$15)-INDEX('Debt Schedule'!$C$19:$L$19,Assumptions!$H$15),0))} -> 0 | E13: {=IF(E$2>Assumptions!$H$15,0,(INDEX('Pro Forma'!$D$26:$M$26,E$2)+INDEX('Pro Forma'!$D$9:$M$9,E$2)*(((1+Assumptions!$H$16+$O13)/(1+Assumptions!$H$16))^E$2-1))-IF(Assumptions!$C$37=1,Assumptions!$C$68,IF(Assumptions!$C$37=2,Assumptions!$C$69,IF(E$2<=Assumptions!$C$41,Assumptions!$C$68,Assumptions!$C$69)))-Assumptions!$C$58-IF(Assumptions!$C$28=1,IF(E$2=1,Assumptions!$C$26,0),Assumptions!$C$26/Assumptions!$H$15)-Assumptions!$C$33+IF(E$2=Assumptions!$H$15,(INDEX('Pro Forma'!$D$26:$M$26,Assumptions!$H$15)+INDEX('Pro Forma'!$D$9:$M$9,Assumptions!$H$15)*(((1+Assumptions!$H$16+$O13)/(1+Assumptions!$H$16))^Assumptions!$H$15-1))/IF((Assumptions!$C$22+$P13)=0,1,Assumptions!$C$22+$P13)*(1-Assumptions!$C$23)-INDEX('Debt Schedule'!$C$8:$L$8,Assumptions!$H$15)-INDEX('Debt Schedule'!$C$19:$L$19,Assumptions!$H$15),0))} -> 0 | F13: {=IF(F$2>Assumptions!$H$15,0,(INDEX('Pro Forma'!$D$26:$M$26,F$2)+INDEX('Pro Forma'!$D$9:$M$9,F$2)*(((1+Assumptions!$H$16+$O13)/(1+Assumptions!$H$16))^F$2-1))-IF(Assumptions!$C$37=1,Assumptions!$C$68,IF(Assumptions!$C$37=2,Assumptions!$C$69,IF(F$2<=Assumptions!$C$41,Assumptions!$C$68,Assumptions!$C$69)))-Assumptions!$C$58-IF(Assumptions!$C$28=1,IF(F$2=1,Assumptions!$C$26,0),Assumptions!$C$26/Assumptions!$H$15)-Assumptions!$C$33+IF(F$2=Assumptions!$H$15,(INDEX('Pro Forma'!$D$26:$M$26,Assumptions!$H$15)+INDEX('Pro Forma'!$D$9:$M$9,Assumptions!$H$15)*(((1+Assumptions!$H$16+$O13)/(1+Assumptions!$H$16))^Assumptions!$H$15-1))/IF((Assumptions!$C$22+$P13)=0,1,Assumptions!$C$22+$P13)*(1-Assumptions!$C$23)-INDEX('Debt Schedule'!$C$8:$L$8,Assumptions!$H$15)-INDEX('Debt Schedule'!$C$19:$L$19,Assumptions!$H$15),0))} -> 0 | G13: {=IF(G$2>Assumptions!$H$15,0,(INDEX('Pro Forma'!$D$26:$M$26,G$2)+INDEX('Pro Forma'!$D$9:$M$9,G$2)*(((1+Assumptions!$H$16+$O13)/(1+Assumptions!$H$16))^G$2-1))-IF(Assumptions!$C$37=1,Assumptions!$C$68,IF(Assumptions!$C$37=2,Assumptions!$C$69,IF(G$2<=Assumptions!$C$41,Assumptions!$C$68,Assumptions!$C$69)))-Assumptions!$C$58-IF(Assumptions!$C$28=1,IF(G$2=1,Assumptions!$C$26,0),Assumptions!$C$26/Assumptions!$H$15)-Assumptions!$C$33+IF(G$2=Assumptions!$H$15,(INDEX('Pro Forma'!$D$26:$M$26,Assumptions!$H$15)+INDEX('Pro Forma'!$D$9:$M$9,Assumptions!$H$15)*(((1+Assumptions!$H$16+$O13)/(1+Assumptions!$H$16))^Assumptions!$H$15-1))/IF((Assumptions!$C$22+$P13)=0,1,Assumptions!$C$22+$P13)*(1-Assumptions!$C$23)-INDEX('Debt Schedule'!$C$8:$L$8,Assumptions!$H$15)-INDEX('Debt Schedule'!$C$19:$L$19,Assumptions!$H$15),0))} -> 0 | H13: {=IF(H$2>Assumptions!$H$15,0,(INDEX('Pro Forma'!$D$26:$M$26,H$2)+INDEX('Pro Forma'!$D$9:$M$9,H$2)*(((1+Assumptions!$H$16+$O13)/(1+Assumptions!$H$16))^H$2-1))-IF(Assumptions!$C$37=1,Assumptions!$C$68,IF(Assumptions!$C$37=2,Assumptions!$C$69,IF(H$2<=Assumptions!$C$41,Assumptions!$C$68,Assumptions!$C$69)))-Assumptions!$C$58-IF(Assumptions!$C$28=1,IF(H$2=1,Assumptions!$C$26,0),Assumptions!$C$26/Assumptions!$H$15)-Assumptions!$C$33+IF(H$2=Assumptions!$H$15,(INDEX('Pro Forma'!$D$26:$M$26,Assumptions!$H$15)+INDEX('Pro Forma'!$D$9:$M$9,Assumptions!$H$15)*(((1+Assumptions!$H$16+$O13)/(1+Assumptions!$H$16))^Assumptions!$H$15-1))/IF((Assumptions!$C$22+$P13)=0,1,Assumptions!$C$22+$P13)*(1-Assumptions!$C$23)-INDEX('Debt Schedule'!$C$8:$L$8,Assumptions!$H$15)-INDEX('Debt Schedule'!$C$19:$L$19,Assumptions!$H$15),0))} -> 0 | I13: {=IF(I$2>Assumptions!$H$15,0,(INDEX('Pro Forma'!$D$26:$M$26,I$2)+INDEX('Pro Forma'!$D$9:$M$9,I$2)*(((1+Assumptions!$H$16+$O13)/(1+Assumptions!$H$16))^I$2-1))-IF(Assumptions!$C$37=1,Assumptions!$C$68,IF(Assumptions!$C$37=2,Assumptions!$C$69,IF(I$2<=Assumptions!$C$41,Assumptions!$C$68,Assumptions!$C$69)))-Assumptions!$C$58-IF(Assumptions!$C$28=1,IF(I$2=1,Assumptions!$C$26,0),Assumptions!$C$26/Assumptions!$H$15)-Assumptions!$C$33+IF(I$2=Assumptions!$H$15,(INDEX('Pro Forma'!$D$26:$M$26,Assumptions!$H$15)+INDEX('Pro Forma'!$D$9:$M$9,Assumptions!$H$15)*(((1+Assumptions!$H$16+$O13)/(1+Assumptions!$H$16))^Assumptions!$H$15-1))/IF((Assumptions!$C$22+$P13)=0,1,Assumptions!$C$22+$P13)*(1-Assumptions!$C$23)-INDEX('Debt Schedule'!$C$8:$L$8,Assumptions!$H$15)-INDEX('Debt Schedule'!$C$19:$L$19,Assumptions!$H$15),0))} -> 0 | J13: {=IF(J$2>Assumptions!$H$15,0,(INDEX('Pro Forma'!$D$26:$M$26,J$2)+INDEX('Pro Forma'!$D$9:$M$9,J$2)*(((1+Assumptions!$H$16+$O13)/(1+Assumptions!$H$16))^J$2-1))-IF(Assumptions!$C$37=1,Assumptions!$C$68,IF(Assumptions!$C$37=2,Assumptions!$C$69,IF(J$2<=Assumptions!$C$41,Assumptions!$C$68,Assumptions!$C$69)))-Assumptions!$C$58-IF(Assumptions!$C$28=1,IF(J$2=1,Assumptions!$C$26,0),Assumptions!$C$26/Assumptions!$H$15)-Assumptions!$C$33+IF(J$2=Assumptions!$H$15,(INDEX('Pro Forma'!$D$26:$M$26,Assumptions!$H$15)+INDEX('Pro Forma'!$D$9:$M$9,Assumptions!$H$15)*(((1+Assumptions!$H$16+$O13)/(1+Assumptions!$H$16))^Assumptions!$H$15-1))/IF((Assumptions!$C$22+$P13)=0,1,Assumptions!$C$22+$P13)*(1-Assumptions!$C$23)-INDEX('Debt Schedule'!$C$8:$L$8,Assumptions!$H$15)-INDEX('Debt Schedule'!$C$19:$L$19,Assumptions!$H$15),0))} -> 0 | K13: {=IF(K$2>Assumptions!$H$15,0,(INDEX('Pro Forma'!$D$26:$M$26,K$2)+INDEX('Pro Forma'!$D$9:$M$9,K$2)*(((1+Assumptions!$H$16+$O13)/(1+Assumptions!$H$16))^K$2-1))-IF(Assumptions!$C$37=1,Assumptions!$C$68,IF(Assumptions!$C$37=2,Assumptions!$C$69,IF(K$2<=Assumptions!$C$41,Assumptions!$C$68,Assumptions!$C$69)))-Assumptions!$C$58-IF(Assumptions!$C$28=1,IF(K$2=1,Assumptions!$C$26,0),Assumptions!$C$26/Assumptions!$H$15)-Assumptions!$C$33+IF(K$2=Assumptions!$H$15,(INDEX('Pro Forma'!$D$26:$M$26,Assumptions!$H$15)+INDEX('Pro Forma'!$D$9:$M$9,Assumptions!$H$15)*(((1+Assumptions!$H$16+$O13)/(1+Assumptions!$H$16))^Assumptions!$H$15-1))/IF((Assumptions!$C$22+$P13)=0,1,Assumptions!$C$22+$P13)*(1-Assumptions!$C$23)-INDEX('Debt Schedule'!$C$8:$L$8,Assumptions!$H$15)-INDEX('Debt Schedule'!$C$19:$L$19,Assumptions!$H$15),0))} -> 0 | ... M13: {=IF(M$2>Assumptions!$H$15,0,(INDEX('Pro Forma'!$D$26:$M$26,M$2)+INDEX('Pro Forma'!$D$9:$M$9,M$2)*(((1+Assumptions!$H$16+$O13)/(1+Assumptions!$H$16))^M$2-1))-IF(Assumptions!$C$37=1,Assumptions!$C$68,IF(Assumptions!$C$37=2,Assumptions!$C$69,IF(M$2<=Assumptions!$C$41,Assumptions!$C$68,Assumptions!$C$69)))-Assumptions!$C$58-IF(Assumptions!$C$28=1,IF(M$2=1,Assumptions!$C$26,0),Assumptions!$C$26/Assumptions!$H$15)-Assumptions!$C$33+IF(M$2=Assumptions!$H$15,(INDEX('Pro Forma'!$D$26:$M$26,Assumptions!$H$15)+INDEX('Pro Forma'!$D$9:$M$9,Assumptions!$H$15)*(((1+Assumptions!$H$16+$O13)/(1+Assumptions!$H$16))^Assumptions!$H$15-1))/IF((Assumptions!$C$22+$P13)=0,1,Assumptions!$C$22+$P13)*(1-Assumptions!$C$23)-INDEX('Debt Schedule'!$C$8:$L$8,Assumptions!$H$15)-INDEX('Debt Schedule'!$C$19:$L$19,Assumptions!$H$15),0))} -> 0 | N13: =IFERROR(IRR(C13:M13),0) -> 0 | O13: =(MOD(ROW()-3,5)-2)*0.005 -> -0.01 | P13: =(INT((ROW()-3)/5)-2)*0.0025 -> 0
C14: =-Assumptions!$C$70 -> 0 | D14: {=IF(D$2>Assumptions!$H$15,0,(INDEX('Pro Forma'!$D$26:$M$26,D$2)+INDEX('Pro Forma'!$D$9:$M$9,D$2)*(((1+Assumptions!$H$16+$O14)/(1+Assumptions!$H$16))^D$2-1))-IF(Assumptions!$C$37=1,Assumptions!$C$68,IF(Assumptions!$C$37=2,Assumptions!$C$69,IF(D$2<=Assumptions!$C$41,Assumptions!$C$68,Assumptions!$C$69)))-Assumptions!$C$58-IF(Assumptions!$C$28=1,IF(D$2=1,Assumptions!$C$26,0),Assumptions!$C$26/Assumptions!$H$15)-Assumptions!$C$33+IF(D$2=Assumptions!$H$15,(INDEX('Pro Forma'!$D$26:$M$26,Assumptions!$H$15)+INDEX('Pro Forma'!$D$9:$M$9,Assumptions!$H$15)*(((1+Assumptions!$H$16+$O14)/(1+Assumptions!$H$16))^Assumptions!$H$15-1))/IF((Assumptions!$C$22+$P14)=0,1,Assumptions!$C$22+$P14)*(1-Assumptions!$C$23)-INDEX('Debt Schedule'!$C$8:$L$8,Assumptions!$H$15)-INDEX('Debt Schedule'!$C$19:$L$19,Assumptions!$H$15),0))} -> 0 | E14: {=IF(E$2>Assumptions!$H$15,0,(INDEX('Pro Forma'!$D$26:$M$26,E$2)+INDEX('Pro Forma'!$D$9:$M$9,E$2)*(((1+Assumptions!$H$16+$O14)/(1+Assumptions!$H$16))^E$2-1))-IF(Assumptions!$C$37=1,Assumptions!$C$68,IF(Assumptions!$C$37=2,Assumptions!$C$69,IF(E$2<=Assumptions!$C$41,Assumptions!$C$68,Assumptions!$C$69)))-Assumptions!$C$58-IF(Assumptions!$C$28=1,IF(E$2=1,Assumptions!$C$26,0),Assumptions!$C$26/Assumptions!$H$15)-Assumptions!$C$33+IF(E$2=Assumptions!$H$15,(INDEX('Pro Forma'!$D$26:$M$26,Assumptions!$H$15)+INDEX('Pro Forma'!$D$9:$M$9,Assumptions!$H$15)*(((1+Assumptions!$H$16+$O14)/(1+Assumptions!$H$16))^Assumptions!$H$15-1))/IF((Assumptions!$C$22+$P14)=0,1,Assumptions!$C$22+$P14)*(1-Assumptions!$C$23)-INDEX('Debt Schedule'!$C$8:$L$8,Assumptions!$H$15)-INDEX('Debt Schedule'!$C$19:$L$19,Assumptions!$H$15),0))} -> 0 | F14: {=IF(F$2>Assumptions!$H$15,0,(INDEX('Pro Forma'!$D$26:$M$26,F$2)+INDEX('Pro Forma'!$D$9:$M$9,F$2)*(((1+Assumptions!$H$16+$O14)/(1+Assumptions!$H$16))^F$2-1))-IF(Assumptions!$C$37=1,Assumptions!$C$68,IF(Assumptions!$C$37=2,Assumptions!$C$69,IF(F$2<=Assumptions!$C$41,Assumptions!$C$68,Assumptions!$C$69)))-Assumptions!$C$58-IF(Assumptions!$C$28=1,IF(F$2=1,Assumptions!$C$26,0),Assumptions!$C$26/Assumptions!$H$15)-Assumptions!$C$33+IF(F$2=Assumptions!$H$15,(INDEX('Pro Forma'!$D$26:$M$26,Assumptions!$H$15)+INDEX('Pro Forma'!$D$9:$M$9,Assumptions!$H$15)*(((1+Assumptions!$H$16+$O14)/(1+Assumptions!$H$16))^Assumptions!$H$15-1))/IF((Assumptions!$C$22+$P14)=0,1,Assumptions!$C$22+$P14)*(1-Assumptions!$C$23)-INDEX('Debt Schedule'!$C$8:$L$8,Assumptions!$H$15)-INDEX('Debt Schedule'!$C$19:$L$19,Assumptions!$H$15),0))} -> 0 | G14: {=IF(G$2>Assumptions!$H$15,0,(INDEX('Pro Forma'!$D$26:$M$26,G$2)+INDEX('Pro Forma'!$D$9:$M$9,G$2)*(((1+Assumptions!$H$16+$O14)/(1+Assumptions!$H$16))^G$2-1))-IF(Assumptions!$C$37=1,Assumptions!$C$68,IF(Assumptions!$C$37=2,Assumptions!$C$69,IF(G$2<=Assumptions!$C$41,Assumptions!$C$68,Assumptions!$C$69)))-Assumptions!$C$58-IF(Assumptions!$C$28=1,IF(G$2=1,Assumptions!$C$26,0),Assumptions!$C$26/Assumptions!$H$15)-Assumptions!$C$33+IF(G$2=Assumptions!$H$15,(INDEX('Pro Forma'!$D$26:$M$26,Assumptions!$H$15)+INDEX('Pro Forma'!$D$9:$M$9,Assumptions!$H$15)*(((1+Assumptions!$H$16+$O14)/(1+Assumptions!$H$16))^Assumptions!$H$15-1))/IF((Assumptions!$C$22+$P14)=0,1,Assumptions!$C$22+$P14)*(1-Assumptions!$C$23)-INDEX('Debt Schedule'!$C$8:$L$8,Assumptions!$H$15)-INDEX('Debt Schedule'!$C$19:$L$19,Assumptions!$H$15),0))} -> 0 | H14: {=IF(H$2>Assumptions!$H$15,0,(INDEX('Pro Forma'!$D$26:$M$26,H$2)+INDEX('Pro Forma'!$D$9:$M$9,H$2)*(((1+Assumptions!$H$16+$O14)/(1+Assumptions!$H$16))^H$2-1))-IF(Assumptions!$C$37=1,Assumptions!$C$68,IF(Assumptions!$C$37=2,Assumptions!$C$69,IF(H$2<=Assumptions!$C$41,Assumptions!$C$68,Assumptions!$C$69)))-Assumptions!$C$58-IF(Assumptions!$C$28=1,IF(H$2=1,Assumptions!$C$26,0),Assumptions!$C$26/Assumptions!$H$15)-Assumptions!$C$33+IF(H$2=Assumptions!$H$15,(INDEX('Pro Forma'!$D$26:$M$26,Assumptions!$H$15)+INDEX('Pro Forma'!$D$9:$M$9,Assumptions!$H$15)*(((1+Assumptions!$H$16+$O14)/(1+Assumptions!$H$16))^Assumptions!$H$15-1))/IF((Assumptions!$C$22+$P14)=0,1,Assumptions!$C$22+$P14)*(1-Assumptions!$C$23)-INDEX('Debt Schedule'!$C$8:$L$8,Assumptions!$H$15)-INDEX('Debt Schedule'!$C$19:$L$19,Assumptions!$H$15),0))} -> 0 | I14: {=IF(I$2>Assumptions!$H$15,0,(INDEX('Pro Forma'!$D$26:$M$26,I$2)+INDEX('Pro Forma'!$D$9:$M$9,I$2)*(((1+Assumptions!$H$16+$O14)/(1+Assumptions!$H$16))^I$2-1))-IF(Assumptions!$C$37=1,Assumptions!$C$68,IF(Assumptions!$C$37=2,Assumptions!$C$69,IF(I$2<=Assumptions!$C$41,Assumptions!$C$68,Assumptions!$C$69)))-Assumptions!$C$58-IF(Assumptions!$C$28=1,IF(I$2=1,Assumptions!$C$26,0),Assumptions!$C$26/Assumptions!$H$15)-Assumptions!$C$33+IF(I$2=Assumptions!$H$15,(INDEX('Pro Forma'!$D$26:$M$26,Assumptions!$H$15)+INDEX('Pro Forma'!$D$9:$M$9,Assumptions!$H$15)*(((1+Assumptions!$H$16+$O14)/(1+Assumptions!$H$16))^Assumptions!$H$15-1))/IF((Assumptions!$C$22+$P14)=0,1,Assumptions!$C$22+$P14)*(1-Assumptions!$C$23)-INDEX('Debt Schedule'!$C$8:$L$8,Assumptions!$H$15)-INDEX('Debt Schedule'!$C$19:$L$19,Assumptions!$H$15),0))} -> 0 | J14: {=IF(J$2>Assumptions!$H$15,0,(INDEX('Pro Forma'!$D$26:$M$26,J$2)+INDEX('Pro Forma'!$D$9:$M$9,J$2)*(((1+Assumptions!$H$16+$O14)/(1+Assumptions!$H$16))^J$2-1))-IF(Assumptions!$C$37=1,Assumptions!$C$68,IF(Assumptions!$C$37=2,Assumptions!$C$69,IF(J$2<=Assumptions!$C$41,Assumptions!$C$68,Assumptions!$C$69)))-Assumptions!$C$58-IF(Assumptions!$C$28=1,IF(J$2=1,Assumptions!$C$26,0),Assumptions!$C$26/Assumptions!$H$15)-Assumptions!$C$33+IF(J$2=Assumptions!$H$15,(INDEX('Pro Forma'!$D$26:$M$26,Assumptions!$H$15)+INDEX('Pro Forma'!$D$9:$M$9,Assumptions!$H$15)*(((1+Assumptions!$H$16+$O14)/(1+Assumptions!$H$16))^Assumptions!$H$15-1))/IF((Assumptions!$C$22+$P14)=0,1,Assumptions!$C$22+$P14)*(1-Assumptions!$C$23)-INDEX('Debt Schedule'!$C$8:$L$8,Assumptions!$H$15)-INDEX('Debt Schedule'!$C$19:$L$19,Assumptions!$H$15),0))} -> 0 | K14: {=IF(K$2>Assumptions!$H$15,0,(INDEX('Pro Forma'!$D$26:$M$26,K$2)+INDEX('Pro Forma'!$D$9:$M$9,K$2)*(((1+Assumptions!$H$16+$O14)/(1+Assumptions!$H$16))^K$2-1))-IF(Assumptions!$C$37=1,Assumptions!$C$68,IF(Assumptions!$C$37=2,Assumptions!$C$69,IF(K$2<=Assumptions!$C$41,Assumptions!$C$68,Assumptions!$C$69)))-Assumptions!$C$58-IF(Assumptions!$C$28=1,IF(K$2=1,Assumptions!$C$26,0),Assumptions!$C$26/Assumptions!$H$15)-Assumptions!$C$33+IF(K$2=Assumptions!$H$15,(INDEX('Pro Forma'!$D$26:$M$26,Assumptions!$H$15)+INDEX('Pro Forma'!$D$9:$M$9,Assumptions!$H$15)*(((1+Assumptions!$H$16+$O14)/(1+Assumptions!$H$16))^Assumptions!$H$15-1))/IF((Assumptions!$C$22+$P14)=0,1,Assumptions!$C$22+$P14)*(1-Assumptions!$C$23)-INDEX('Debt Schedule'!$C$8:$L$8,Assumptions!$H$15)-INDEX('Debt Schedule'!$C$19:$L$19,Assumptions!$H$15),0))} -> 0 | ... M14: {=IF(M$2>Assumptions!$H$15,0,(INDEX('Pro Forma'!$D$26:$M$26,M$2)+INDEX('Pro Forma'!$D$9:$M$9,M$2)*(((1+Assumptions!$H$16+$O14)/(1+Assumptions!$H$16))^M$2-1))-IF(Assumptions!$C$37=1,Assumptions!$C$68,IF(Assumptions!$C$37=2,Assumptions!$C$69,IF(M$2<=Assumptions!$C$41,Assumptions!$C$68,Assumptions!$C$69)))-Assumptions!$C$58-IF(Assumptions!$C$28=1,IF(M$2=1,Assumptions!$C$26,0),Assumptions!$C$26/Assumptions!$H$15)-Assumptions!$C$33+IF(M$2=Assumptions!$H$15,(INDEX('Pro Forma'!$D$26:$M$26,Assumptions!$H$15)+INDEX('Pro Forma'!$D$9:$M$9,Assumptions!$H$15)*(((1+Assumptions!$H$16+$O14)/(1+Assumptions!$H$16))^Assumptions!$H$15-1))/IF((Assumptions!$C$22+$P14)=0,1,Assumptions!$C$22+$P14)*(1-Assumptions!$C$23)-INDEX('Debt Schedule'!$C$8:$L$8,Assumptions!$H$15)-INDEX('Debt Schedule'!$C$19:$L$19,Assumptions!$H$15),0))} -> 0 | N14: =IFERROR(IRR(C14:M14),0) -> 0 | O14: =(MOD(ROW()-3,5)-2)*0.005 -> -0.005 | P14: =(INT((ROW()-3)/5)-2)*0.0025 -> 0
... C27: =-Assumptions!$C$70 -> 0 | D27: {=IF(D$2>Assumptions!$H$15,0,(INDEX('Pro Forma'!$D$26:$M$26,D$2)+INDEX('Pro Forma'!$D$9:$M$9,D$2)*(((1+Assumptions!$H$16+$O27)/(1+Assumptions!$H$16))^D$2-1))-IF(Assumptions!$C$37=1,Assumptions!$C$68,IF(Assumptions!$C$37=2,Assumptions!$C$69,IF(D$2<=Assumptions!$C$41,Assumptions!$C$68,Assumptions!$C$69)))-Assumptions!$C$58-IF(Assumptions!$C$28=1,IF(D$2=1,Assumptions!$C$26,0),Assumptions!$C$26/Assumptions!$H$15)-Assumptions!$C$33+IF(D$2=Assumptions!$H$15,(INDEX('Pro Forma'!$D$26:$M$26,Assumptions!$H$15)+INDEX('Pro Forma'!$D$9:$M$9,Assumptions!$H$15)*(((1+Assumptions!$H$16+$O27)/(1+Assumptions!$H$16))^Assumptions!$H$15-1))/IF((Assumptions!$C$22+$P27)=0,1,Assumptions!$C$22+$P27)*(1-Assumptions!$C$23)-INDEX('Debt Schedule'!$C$8:$L$8,Assumptions!$H$15)-INDEX('Debt Schedule'!$C$19:$L$19,Assumptions!$H$15),0))} -> 0 | E27: {=IF(E$2>Assumptions!$H$15,0,(INDEX('Pro Forma'!$D$26:$M$26,E$2)+INDEX('Pro Forma'!$D$9:$M$9,E$2)*(((1+Assumptions!$H$16+$O27)/(1+Assumptions!$H$16))^E$2-1))-IF(Assumptions!$C$37=1,Assumptions!$C$68,IF(Assumptions!$C$37=2,Assumptions!$C$69,IF(E$2<=Assumptions!$C$41,Assumptions!$C$68,Assumptions!$C$69)))-Assumptions!$C$58-IF(Assumptions!$C$28=1,IF(E$2=1,Assumptions!$C$26,0),Assumptions!$C$26/Assumptions!$H$15)-Assumptions!$C$33+IF(E$2=Assumptions!$H$15,(INDEX('Pro Forma'!$D$26:$M$26,Assumptions!$H$15)+INDEX('Pro Forma'!$D$9:$M$9,Assumptions!$H$15)*(((1+Assumptions!$H$16+$O27)/(1+Assumptions!$H$16))^Assumptions!$H$15-1))/IF((Assumptions!$C$22+$P27)=0,1,Assumptions!$C$22+$P27)*(1-Assumptions!$C$23)-INDEX('Debt Schedule'!$C$8:$L$8,Assumptions!$H$15)-INDEX('Debt Schedule'!$C$19:$L$19,Assumptions!$H$15),0))} -> 0 | F27: {=IF(F$2>Assumptions!$H$15,0,(INDEX('Pro Forma'!$D$26:$M$26,F$2)+INDEX('Pro Forma'!$D$9:$M$9,F$2)*(((1+Assumptions!$H$16+$O27)/(1+Assumptions!$H$16))^F$2-1))-IF(Assumptions!$C$37=1,Assumptions!$C$68,IF(Assumptions!$C$37=2,Assumptions!$C$69,IF(F$2<=Assumptions!$C$41,Assumptions!$C$68,Assumptions!$C$69)))-Assumptions!$C$58-IF(Assumptions!$C$28=1,IF(F$2=1,Assumptions!$C$26,0),Assumptions!$C$26/Assumptions!$H$15)-Assumptions!$C$33+IF(F$2=Assumptions!$H$15,(INDEX('Pro Forma'!$D$26:$M$26,Assumptions!$H$15)+INDEX('Pro Forma'!$D$9:$M$9,Assumptions!$H$15)*(((1+Assumptions!$H$16+$O27)/(1+Assumptions!$H$16))^Assumptions!$H$15-1))/IF((Assumptions!$C$22+$P27)=0,1,Assumptions!$C$22+$P27)*(1-Assumptions!$C$23)-INDEX('Debt Schedule'!$C$8:$L$8,Assumptions!$H$15)-INDEX('Debt Schedule'!$C$19:$L$19,Assumptions!$H$15),0))} -> 0 | G27: {=IF(G$2>Assumptions!$H$15,0,(INDEX('Pro Forma'!$D$26:$M$26,G$2)+INDEX('Pro Forma'!$D$9:$M$9,G$2)*(((1+Assumptions!$H$16+$O27)/(1+Assumptions!$H$16))^G$2-1))-IF(Assumptions!$C$37=1,Assumptions!$C$68,IF(Assumptions!$C$37=2,Assumptions!$C$69,IF(G$2<=Assumptions!$C$41,Assumptions!$C$68,Assumptions!$C$69)))-Assumptions!$C$58-IF(Assumptions!$C$28=1,IF(G$2=1,Assumptions!$C$26,0),Assumptions!$C$26/Assumptions!$H$15)-Assumptions!$C$33+IF(G$2=Assumptions!$H$15,(INDEX('Pro Forma'!$D$26:$M$26,Assumptions!$H$15)+INDEX('Pro Forma'!$D$9:$M$9,Assumptions!$H$15)*(((1+Assumptions!$H$16+$O27)/(1+Assumptions!$H$16))^Assumptions!$H$15-1))/IF((Assumptions!$C$22+$P27)=0,1,Assumptions!$C$22+$P27)*(1-Assumptions!$C$23)-INDEX('Debt Schedule'!$C$8:$L$8,Assumptions!$H$15)-INDEX('Debt Schedule'!$C$19:$L$19,Assumptions!$H$15),0))} -> 0 | H27: {=IF(H$2>Assumptions!$H$15,0,(INDEX('Pro Forma'!$D$26:$M$26,H$2)+INDEX('Pro Forma'!$D$9:$M$9,H$2)*(((1+Assumptions!$H$16+$O27)/(1+Assumptions!$H$16))^H$2-1))-IF(Assumptions!$C$37=1,Assumptions!$C$68,IF(Assumptions!$C$37=2,Assumptions!$C$69,IF(H$2<=Assumptions!$C$41,Assumptions!$C$68,Assumptions!$C$69)))-Assumptions!$C$58-IF(Assumptions!$C$28=1,IF(H$2=1,Assumptions!$C$26,0),Assumptions!$C$26/Assumptions!$H$15)-Assumptions!$C$33+IF(H$2=Assumptions!$H$15,(INDEX('Pro Forma'!$D$26:$M$26,Assumptions!$H$15)+INDEX('Pro Forma'!$D$9:$M$9,Assumptions!$H$15)*(((1+Assumptions!$H$16+$O27)/(1+Assumptions!$H$16))^Assumptions!$H$15-1))/IF((Assumptions!$C$22+$P27)=0,1,Assumptions!$C$22+$P27)*(1-Assumptions!$C$23)-INDEX('Debt Schedule'!$C$8:$L$8,Assumptions!$H$15)-INDEX('Debt Schedule'!$C$19:$L$19,Assumptions!$H$15),0))} -> 0 | I27: {=IF(I$2>Assumptions!$H$15,0,(INDEX('Pro Forma'!$D$26:$M$26,I$2)+INDEX('Pro Forma'!$D$9:$M$9,I$2)*(((1+Assumptions!$H$16+$O27)/(1+Assumptions!$H$16))^I$2-1))-IF(Assumptions!$C$37=1,Assumptions!$C$68,IF(Assumptions!$C$37=2,Assumptions!$C$69,IF(I$2<=Assumptions!$C$41,Assumptions!$C$68,Assumptions!$C$69)))-Assumptions!$C$58-IF(Assumptions!$C$28=1,IF(I$2=1,Assumptions!$C$26,0),Assumptions!$C$26/Assumptions!$H$15)-Assumptions!$C$33+IF(I$2=Assumptions!$H$15,(INDEX('Pro Forma'!$D$26:$M$26,Assumptions!$H$15)+INDEX('Pro Forma'!$D$9:$M$9,Assumptions!$H$15)*(((1+Assumptions!$H$16+$O27)/(1+Assumptions!$H$16))^Assumptions!$H$15-1))/IF((Assumptions!$C$22+$P27)=0,1,Assumptions!$C$22+$P27)*(1-Assumptions!$C$23)-INDEX('Debt Schedule'!$C$8:$L$8,Assumptions!$H$15)-INDEX('Debt Schedule'!$C$19:$L$19,Assumptions!$H$15),0))} -> 0 | J27: {=IF(J$2>Assumptions!$H$15,0,(INDEX('Pro Forma'!$D$26:$M$26,J$2)+INDEX('Pro Forma'!$D$9:$M$9,J$2)*(((1+Assumptions!$H$16+$O27)/(1+Assumptions!$H$16))^J$2-1))-IF(Assumptions!$C$37=1,Assumptions!$C$68,IF(Assumptions!$C$37=2,Assumptions!$C$69,IF(J$2<=Assumptions!$C$41,Assumptions!$C$68,Assumptions!$C$69)))-Assumptions!$C$58-IF(Assumptions!$C$28=1,IF(J$2=1,Assumptions!$C$26,0),Assumptions!$C$26/Assumptions!$H$15)-Assumptions!$C$33+IF(J$2=Assumptions!$H$15,(INDEX('Pro Forma'!$D$26:$M$26,Assumptions!$H$15)+INDEX('Pro Forma'!$D$9:$M$9,Assumptions!$H$15)*(((1+Assumptions!$H$16+$O27)/(1+Assumptions!$H$16))^Assumptions!$H$15-1))/IF((Assumptions!$C$22+$P27)=0,1,Assumptions!$C$22+$P27)*(1-Assumptions!$C$23)-INDEX('Debt Schedule'!$C$8:$L$8,Assumptions!$H$15)-INDEX('Debt Schedule'!$C$19:$L$19,Assumptions!$H$15),0))} -> 0 | K27: {=IF(K$2>Assumptions!$H$15,0,(INDEX('Pro Forma'!$D$26:$M$26,K$2)+INDEX('Pro Forma'!$D$9:$M$9,K$2)*(((1+Assumptions!$H$16+$O27)/(1+Assumptions!$H$16))^K$2-1))-IF(Assumptions!$C$37=1,Assumptions!$C$68,IF(Assumptions!$C$37=2,Assumptions!$C$69,IF(K$2<=Assumptions!$C$41,Assumptions!$C$68,Assumptions!$C$69)))-Assumptions!$C$58-IF(Assumptions!$C$28=1,IF(K$2=1,Assumptions!$C$26,0),Assumptions!$C$26/Assumptions!$H$15)-Assumptions!$C$33+IF(K$2=Assumptions!$H$15,(INDEX('Pro Forma'!$D$26:$M$26,Assumptions!$H$15)+INDEX('Pro Forma'!$D$9:$M$9,Assumptions!$H$15)*(((1+Assumptions!$H$16+$O27)/(1+Assumptions!$H$16))^Assumptions!$H$15-1))/IF((Assumptions!$C$22+$P27)=0,1,Assumptions!$C$22+$P27)*(1-Assumptions!$C$23)-INDEX('Debt Schedule'!$C$8:$L$8,Assumptions!$H$15)-INDEX('Debt Schedule'!$C$19:$L$19,Assumptions!$H$15),0))} -> 0 | ... M27: {=IF(M$2>Assumptions!$H$15,0,(INDEX('Pro Forma'!$D$26:$M$26,M$2)+INDEX('Pro Forma'!$D$9:$M$9,M$2)*(((1+Assumptions!$H$16+$O27)/(1+Assumptions!$H$16))^M$2-1))-IF(Assumptions!$C$37=1,Assumptions!$C$68,IF(Assumptions!$C$37=2,Assumptions!$C$69,IF(M$2<=Assumptions!$C$41,Assumptions!$C$68,Assumptions!$C$69)))-Assumptions!$C$58-IF(Assumptions!$C$28=1,IF(M$2=1,Assumptions!$C$26,0),Assumptions!$C$26/Assumptions!$H$15)-Assumptions!$C$33+IF(M$2=Assumptions!$H$15,(INDEX('Pro Forma'!$D$26:$M$26,Assumptions!$H$15)+INDEX('Pro Forma'!$D$9:$M$9,Assumptions!$H$15)*(((1+Assumptions!$H$16+$O27)/(1+Assumptions!$H$16))^Assumptions!$H$15-1))/IF((Assumptions!$C$22+$P27)=0,1,Assumptions!$C$22+$P27)*(1-Assumptions!$C$23)-INDEX('Debt Schedule'!$C$8:$L$8,Assumptions!$H$15)-INDEX('Debt Schedule'!$C$19:$L$19,Assumptions!$H$15),0))} -> 0 | N27: =IFERROR(IRR(C27:M27),0) -> 0 | O27: =(MOD(ROW()-3,5)-2)*0.005 -> 0.01 | P27: =(INT((ROW()-3)/5)-2)*0.0025 -> 0.005
A30: =IF(-C3=0,0,SUM(D3:M3)/(-C3)) -> 0
A31: =IF(-C4=0,0,SUM(D4:M4)/(-C4)) -> 0
A32: =IF(-C5=0,0,SUM(D5:M5)/(-C5)) -> 0
A33: =IF(-C6=0,0,SUM(D6:M6)/(-C6)) -> 0
A34: =IF(-C7=0,0,SUM(D7:M7)/(-C7)) -> 0
A35: =IF(-C8=0,0,SUM(D8:M8)/(-C8)) -> 0
A36: =IF(-C9=0,0,SUM(D9:M9)/(-C9)) -> 0
A37: =IF(-C10=0,0,SUM(D10:M10)/(-C10)) -> 0
A38: =IF(-C11=0,0,SUM(D11:M11)/(-C11)) -> 0
A39: =IF(-C12=0,0,SUM(D12:M12)/(-C12)) -> 0
A40: =IF(-C13=0,0,SUM(D13:M13)/(-C13)) -> 0
A41: =IF(-C14=0,0,SUM(D14:M14)/(-C14)) -> 0
... A54: =IF(-C27=0,0,SUM(D27:M27)/(-C27)) -> 0
